Workbook
Name _174_CrPC: Droplist!$W$2:$W$10
Name Act_Type: Droplist!$E$1:$E$9
Name Bodily_Offiences: Droplist!$K$2:$K$10
Name Classification: Droplist!$G$1:$G$17
Name Crime__Against_Women: Droplist!$L$2:$L$10
Name Enforcement: Droplist!$S$2:$S$10
Name GravityType: Droplist!$C$1:$C$3
Name Missing_Cases: Droplist!$V$2:$V$10
Name NDPS: Droplist!$T$2:$T$10
Name Other_CrPC: Droplist!$Y$2:$Y$10
Name Other_IPC: Droplist!$R$2:$R$10
Name Others: Droplist!$Z$2:$Z$10
Name POCSO_Cases: Droplist!$M$2:$M$10
Name Property_Offences: Droplist!$N$2:$N$10
Name Reasons: #REF!
Name Road_Accidents: Droplist!$P$2:$P$10
Name SC_ST_Cases: Droplist!$O$2:$O$10
Name Security_Cases: Droplist!$X$2:$X$10
Name SLL: Droplist!$U$2:$U$10
Name Total: Droplist!$J$2:$J$10
Name White_Collar_Offences: Droplist!$Q$2:$Q$10

Sheet Total
A1: S.No. | B1: Sub-Division | C1: Cirlce | D1: I.O Name | E1: Police Station | F1: FIR NO | G1: ACTS & SEC | H1: FIR DT | I1: Month | J1: Year | K1: Crime Head | L1: Sub-Head | M1: Crime Classfication | N1: Act Type | O1: Gravity Type | P1: Date of charge | Q1: Return of Charge Sheet | R1: Resubmit charge sheet | S1: Stage | T1: Court Disposal | U1: Date of Police Disposal | V1: Type of Disposal | W1: Old Reason for UI | X1: Reason for UI | Y1: Reason Wise Date | Z1: Brief | AA1: TOTAL | AB1: No. of Days | AC1: Time Line | AD1: Number Pending No of days | AE1: Time Line | AF1: Sheet Holder | AG1: Merge PS Names | AH1: Time Line Actual UI Cases
A2: 1 | B2: Tekkali Sub-Division | C2: Kothuru Circle | E2: Hiramandalam | F2: '14/2016' | G2: 147, 148, 341, 342, 353, 323, 427, 435, r.w 149 IPC | H2: 42428 | I2: Feb | J2: 2016 | K2: Rioting (Unlawful Assembly) | M2: Bodily Offiences | N2: IPC | O2: Non-Grave | S2: UI | W2: For Arrest of Accused | X2: For Arrest of Accused | Z2: Occurred on 28.02.2016 at 12.00 hrs at spiil way, spill channel, earth dam at BRR Vamsadhara Reservoir, Hiramandalam village and reported on the same day at 15.00 hrs by the complainant Sri J. Srinivasa Rao, Inspector of Police, Pathapatnam Circle, wherein the accused 1. Korada Narayana Rao, District Agricultural labour union president and 14 others and some other Rehabilitees came as unlaw ful assembly along with deadly weapons like Sticks and iron rods and obstructed the BRR Project works, surrounded, beat with hands the J.Ramarao, Tahsildar, Hiramandalam and fell down. While complaint his staff saved the Tahsildar, Hiramandalam from the hands accused. Then they damaged plastic chairs, set fire to tents. Also beat the Konari Simhachalam, while trying to stop. Hence issued report by gi | AA2: Total | AB2: =IF(S2="UI",DATEDIF(H2,TODAY(),"D"),"") -> 3883 | AC2: =IF(S2="UI",IF(AB2>365,"Above 1 Year",IF(AND(AB2<=365,AB2>180),"Above 6 Months",IF(AND(AB2<=180,AB2>90),"Above 3 Months",IF(AND(AB2<=90,AB2>60),"Above 60 Days",IF(AND(AB2<=60,AB2>45),"45 to 60 Days","Below 45 Days"))))),"") -> Above 1 Year | AD2: =IF(Y2<>"",DATEDIF(Y2,TODAY(),"D"),"") | AE2: =IF(AD2<>"",IF(AD2>365,"Above 1 Year",IF(AND(AD2<=365,AD2>180),"Above 6 Months",IF(AND(AD2<=180,AD2>90),"Above 3 Months",IF(AND(AD2<=90,AD2>60),"Above 60 Days",IF(AND(AD2<=60,AD2>45),"45 to 60 Days","Below 45 Days"))))),"") | AF2: D-6(Bodily) | AG2: Hiramandalam,'14/2016' | AH2: =IF(X2="SC/PRC/CC No. Awaited","",AC2) -> Above 1 Year
A3: 2 | B3: Tekkali Sub-Division | C3: Narasannapeta Circle | E3: Narasannapeta | F3: '67/2016' | G3: 403,409,420 IPC | H3: 42504 | I3: May | J3: 2016 | K3: Criminial Misappropriation | M3: White Collar Offences | N3: IPC | O3: Non-Grave | P3: 42936 | S3: UI | W3: SC/PRC/CC No. Awaited | X3: SC/PRC/CC No. Awaited | Y3: 42936 | Z3: THIS IS A CASE OF MISAPPROPRIATION. IN 2010 TO 2011 FERTILIZERS ARE MISAPPROPRIATION INPRIMARY AGRICULTURAL SOCIETY THROUGHT THE PADALA NAGESWARARAO, HE IS WORKING AS A SECRETORY. THE TOTAL AMOUNT OF MISAPPROPRIATION IS 1,10,000/-. | AA3: Total | AB3: =IF(S3="UI",DATEDIF(H3,TODAY(),"D"),"") -> 3807 | AC3: =IF(S3="UI",IF(AB3>365,"Above 1 Year",IF(AND(AB3<=365,AB3>180),"Above 6 Months",IF(AND(AB3<=180,AB3>90),"Above 3 Months",IF(AND(AB3<=90,AB3>60),"Above 60 Days",IF(AND(AB3<=60,AB3>45),"45 to 60 Days","Below 45 Days"))))),"") -> Above 1 Year | AD3: =IF(Y3<>"",DATEDIF(Y3,TODAY(),"D"),"") -> 3375 | AE3: =IF(AD3<>"",IF(AD3>365,"Above 1 Year",IF(AND(AD3<=365,AD3>180),"Above 6 Months",IF(AND(AD3<=180,AD3>90),"Above 3 Months",IF(AND(AD3<=90,AD3>60),"Above 60 Days",IF(AND(AD3<=60,AD3>45),"45 to 60 Days","Below 45 Days"))))),"") -> Above 1 Year | AF3: D-6(White collar) | AG3: Narasannapeta,'67/2016' | AH3: =IF(X3="SC/PRC/CC No. Awaited","",AC3)
A4: 3 | B4: Tekkali Sub-Division | C4: 0 | E4: Tekkali PS | F4: '44/2017' | G4: 420,403,406 IPC | H4: 42816 | I4: Mar | J4: 2017 | K4: Criminial Misappropriation | M4: White Collar Offences | N4: IPC | O4: Non-Grave | P4: 42949 | S4: UI | W4: SC/PRC/CC No. Awaited | X4: SC/PRC/CC No. Awaited | Y4: 42949 | Z4: The complainant M. Thyagaraja, Asst. Manager (General), O/o District Manager, A.P.S.C.S.C.L., Srikakulam reported that during KMS 2016-17, a quantity of 798.920 Mts of paddy has been issued to the accused Ratnala Prasada Rao, S/o. late Venkata Rao, Proprietor, M/S RVR Enterprises, C/o. Krisna MRM, Tekkali. The miller has to deliver a quantity of 535.276 MTs of custom milled rice to APSCSCL towards resultant rice @ 67%. On review of CMR deliveries by the Rice millers in the district, it is observed that the accused has not delivered single grain towards custom milled rice against KMS 2016-17. On 21.3.2017 when the complainant surprisely visited the mill of the accused then the complainant found out of the 798.920 MTs of paddy issued for custom milling, only 81.600 MTS of paddy is availab | AA4: Total | AB4: =IF(S4="UI",DATEDIF(H4,TODAY(),"D"),"") -> 3495 | AC4: =IF(S4="UI",IF(AB4>365,"Above 1 Year",IF(AND(AB4<=365,AB4>180),"Above 6 Months",IF(AND(AB4<=180,AB4>90),"Above 3 Months",IF(AND(AB4<=90,AB4>60),"Above 60 Days",IF(AND(AB4<=60,AB4>45),"45 to 60 Days","Below 45 Days"))))),"") -> Above 1 Year | AD4: =IF(Y4<>"",DATEDIF(Y4,TODAY(),"D"),"") -> 3362 | AE4: =IF(AD4<>"",IF(AD4>365,"Above 1 Year",IF(AND(AD4<=365,AD4>180),"Above 6 Months",IF(AND(AD4<=180,AD4>90),"Above 3 Months",IF(AND(AD4<=90,AD4>60),"Above 60 Days",IF(AND(AD4<=60,AD4>45),"45 to 60 Days","Below 45 Days"))))),"") -> Above 1 Year | AF4: D-6(White collar) | AG4: Tekkali PS,'44/2017' | AH4: =IF(X4="SC/PRC/CC No. Awaited","",AC4)
A5: 4 | B5: Tekkali Sub-Division | C5: Kothuru Circle | E5: Hiramandalam | F5: '54/2017' | G5: 148,147,353,506 r/w 149 IPC, 7 CLA-1932 | H5: 42957 | I5: Aug | J5: 2017 | K5: Rioting (Unlawful Assembly) | M5: Bodily Offiences | N5: IPC | O5: Non-Grave | S5: UI | W5: For Arrest of Accused | X5: For Arrest of Accused | Z5: The Complainant Report Copy was Enclosed herewith Uploaded for the favour of Perusal. 1) Gavara Govinda Rao, s/o lt. Tellanna, 50 years, Kapu, Garlapadu village, Hiramandalam Mandal. 2) Madapana Ganapathi Rao S/o Laxminarayana, age 38 yrs, Kapu, Garlapadu village, Hiramandalam Mandal. 3) Agathamudi Jayamma, w/o Balanaidu, 50 yrs, Kapu, Garlapadu village, Hiramandalam Mandal. 4) Gedela laxmi, w/o lt. Gaddem Naidu, 30 yrs, Kapu, Garlapadu village, Hiramandalam Mandal. 5) Buri Krishnaveni, w/o Seshagiri, 30 years, Kapu, Garlapadu village,Hiramandalam Mandal. 6)Madapana Appa Rao, s/o Mukhalingam, 50 years, Kapu, Garlapadu village, Hiramandalam Mandal. 7) Vanjarapu. Rama Rao, s/o lt. Appanna, 65 years, Kapu, Garlapadu village, Hiramandalam Mandal. 8) Palli Jagannadha Rao, s/o La | AA5: Total | AB5: =IF(S5="UI",DATEDIF(H5,TODAY(),"D"),"") -> 3354 | AC5: =IF(S5="UI",IF(AB5>365,"Above 1 Year",IF(AND(AB5<=365,AB5>180),"Above 6 Months",IF(AND(AB5<=180,AB5>90),"Above 3 Months",IF(AND(AB5<=90,AB5>60),"Above 60 Days",IF(AND(AB5<=60,AB5>45),"45 to 60 Days","Below 45 Days"))))),"") -> Above 1 Year | AD5: =IF(Y5<>"",DATEDIF(Y5,TODAY(),"D"),"") | AE5: =IF(AD5<>"",IF(AD5>365,"Above 1 Year",IF(AND(AD5<=365,AD5>180),"Above 6 Months",IF(AND(AD5<=180,AD5>90),"Above 3 Months",IF(AND(AD5<=90,AD5>60),"Above 60 Days",IF(AND(AD5<=60,AD5>45),"45 to 60 Days","Below 45 Days"))))),"") | AF5: D-6(Bodily) | AG5: Hiramandalam,'54/2017' | AH5: =IF(X5="SC/PRC/CC No. Awaited","",AC5) -> Above 1 Year
A6: 5 | B6: Tekkali Sub-Division | C6: Kothuru Circle | E6: Hiramandalam | F6: '56/2017' | G6: 147, 148, 353, 506, 188 r.w 149 IPC & Sec.7 (1)(a) of Criminal Law Amendment Act-1932 | H6: 42963 | I6: Aug | J6: 2017 | K6: Rioting (Unlawful Assembly) | M6: Bodily Offiences | N6: IPC | O6: Non-Grave | S6: UI | W6: For Arrest of Accused | X6: For Arrest of Accused | Z6: Occurred on 16.08.2017 at about 11.00 hrs and reported same day at 14.00 hrs by the Complainant Sri.M.Kali Prasad, Tahasildar & Mandal Executive Magistrate of Hiramandalam and stated that at Tulagam fields the Accused about 100 members of displaced villagers of Tulagam, Duggupuram and Padali Villagers were came with supported with Gorle Ram Sankar under along with rehabilitiees were came and taken them with deadly weapons and stowed sticks and raised slogans and told them stop the works of Vamsadhara Reservoir BRR Project and warned immediately stop the works and otherwise we attack workers and vehicles go back and they were obstructing the public servants their legitimate duties and then the complainant reported against the accused persons. | AA6: Total | AB6: =IF(S6="UI",DATEDIF(H6,TODAY(),"D"),"") -> 3348 | AC6: =IF(S6="UI",IF(AB6>365,"Above 1 Year",IF(AND(AB6<=365,AB6>180),"Above 6 Months",IF(AND(AB6<=180,AB6>90),"Above 3 Months",IF(AND(AB6<=90,AB6>60),"Above 60 Days",IF(AND(AB6<=60,AB6>45),"45 to 60 Days","Below 45 Days"))))),"") -> Above 1 Year | AD6: =IF(Y6<>"",DATEDIF(Y6,TODAY(),"D"),"") | AE6: =IF(AD6<>"",IF(AD6>365,"Above 1 Year",IF(AND(AD6<=365,AD6>180),"Above 6 Months",IF(AND(AD6<=180,AD6>90),"Above 3 Months",IF(AND(AD6<=90,AD6>60),"Above 60 Days",IF(AND(AD6<=60,AD6>45),"45 to 60 Days","Below 45 Days"))))),"") | AF6: D-6(Bodily) | AG6: Hiramandalam,'56/2017' | AH6: =IF(X6="SC/PRC/CC No. Awaited","",AC6) -> Above 1 Year
A7: 6 | B7: Tekkali Sub-Division | C7: Kothuru Circle | E7: Hiramandalam | F7: '58/2017' | G7: 147, 148, 341, 332, 353, 506, 188 r.w 149 IPC & Sec.7 (1) (a) Of Criminal Law Amendment Act-1932 | H7: 42963 | I7: Aug | J7: 2017 | K7: Rioting (Unlawful Assembly) | M7: Bodily Offiences | N7: IPC | O7: Non-Grave | S7: UI | W7: For Arrest of Accused | X7: For Arrest of Accused | Z7: Occurred on 16-08-2017 at about 15.10 hrs and reported same day at 18.30 hrs by the Complainant Chamtula Rama Rao S/o.late Tatababu, age 34 yrs, Caste by Kapu, Kintali Village, Madugula Mandal of Visakhapatnam District and worked as Sub-inspector of Police, Laveru Police Station and doing duty at Hiramandalam Police Station limits and Duggupuram to Padali villages beside fields and the Complainant protect the workers of BRR Vamsadhar project mud works in the same time the rehabilitates of Duggpuram and Padali Villagers and came and with stone, deadly weapons and stowed sticks and tried to attacked the Public servants of Police, while they were obstructing the legitimate duties of them and the complainant lodges a report against the accused person of Lothugedda Sundaranarayana and others 46 | AA7: Total | AB7: =IF(S7="UI",DATEDIF(H7,TODAY(),"D"),"") -> 3348 | AC7: =IF(S7="UI",IF(AB7>365,"Above 1 Year",IF(AND(AB7<=365,AB7>180),"Above 6 Months",IF(AND(AB7<=180,AB7>90),"Above 3 Months",IF(AND(AB7<=90,AB7>60),"Above 60 Days",IF(AND(AB7<=60,AB7>45),"45 to 60 Days","Below 45 Days"))))),"") -> Above 1 Year | AD7: =IF(Y7<>"",DATEDIF(Y7,TODAY(),"D"),"") | AE7: =IF(AD7<>"",IF(AD7>365,"Above 1 Year",IF(AND(AD7<=365,AD7>180),"Above 6 Months",IF(AND(AD7<=180,AD7>90),"Above 3 Months",IF(AND(AD7<=90,AD7>60),"Above 60 Days",IF(AND(AD7<=60,AD7>45),"45 to 60 Days","Below 45 Days"))))),"") | AF7: D-6(Bodily) | AG7: Hiramandalam,'58/2017' | AH7: =IF(X7="SC/PRC/CC No. Awaited","",AC7) -> Above 1 Year
A8: 7 | B8: Srikakulam Sub-Division | C8: J.R.Puram Circle | E8: Etcherla | F8: '173/2017' | G8: Man Missing Person | H8: 43000 | I8: Sep | J8: 2017 | K8: Missing Cases | L8: Man Missing | M8: Missing Cases | N8: Missing | O8: Non-Grave | S8: UI | W8: Pending records from other depts., | X8: Pending records from other depts., | Y8: 46030 | Z8: OCCURRED ON 18..09..2017 AT ABOUT 09.00 HOURS AT ALLINAGRAM VILLAGE, ETCHERLA MANDAL, SRIKAKULAM DISTRICT AND REPORTD BY THE COMPLAINANT KILLO CHITTIBABU S/O SHONNU, 25 YEARS, ST GOWDA BY CASTE,MARRIPALEM VILLAGE, PADERU MANDAL, VISAKHAPATNAM DISTRICT IN WHICH IT IS INFORMED THAT ONE KILLO LAKSHMANARAO S/O ADDANNA, 36 YEARS, ST GOWDA BY CASTE, GONDURU VILLAGE, DOKULURU POST, PADEROO MANDAL WHO IS BROTHER OF THE COMPLAINANT AND 4 OTHER ARE CAME TO COOLI WORKS ON 15..08..2017 BHAGIRADHA BORU WELLS WORKS OF DUBBAKULA RAKESH NATIVE OF MURAPAKA VILLAGE, LAVERU MANDAL, SRIKAKULAM DISTRICT.IN THIS REGUARD THEY ARE WORKING BORU WELL WORKS AT ALLINAGARAM VILLAGE FROM 2 DAY WHILE ON 18..09..2017 AT 09.00 HOURS KILLO LAXMANA RAO CON’T DO THIS WORK I AM GOING TO MY HOUSE AND ASKING SOME MONEY FOR C | AA8: Total | AB8: =IF(S8="UI",DATEDIF(H8,TODAY(),"D"),"") -> 3311 | AC8: =IF(S8="UI",IF(AB8>365,"Above 1 Year",IF(AND(AB8<=365,AB8>180),"Above 6 Months",IF(AND(AB8<=180,AB8>90),"Above 3 Months",IF(AND(AB8<=90,AB8>60),"Above 60 Days",IF(AND(AB8<=60,AB8>45),"45 to 60 Days","Below 45 Days"))))),"") -> Above 1 Year | AD8: =IF(Y8<>"",DATEDIF(Y8,TODAY(),"D"),"") -> 281 | AE8: =IF(AD8<>"",IF(AD8>365,"Above 1 Year",IF(AND(AD8<=365,AD8>180),"Above 6 Months",IF(AND(AD8<=180,AD8>90),"Above 3 Months",IF(AND(AD8<=90,AD8>60),"Above 60 Days",IF(AND(AD8<=60,AD8>45),"45 to 60 Days","Below 45 Days"))))),"") -> Above 6 Months | AF8: D-4(Missing) | AG8: Etcherla,'173/2017' | AH8: =IF(X8="SC/PRC/CC No. Awaited","",AC8) -> Above 1 Year
A9: 8 | B9: Kasibugga Sub-Division | C9: 0 | E9: Kasibugga | F9: '33/2018' | G9: 143,283,341 r.w 149 IPC | H9: 43144 | I9: Feb | J9: 2018 | K9: Other IPC | M9: Other IPC | N9: IPC | O9: Non-Grave | S9: UI | W9: SC/PRC/CC No. Awaited | X9: SC/PRC/CC No. Awaited | Y9: 46197 | Z9: ON OCCURRED AT 30.01.2018 AT 10.30 AM TO 16.30 PM HRS THE REPORTED THAT 13.02.2018 AT 21.00 HRS THE COMPLAINANT REPORTED THAT HIS GO TO ON TRAFIC DUTY WITH KASIBUGGA TOWN PARIMISSION WITH STATION HOUSE OFFICER THEN THE OCCURRENCE TIME WAS COMING SOME PERSONS DHARNA WITH CASHEW STATUE IN PALASA AND PUBLIC INCONVENCE AND TRAFIC JAM IN CONTUNE TO 3 ROAD JUNCTION WITHOUT INTIMATION SO FORTHRE ACTION TO THAT PERSONS THE CASE WAS REGISTER CR NO 33/2018 U/S 143,283,341,R/W149 IPC OF KASIBUGGA POLICE STATION | AA9: Total | AB9: =IF(S9="UI",DATEDIF(H9,TODAY(),"D"),"") -> 3167 | AC9: =IF(S9="UI",IF(AB9>365,"Above 1 Year",IF(AND(AB9<=365,AB9>180),"Above 6 Months",IF(AND(AB9<=180,AB9>90),"Above 3 Months",IF(AND(AB9<=90,AB9>60),"Above 60 Days",IF(AND(AB9<=60,AB9>45),"45 to 60 Days","Below 45 Days"))))),"") -> Above 1 Year | AD9: =IF(Y9<>"",DATEDIF(Y9,TODAY(),"D"),"") -> 114 | AE9: =IF(AD9<>"",IF(AD9>365,"Above 1 Year",IF(AND(AD9<=365,AD9>180),"Above 6 Months",IF(AND(AD9<=180,AD9>90),"Above 3 Months",IF(AND(AD9<=90,AD9>60),"Above 60 Days",IF(AND(AD9<=60,AD9>45),"45 to 60 Days","Below 45 Days"))))),"") -> Above 3 Months | AF9: D-6(Other IPC) | AG9: Kasibugga,'33/2018' | AH9: =IF(X9="SC/PRC/CC No. Awaited","",AC9)
A10: 9 | B10: Srikakulam Sub-Division | C10: Srikakulam Rural Circle | E10: Gara | F10: '91/2018' | G10: 306 IPC | H10: 43276 | I10: Jun | J10: 2018 | K10: Other IPC | M10: Other IPC | N10: IPC | O10: Non-Grave | P10: 43554 | S10: UI | W10: SC/PRC/CC No. Awaited | X10: SC/PRC/CC No. Awaited | Y10: 43554 | Z10: Occurred on 25.06.2018 prior to 00.30 hrs at Cheekati Suryanarayana slabbed house at Mogadalapadu village, Vatsvalsa pnchayat, Gara mandal and reported on the morning at 09.099 hrs, in which the complainant Kinthali Padmaja w/o late Srinivasa rao, 35 yrs, Kalinga vysya caste, . No. 1-24-100/A, Bavaji Nagar, Balaga, Srikakulam reported that prior to 20 years she was married with her husband and they blessed a son Poorna Chandu(17) daughter Harika. Her husband worked as R.M.P. at Komaravanipeta, Mogadalapadu villages of Gara mandal and also doing chits business. While constructed a house and not maintaining the chits properly, so her husband financially loss. Since 5 years her mother-in-law harassed her husband that her husband construct the house in the name of her mother-in-law, for cle | AA10: Total | AB10: =IF(S10="UI",DATEDIF(H10,TODAY(),"D"),"") -> 3035 | AC10: =IF(S10="UI",IF(AB10>365,"Above 1 Year",IF(AND(AB10<=365,AB10>180),"Above 6 Months",IF(AND(AB10<=180,AB10>90),"Above 3 Months",IF(AND(AB10<=90,AB10>60),"Above 60 Days",IF(AND(AB10<=60,AB10>45),"45 to 60 Days","Below 45 Days"))))),"") -> Above 1 Year | AD10: =IF(Y10<>"",DATEDIF(Y10,TODAY(),"D"),"") -> 2757 | AE10: =IF(AD10<>"",IF(AD10>365,"Above 1 Year",IF(AND(AD10<=365,AD10>180),"Above 6 Months",IF(AND(AD10<=180,AD10>90),"Above 3 Months",IF(AND(AD10<=90,AD10>60),"Above 60 Days",IF(AND(AD10<=60,AD10>45),"45 to 60 Days","Below 45 Days"))))),"") -> Above 1 Year | AF10: D-6(Other IPC) | AG10: Gara,'91/2018' | AH10: =IF(X10="SC/PRC/CC No. Awaited","",AC10)
A11: 10 | B11: Srikakulam Sub-Division | C11: Srikakulam Rural Circle | E11: Srikakulam I Town | F11: '9/2019' | G11: 420 IPC, 66-C,66-D ITA-2000-2008 | H11: 43483 | I11: Jan | J11: 2019 | K11: Cyber Crime offences | M11: Cyber Crime offences | N11: IPC | O11: Non-Grave | S11: UI | W11: Want of clues | X11: Want of clues | Z11: This is a case of cheating by personation by means of electronic device that occurred on 17.01.2019 at 1230 hours at State Bank of India, Main Branch, Srikakulam town and reported belatedly on 18.01.2019 at 1800 hours by the complainant Dusi Surya Prakash,S/o. Late Sundara Ramarao, age 63 years, Brhmin by caste, Door No. 1-41-26, Bharathi nagar, Hospital Road, Balaga, Srikakulam town is retired SBI Manager, Srikakulam that on 17.01.2019 at 1230 hours, some unknown caller Santhosh Sharma made a call from SIM No. 8789129706 to his SIM No. 9440116227 ATM Verification asking for his Account No.10718089866,OTP and Personal deatils and unfortunately without knowing he provide all the required details un known caller asking me which includes OTP also. on the pretext that his account was in troubl | AA11: Total | AB11: =IF(S11="UI",DATEDIF(H11,TODAY(),"D"),"") -> 2828 | AC11: =IF(S11="UI",IF(AB11>365,"Above 1 Year",IF(AND(AB11<=365,AB11>180),"Above 6 Months",IF(AND(AB11<=180,AB11>90),"Above 3 Months",IF(AND(AB11<=90,AB11>60),"Above 60 Days",IF(AND(AB11<=60,AB11>45),"45 to 60 Days","Below 45 Days"))))),"") -> Above 1 Year | AD11: =IF(Y11<>"",DATEDIF(Y11,TODAY(),"D"),"") | AE11: =IF(AD11<>"",IF(AD11>365,"Above 1 Year",IF(AND(AD11<=365,AD11>180),"Above 6 Months",IF(AND(AD11<=180,AD11>90),"Above 3 Months",IF(AND(AD11<=90,AD11>60),"Above 60 Days",IF(AND(AD11<=60,AD11>45),"45 to 60 Days","Below 45 Days"))))),"") | AF11: Cyber Cell | AG11: Srikakulam I Town,'9/2019' | AH11: =IF(X11="SC/PRC/CC No. Awaited","",AC11) -> Above 1 Year
A12: 11 | B12: Srikakulam Sub-Division | C12: Srikakulam Rural Circle | D12: CI-Srikakulam Rural Circle | E12: Srikakulam Rural | F12: '20/2019' | G12: 380,302 IPC | H12: 43503 | I12: Feb | J12: 2019 | K12: Murder for gain | L12: Murder for gain | M12: Property Offences | N12: IPC | O12: Grave | S12: UI | W12: For Arrest of Accused | X12: For Arrest of Accused | Z12: Occurred on 07.02.19 in between 09.00 Hrs to 17.30 Hrs at Plot No S2/7-28, Viziaynagar Colony, Bondhilipuram, Chapuram Panchayat Srikakulam Rural Mandal and reported on the same day at 22.00 Hrs where in the complaint Abdhul Zilani S/o Abdhul Kuddhus, Age 38 Yrs., Caste by Muslium, Plot No S2/7-28, Viziaynagar Colony, Bondhilipuram, Chapuram Panchayat Srikakulam Rural Mandal reported that he is living by doing “Prince Foot Wear” business at Srikakulam , and he is residing at above said address along with his two sons by names Jafar 16 yrs , Nishan 13 Yrs, his wife by name Abdhul Mehur Nisha-35 Yrs and his mother Jhorona Bhai 67 Yrs. On 07.02.19 at 09.00 Hrs he went to Rajam and Ranasthalam Villages for Weekly collections, and at 17.30 Hrs he received a phone call from his elder son that hi | AA12: Total | AB12: =IF(S12="UI",DATEDIF(H12,TODAY(),"D"),"") -> 2808 | AC12: =IF(S12="UI",IF(AB12>365,"Above 1 Year",IF(AND(AB12<=365,AB12>180),"Above 6 Months",IF(AND(AB12<=180,AB12>90),"Above 3 Months",IF(AND(AB12<=90,AB12>60),"Above 60 Days",IF(AND(AB12<=60,AB12>45),"45 to 60 Days","Below 45 Days"))))),"") -> Above 1 Year | AD12: =IF(Y12<>"",DATEDIF(Y12,TODAY(),"D"),"") | AE12: =IF(AD12<>"",IF(AD12>365,"Above 1 Year",IF(AND(AD12<=365,AD12>180),"Above 6 Months",IF(AND(AD12<=180,AD12>90),"Above 3 Months",IF(AND(AD12<=90,AD12>60),"Above 60 Days",IF(AND(AD12<=60,AD12>45),"45 to 60 Days","Below 45 Days"))))),"") | AF12: D-3 & D-5 (CAW) | AG12: Srikakulam Rural,'20/2019' | AH12: =IF(X12="SC/PRC/CC No. Awaited","",AC12) -> Above 1 Year
A13: 12 | B13: Srikakulam Sub-Division | C13: 0 | E13: Srikakulam II Town | F13: '13/2019' | G13: 420 IPC, 66-C,66-D ITA-2000-2008 | H13: 43506 | I13: Feb | J13: 2019 | K13: Cyber Crime offences | M13: Cyber Crime offences | N13: IPC | O13: Non-Grave | S13: UI | W13: For Suspect Verification | X13: Want of clues | Z13: This is a case of cheating coupled with using pass word of another person and also cheating duly using computer resource occurred on 09.02.2019 at 13.45 hrs at Rainbow hospital, Srikakulam town and reported on 10.02.2019 at 11.00 hrs, wherein the complt. Palla Suribabu s/o Yerrayya, 33 yrs, Yadav by caste, Byri vill, Srikakulam rural mandalam reported that some unknown person had cheated him and withdrew the amounts spells-wise to a total of Rs. 1,10,900/- through computer resource by using his ATM card, PIN and OTP number. | AA13: Total | AB13: =IF(S13="UI",DATEDIF(H13,TODAY(),"D"),"") -> 2805 | AC13: =IF(S13="UI",IF(AB13>365,"Above 1 Year",IF(AND(AB13<=365,AB13>180),"Above 6 Months",IF(AND(AB13<=180,AB13>90),"Above 3 Months",IF(AND(AB13<=90,AB13>60),"Above 60 Days",IF(AND(AB13<=60,AB13>45),"45 to 60 Days","Below 45 Days"))))),"") -> Above 1 Year | AD13: =IF(Y13<>"",DATEDIF(Y13,TODAY(),"D"),"") | AE13: =IF(AD13<>"",IF(AD13>365,"Above 1 Year",IF(AND(AD13<=365,AD13>180),"Above 6 Months",IF(AND(AD13<=180,AD13>90),"Above 3 Months",IF(AND(AD13<=90,AD13>60),"Above 60 Days",IF(AND(AD13<=60,AD13>45),"45 to 60 Days","Below 45 Days"))))),"") | AF13: Cyber Cell | AG13: Srikakulam II Town,'13/2019' | AH13: =IF(X13="SC/PRC/CC No. Awaited","",AC13) -> Above 1 Year
A14: 13 | B14: Kasibugga Sub-Division | C14: Sompeta Circle | E14: Sompeta | F14: '24/2019' | G14: 174 CrPC | H14: 43549 | I14: Mar | J14: 2019 | K14: 174 CrPC | M14: 174 CrPC | N14: 174 CrPC | O14: Non-Grave | S14: UI | W14: Pending records from other depts., | X14: Pending records from other depts., | Y14: 45432 | Z14: on 25-03-2019 at 10-00 hrs the complainant Palavalasa Kalyani, w/o Sriramurty, age 28yrs, caste by Kalinga, working as process server, VI Additional Dist. Judge, Sompeta, residents of Geetha cable street, Sompeta lodged a written report stating that she is working as process server, VI Additional Dist. Judge, Sompeta since 2015. Every day morning at 08-00 hrs she attending Banglow duty at VI Additional Dist. Judge Madam House. As usually, today, i.e. on 25-3-2019 morning at about 08-00 hours she attending Bunglow duty i.e. the house of Judge Madam situated at BC colony, Kothapeta street belongs to Vysyaraju Gopi Kiran. She along with sweeper Urmila knocked the doors and pressed the calling bell. But no response. Due to suspicion, she informed their court staff Baburao, Sur | AA14: Total | AB14: =IF(S14="UI",DATEDIF(H14,TODAY(),"D"),"") -> 2762 | AC14: =IF(S14="UI",IF(AB14>365,"Above 1 Year",IF(AND(AB14<=365,AB14>180),"Above 6 Months",IF(AND(AB14<=180,AB14>90),"Above 3 Months",IF(AND(AB14<=90,AB14>60),"Above 60 Days",IF(AND(AB14<=60,AB14>45),"45 to 60 Days","Below 45 Days"))))),"") -> Above 1 Year | AD14: =IF(Y14<>"",DATEDIF(Y14,TODAY(),"D"),"") -> 879 | AE14: =IF(AD14<>"",IF(AD14>365,"Above 1 Year",IF(AND(AD14<=365,AD14>180),"Above 6 Months",IF(AND(AD14<=180,AD14>90),"Above 3 Months",IF(AND(AD14<=90,AD14>60),"Above 60 Days",IF(AND(AD14<=60,AD14>45),"45 to 60 Days","Below 45 Days"))))),"") -> Above 1 Year | AF14: D-4(174 CrPC) | AG14: Sompeta,'24/2019' | AH14: =IF(X14="SC/PRC/CC No. Awaited","",AC14) -> Above 1 Year
A15: 14 | B15: Tekkali Sub-Division | C15: Narasannapeta Circle | E15: Polaki | F15: '88/2019' | G15: Man Missing Person | H15: 43558 | I15: Apr | J15: 2019 | K15: Missing Cases | L15: Man Missing | M15: Missing Cases | N15: Missing | O15: Non-Grave | S15: UI | W15: Want of clues | X15: Want of clues | Z15: This is a case of Man missing, occurred on 25.03.2019 at 11:00hrs in renku Jaganadhapeta village,Polaki Mandal and reported on 03.04.2019 at 15.00hrs by the complainant Tulugu Saradha W/o Suryanarayana ,Age 30 yrs,runkujaganadhapuram village of Polaki Mandal reported that on 25-03-2019 at about 1100 hrs her father by name Yarabati Appalaramayya S/o lt Chinnavadu, Age 68 yrs, kapu by caste, Runkujaganadhapuram village left from her home for going to Narasannapeta to watch TDP MLA nomination and didn’t return back still now, Complainant, her family members and villagers causes enquiries about missing person in and around the village and surrounding villages, but could not get useful information | AA15: Total | AB15: =IF(S15="UI",DATEDIF(H15,TODAY(),"D"),"") -> 2753 | AC15: =IF(S15="UI",IF(AB15>365,"Above 1 Year",IF(AND(AB15<=365,AB15>180),"Above 6 Months",IF(AND(AB15<=180,AB15>90),"Above 3 Months",IF(AND(AB15<=90,AB15>60),"Above 60 Days",IF(AND(AB15<=60,AB15>45),"45 to 60 Days","Below 45 Days"))))),"") -> Above 1 Year | AD15: =IF(Y15<>"",DATEDIF(Y15,TODAY(),"D"),"") | AE15: =IF(AD15<>"",IF(AD15>365,"Above 1 Year",IF(AND(AD15<=365,AD15>180),"Above 6 Months",IF(AND(AD15<=180,AD15>90),"Above 3 Months",IF(AND(AD15<=90,AD15>60),"Above 60 Days",IF(AND(AD15<=60,AD15>45),"45 to 60 Days","Below 45 Days"))))),"") | AF15: D-4(Missing) | AG15: Polaki,'88/2019' | AH15: =IF(X15="SC/PRC/CC No. Awaited","",AC15) -> Above 1 Year
A16: 15 | B16: Srikakulam Sub-Division | C16: 0 | E16: Srikakulam II Town | F16: '67/2019' | G16: 420 IPC, 66-C,66-D ITA-2000-2008 | H16: 43575 | I16: Apr | J16: 2019 | K16: Cyber Crime offences | M16: Cyber Crime offences | N16: IPC | O16: Non-Grave | S16: UI | W16: For Suspect Verification | X16: Want of clues | Z16: This is a case of cheating by personation by using any communication device or computer resource that occurred Prior to 03.11.2018 at Pondara street, Kalinga hights, Balaga, Srikakulam town and reported on 20.04.2019 at 18.30 hours. where the complainant Dupam Kishor, s/o Janakeswara rao, 38 yrs, Vatarnary department, r/o Pondara street, Kalinga hights, Balaga, Srikakulam town reported that on 24.09.2018 at 09.00 hrs the accused Venkatesh informed the complainant over phone No. 8790996638 through his Nos.80175779512, 9674718043 that he has won lottery for Rs. 12,80,000 and asked to pay an amount of Rs. 12,800/- in Bank and issued an account No. 37924172660. Believing the words, he deposited the said amount. On 12.10.2018 he received phone call to Sonia Mehatha asked to pay an amount of Rs | AA16: Total | AB16: =IF(S16="UI",DATEDIF(H16,TODAY(),"D"),"") -> 2736 | AC16: =IF(S16="UI",IF(AB16>365,"Above 1 Year",IF(AND(AB16<=365,AB16>180),"Above 6 Months",IF(AND(AB16<=180,AB16>90),"Above 3 Months",IF(AND(AB16<=90,AB16>60),"Above 60 Days",IF(AND(AB16<=60,AB16>45),"45 to 60 Days","Below 45 Days"))))),"") -> Above 1 Year | AD16: =IF(Y16<>"",DATEDIF(Y16,TODAY(),"D"),"") | AE16: =IF(AD16<>"",IF(AD16>365,"Above 1 Year",IF(AND(AD16<=365,AD16>180),"Above 6 Months",IF(AND(AD16<=180,AD16>90),"Above 3 Months",IF(AND(AD16<=90,AD16>60),"Above 60 Days",IF(AND(AD16<=60,AD16>45),"45 to 60 Days","Below 45 Days"))))),"") | AF16: Cyber Cell | AG16: Srikakulam II Town,'67/2019' | AH16: =IF(X16="SC/PRC/CC No. Awaited","",AC16) -> Above 1 Year
A17: 16 | B17: Srikakulam Sub-Division | C17: 0 | E17: Srikakulam II Town | F17: '70/2019' | G17: 66-C,66-D ITA-2000-2008 | H17: 43578 | I17: Apr | J17: 2019 | K17: Cyber Crime offences | M17: Cyber Crime offences | N17: IPC | O17: Non-Grave | S17: UI | W17: For Suspect Verification | X17: Want of clues | Z17: Occurred on prior to 09.04.2019 at Gandi Nagar, Illisipuram junction, Srikakulam town and reported on 23.04.2019 at 10.30 hrs, where in the Complainant Mudu Ramji Naik S/o late Sriramulu, age 35 years, S.T. (Lambadi) by caste, Illisipuram Srikakulam reported that he is working as Asst. Professor at Ambedkar University. He has an Account in Andhra Bank with No.01810100003013 and its credit Card No.4373782067435002. On 04-04-2019 at 05.15 PM, he received a phone call from an unknown person with SIM No.9169764561 and collected his credit card number by deceiving that he would provide SBI Credit card in addition to the Andhra Bank Credit Card. After some time, he asked OTP numbers which are received to his mobile by that time by informing that the OTP numbers are required to make cross check. | AA17: Total | AB17: =IF(S17="UI",DATEDIF(H17,TODAY(),"D"),"") -> 2733 | AC17: =IF(S17="UI",IF(AB17>365,"Above 1 Year",IF(AND(AB17<=365,AB17>180),"Above 6 Months",IF(AND(AB17<=180,AB17>90),"Above 3 Months",IF(AND(AB17<=90,AB17>60),"Above 60 Days",IF(AND(AB17<=60,AB17>45),"45 to 60 Days","Below 45 Days"))))),"") -> Above 1 Year | AD17: =IF(Y17<>"",DATEDIF(Y17,TODAY(),"D"),"") | AE17: =IF(AD17<>"",IF(AD17>365,"Above 1 Year",IF(AND(AD17<=365,AD17>180),"Above 6 Months",IF(AND(AD17<=180,AD17>90),"Above 3 Months",IF(AND(AD17<=90,AD17>60),"Above 60 Days",IF(AND(AD17<=60,AD17>45),"45 to 60 Days","Below 45 Days"))))),"") | AF17: Cyber Cell | AG17: Srikakulam II Town,'70/2019' | AH17: =IF(X17="SC/PRC/CC No. Awaited","",AC17) -> Above 1 Year
A18: 17 | B18: Srikakulam Sub-Division | C18: Srikakulam Rural Circle | E18: Gara | F18: '97/2019' | G18: Woman Missing Person | H18: 43593 | I18: May | J18: 2019 | K18: Missing Cases | L18: Women Missing | M18: Missing Cases | N18: Missing | O18: Non-Grave | S18: UI | W18: Want of clues | X18: Want of clues | Z18: This is a case of woman missing occurred on 24.04.2018 at 13.00 hrs at Vadapalem village, Gara mandal and reported on 08.05.2019 at 10.00 hrs, in which the complainant Surada Rajesh s/o lt Rama Rao, 24 yrs, Vadapalem village, Gara Manual working as fisher man at Veeravali town, Gujarath and he reported that his wife Surada Varalakshmi w/o Rajesh, 22 years, vadabalija by caste, Vadapalem village, Gara Mandal, on 24.04.2018 he received information from his elder brother at about 13.00 hrs his wife left from his home for purchasing vegetables and did not returned, on that he come back to home and searched here and there and their relatives houses for his wife, but got no information, then he came to P.S. on 08.05.2019 and gave the report. | AA18: Total | AB18: =IF(S18="UI",DATEDIF(H18,TODAY(),"D"),"") -> 2718 | AC18: =IF(S18="UI",IF(AB18>365,"Above 1 Year",IF(AND(AB18<=365,AB18>180),"Above 6 Months",IF(AND(AB18<=180,AB18>90),"Above 3 Months",IF(AND(AB18<=90,AB18>60),"Above 60 Days",IF(AND(AB18<=60,AB18>45),"45 to 60 Days","Below 45 Days"))))),"") -> Above 1 Year | AD18: =IF(Y18<>"",DATEDIF(Y18,TODAY(),"D"),"") | AE18: =IF(AD18<>"",IF(AD18>365,"Above 1 Year",IF(AND(AD18<=365,AD18>180),"Above 6 Months",IF(AND(AD18<=180,AD18>90),"Above 3 Months",IF(AND(AD18<=90,AD18>60),"Above 60 Days",IF(AND(AD18<=60,AD18>45),"45 to 60 Days","Below 45 Days"))))),"") | AF18: D-4(Missing) | AG18: Gara,'97/2019' | AH18: =IF(X18="SC/PRC/CC No. Awaited","",AC18) -> Above 1 Year
A19: 18 | B19: Kasibugga Sub-Division | C19: Kasibugga Rural Circle | E19: Vajrapukothuru | F19: '81/2019' | G19: Woman,Girl,Boy Missing Person | H19: 43596 | I19: May | J19: 2019 | K19: Missing Cases | L19: Women Missing | M19: Missing Cases | N19: Missing | O19: Non-Grave | S19: UI | W19: Want of clues | X19: Want of clues | Z19: Occurred on 02.02.2019 at the house of the complainant Garudabhadra village, Vajrapukotturu PS and reported on 11.05.2019 at 19.00 hrs in which the complainant Arli Kalyan, s/o Danesh, 38 yrs, Jalari by caste, Garudabhadra village, Vajrapukotturu Mandal reported that his wife Sirisha, aged about 32 yrs left the house with their two children i.e. Son Arli Akhil aged about 5 yrs and Daughter Jahnavi aged about 8 yrs left the house telling him that she was going to her parents house at Visakhapatnam but did not return back home. Late he came to know that she had gone with his villager Burjupeta Venkatesh, s/o Krishna Rao, 25 yrs, Rajaka by caste. | AA19: Total | AB19: =IF(S19="UI",DATEDIF(H19,TODAY(),"D"),"") -> 2715 | AC19: =IF(S19="UI",IF(AB19>365,"Above 1 Year",IF(AND(AB19<=365,AB19>180),"Above 6 Months",IF(AND(AB19<=180,AB19>90),"Above 3 Months",IF(AND(AB19<=90,AB19>60),"Above 60 Days",IF(AND(AB19<=60,AB19>45),"45 to 60 Days","Below 45 Days"))))),"") -> Above 1 Year | AD19: =IF(Y19<>"",DATEDIF(Y19,TODAY(),"D"),"") | AE19: =IF(AD19<>"",IF(AD19>365,"Above 1 Year",IF(AND(AD19<=365,AD19>180),"Above 6 Months",IF(AND(AD19<=180,AD19>90),"Above 3 Months",IF(AND(AD19<=90,AD19>60),"Above 60 Days",IF(AND(AD19<=60,AD19>45),"45 to 60 Days","Below 45 Days"))))),"") | AF19: D-4(Missing) | AG19: Vajrapukothuru,'81/2019' | AH19: =IF(X19="SC/PRC/CC No. Awaited","",AC19) -> Above 1 Year
A20: 19 | B20: Tekkali Sub-Division | C20: Narasannapeta Circle | E20: Polaki | F20: '123/2019' | G20: Man Missing Person | H20: 43603 | I20: May | J20: 2019 | K20: Missing Cases | L20: Man Missing | M20: Missing Cases | N20: Missing | O20: Non-Grave | S20: UI | W20: Want of clues | X20: Want of clues | Z20: This is a case of Man missing, occurred on 12.05.2019 at 11:00hrs in Apparaopeta Colony,Polaki Mandal and reported on 18.05.2019 at 18.00Hrs by the complainant Linguberi Appa rao s/o Jogulu, age-45Years, caste by Srisaina, apparaopeta Colony, Polaki mandal reported that on 12.05.2019 at about 1100 hrs her father by name linguberi Jogulu S/o late Yerrayya,age- 82years, caste by srisaina, apparaopeta Colony, Polaki mandal. the missing person was mental disordered . On left from her home and didn’t return back still now, Complainant, her family members and villagers causes enquiries about missing person in and around the village and surrounding villages, but could not get useful information. | AA20: Total | AB20: =IF(S20="UI",DATEDIF(H20,TODAY(),"D"),"") -> 2708 | AC20: =IF(S20="UI",IF(AB20>365,"Above 1 Year",IF(AND(AB20<=365,AB20>180),"Above 6 Months",IF(AND(AB20<=180,AB20>90),"Above 3 Months",IF(AND(AB20<=90,AB20>60),"Above 60 Days",IF(AND(AB20<=60,AB20>45),"45 to 60 Days","Below 45 Days"))))),"") -> Above 1 Year | AD20: =IF(Y20<>"",DATEDIF(Y20,TODAY(),"D"),"") | AE20: =IF(AD20<>"",IF(AD20>365,"Above 1 Year",IF(AND(AD20<=365,AD20>180),"Above 6 Months",IF(AND(AD20<=180,AD20>90),"Above 3 Months",IF(AND(AD20<=90,AD20>60),"Above 60 Days",IF(AND(AD20<=60,AD20>45),"45 to 60 Days","Below 45 Days"))))),"") | AF20: D-4(Missing) | AG20: Polaki,'123/2019' | AH20: =IF(X20="SC/PRC/CC No. Awaited","",AC20) -> Above 1 Year
A21: 20 | B21: Tekkali Sub-Division | C21: Kothuru Circle | E21: Kothuru | F21: '125/2019' | G21: Man Missing Person | H21: 43612 | I21: May | J21: 2019 | K21: Missing Cases | L21: Man Missing | M21: Missing Cases | N21: Missing | O21: Non-Grave | S21: UI | W21: Want of clues | X21: Want of clues | Z21: Occurred on 19.05.2019 at about 10.30 hrs at Nivagam bus station and reported on 27.05.2019 at about 12.00 hrs which the complainant Kolleti Raju s/o Suryanarayana, age 45 yrs, Rajaka, Sigipuram village, Pathapatnam Mandal reported that his father Kolleti Suryanarayana s/o late busayya, 70 yrs went marriage at Sirusuvada village and returned from there and waiting for a bus at Nivagam village in order to come their village and missed from there | AA21: Total | AB21: =IF(S21="UI",DATEDIF(H21,TODAY(),"D"),"") -> 2699 | AC21: =IF(S21="UI",IF(AB21>365,"Above 1 Year",IF(AND(AB21<=365,AB21>180),"Above 6 Months",IF(AND(AB21<=180,AB21>90),"Above 3 Months",IF(AND(AB21<=90,AB21>60),"Above 60 Days",IF(AND(AB21<=60,AB21>45),"45 to 60 Days","Below 45 Days"))))),"") -> Above 1 Year | AD21: =IF(Y21<>"",DATEDIF(Y21,TODAY(),"D"),"") | AE21: =IF(AD21<>"",IF(AD21>365,"Above 1 Year",IF(AND(AD21<=365,AD21>180),"Above 6 Months",IF(AND(AD21<=180,AD21>90),"Above 3 Months",IF(AND(AD21<=90,AD21>60),"Above 60 Days",IF(AND(AD21<=60,AD21>45),"45 to 60 Days","Below 45 Days"))))),"") | AF21: D-4(Missing) | AG21: Kothuru,'125/2019' | AH21: =IF(X21="SC/PRC/CC No. Awaited","",AC21) -> Above 1 Year
A22: 21 | B22: Kasibugga Sub-Division | C22: Sompeta Circle | E22: Baruva | F22: '57/2019' | G22: Man Missing Person | H22: 43614 | I22: May | J22: 2019 | K22: Missing Cases | L22: Man Missing | M22: Missing Cases | N22: Missing | O22: Non-Grave | S22: UI | W22: Want of clues | X22: Want of clues | Z22: This is a case of man Missing, which occurred on 16-05-2019 at about 17.15 hrs from baruvakotturu, baruva village of Sompeta Mandal and reported on 29-05-2019 at 12.30 hrs, wherein the complainant Ambati Dandasi, S/o Late Jagannaikulu, 52 yrs., tylor,Baruva kotturu village, Sompeta mandal stated that on 16.05.2019 at 17.15 hrs., his Son came to Grand mother House in summer holidays at Nadumuru village , sompeta mandal. That day his son missing did not returned in the evening and there from he found missing. | AA22: Total | AB22: =IF(S22="UI",DATEDIF(H22,TODAY(),"D"),"") -> 2697 | AC22: =IF(S22="UI",IF(AB22>365,"Above 1 Year",IF(AND(AB22<=365,AB22>180),"Above 6 Months",IF(AND(AB22<=180,AB22>90),"Above 3 Months",IF(AND(AB22<=90,AB22>60),"Above 60 Days",IF(AND(AB22<=60,AB22>45),"45 to 60 Days","Below 45 Days"))))),"") -> Above 1 Year | AD22: =IF(Y22<>"",DATEDIF(Y22,TODAY(),"D"),"") | AE22: =IF(AD22<>"",IF(AD22>365,"Above 1 Year",IF(AND(AD22<=365,AD22>180),"Above 6 Months",IF(AND(AD22<=180,AD22>90),"Above 3 Months",IF(AND(AD22<=90,AD22>60),"Above 60 Days",IF(AND(AD22<=60,AD22>45),"45 to 60 Days","Below 45 Days"))))),"") | AF22: D-4(Missing) | AG22: Baruva,'57/2019' | AH22: =IF(X22="SC/PRC/CC No. Awaited","",AC22) -> Above 1 Year
A23: 22 | B23: Srikakulam Sub-Division | C23: 0 | E23: Srikakulam II Town | F23: '94/2019' | G23: 420 IPC, 66-C,66-D ITA-2000-2008 | H23: 43622 | I23: Jun | J23: 2019 | K23: Cyber Crime offences | M23: Cyber Crime offences | N23: IPC | O23: Non-Grave | S23: UI | W23: For Suspect Verification | X23: Want of clues | Z23: The Complainant Dadirao Venkata Kanaka Mahalaxmi Aswini Kumari W/o Vandranki Srinivasa Rao, age 43 years, Patnaik by caste, Kattera Veedhi, Srikakulam town reported that she has a bank account with Debit Card in State Bank of India with A/C No.11152457031. On 06-06-2019 at 02.46PM, one unknown person called with his mobile No.9407300859 to her mobile No.9441123083, by introducing himself that he is calling from S.B.I. Bank, he collected ATM Card Number and CVV number. By believing him, she informed all details including OTP numbers which were received three times to her mobile numbers. Later an amount of Rs.10,999/-, 31,499/- and 7,297 total Rs.49,795/- was transferred from her bank account. | AA23: Total | AB23: =IF(S23="UI",DATEDIF(H23,TODAY(),"D"),"") -> 2689 | AC23: =IF(S23="UI",IF(AB23>365,"Above 1 Year",IF(AND(AB23<=365,AB23>180),"Above 6 Months",IF(AND(AB23<=180,AB23>90),"Above 3 Months",IF(AND(AB23<=90,AB23>60),"Above 60 Days",IF(AND(AB23<=60,AB23>45),"45 to 60 Days","Below 45 Days"))))),"") -> Above 1 Year | AD23: =IF(Y23<>"",DATEDIF(Y23,TODAY(),"D"),"") | AE23: =IF(AD23<>"",IF(AD23>365,"Above 1 Year",IF(AND(AD23<=365,AD23>180),"Above 6 Months",IF(AND(AD23<=180,AD23>90),"Above 3 Months",IF(AND(AD23<=90,AD23>60),"Above 60 Days",IF(AND(AD23<=60,AD23>45),"45 to 60 Days","Below 45 Days"))))),"") | AF23: Cyber Cell | AG23: Srikakulam II Town,'94/2019' | AH23: =IF(X23="SC/PRC/CC No. Awaited","",AC23) -> Above 1 Year
A24: 23 | B24: Tekkali Sub-Division | C24: Tekkali Rural Circle | E24: Nandigam | F24: '103/2019' | G24: Man Missing Person | H24: 43625 | I24: Jun | J24: 2019 | K24: Missing Cases | L24: Man Missing | M24: Missing Cases | N24: Missing | O24: Non-Grave | S24: Police Disposal | W24: Want of clues | X24: Finalized | Z24: Occurred on 14.05.2019 at Deenabandupuram village, Nandigam Mandal and reported on 09.06.2019 at 17.30 hrs in which the complainant Sonapuram Laxmi, w/o Lavanna @ Kalavayya, 28 yrs, Deenabandupuram village, Nandigam Mandal reported that her husband Sonapuram Lavanna, s/o Ramulu, 34 yrs was eking livelihood at Guntur came to the village on 13.05.2019 to attend a function. On 14.05.2019 he attended the function and after that he made a call to her and stated that he was going to Guntur. From then he did not come to her or called her and his phone was switched off. | AA24: Total | AB24: =IF(S24="UI",DATEDIF(H24,TODAY(),"D"),"") | AC24: =IF(S24="UI",IF(AB24>365,"Above 1 Year",IF(AND(AB24<=365,AB24>180),"Above 6 Months",IF(AND(AB24<=180,AB24>90),"Above 3 Months",IF(AND(AB24<=90,AB24>60),"Above 60 Days",IF(AND(AB24<=60,AB24>45),"45 to 60 Days","Below 45 Days"))))),"") | AD24: =IF(Y24<>"",DATEDIF(Y24,TODAY(),"D"),"") | AE24: =IF(AD24<>"",IF(AD24>365,"Above 1 Year",IF(AND(AD24<=365,AD24>180),"Above 6 Months",IF(AND(AD24<=180,AD24>90),"Above 3 Months",IF(AND(AD24<=90,AD24>60),"Above 60 Days",IF(AND(AD24<=60,AD24>45),"45 to 60 Days","Below 45 Days"))))),"") | AF24: D-4(Missing) | AG24: Nandigam,'103/2019' | AH24: =IF(X24="SC/PRC/CC No. Awaited","",AC24)
A25: 24 | B25: Tekkali Sub-Division | C25: Narasannapeta Circle | E25: Polaki | F25: '148/2019' | G25: 324,307,326,323 r/w 34 IPC | H25: 43639 | I25: Jun | J25: 2019 | K25: Attempt To Murder | M25: Bodily Offiences | N25: IPC | O25: Non-Grave | P25: 44188 | Q25: Yes | S25: UI | W25: Charge Sheet returned form court | X25: Charge Sheet returned form court | Y25: 44188 | Z25: This is a case of attempt to murder that occurred on 27.03.2018 at 07.00 hrs at Dubbakavanipeta village (v) Polaki (M) and reported on the same day at 13.30 hrs by the complainant Duppattla Rambabu s/o Sriramulu, age- 42years, caste kalinga, Dubbakavanipeta village, Polaki mandal , wherein the accused Dubbaka Ravi Babu and 10 others attacked the complainant and father , mother and Complainant father in law bet him Iron road and kattahuva, stick and hand , legs and stone caused bleeding injuries. due to a dispute that the complainant placed her damage the wall place by the family members of the accused | AA25: Total | AB25: =IF(S25="UI",DATEDIF(H25,TODAY(),"D"),"") -> 2672 | AC25: =IF(S25="UI",IF(AB25>365,"Above 1 Year",IF(AND(AB25<=365,AB25>180),"Above 6 Months",IF(AND(AB25<=180,AB25>90),"Above 3 Months",IF(AND(AB25<=90,AB25>60),"Above 60 Days",IF(AND(AB25<=60,AB25>45),"45 to 60 Days","Below 45 Days"))))),"") -> Above 1 Year | AD25: =IF(Y25<>"",DATEDIF(Y25,TODAY(),"D"),"") -> 2123 | AE25: =IF(AD25<>"",IF(AD25>365,"Above 1 Year",IF(AND(AD25<=365,AD25>180),"Above 6 Months",IF(AND(AD25<=180,AD25>90),"Above 3 Months",IF(AND(AD25<=90,AD25>60),"Above 60 Days",IF(AND(AD25<=60,AD25>45),"45 to 60 Days","Below 45 Days"))))),"") -> Above 1 Year | AF25: D-6(Bodily) | AG25: Polaki,'148/2019' | AH25: =IF(X25="SC/PRC/CC No. Awaited","",AC25) -> Above 1 Year
A26: 25 | B26: Srikakulam Sub-Division | C26: Srikakulam Rural Circle | E26: Srikakulam Rural | F26: '216/2019' | G26: Woman Missing Person | H26: 43669 | I26: Jul | J26: 2019 | K26: Missing Cases | L26: Women Missing | M26: Missing Cases | N26: Missing | O26: Non-Grave | S26: UI | W26: Want of clues | X26: Want of clues | Z26: Occurred on 17.07.2019 at 11.00 hrs at Reddikillipalem village, Srikakulam mandal and reported on 23.07.2019 at 18.30 hrs, where in the complainant Pandhiri Thrinadharao S/o Adhinarayana age 32 years, caste by Padhma saali, Reddikillipalem village, Srikakulam mandal reported that his mother Pandhiri Rathnalu w/o Adhinarayana age 53 years, she left home on 17.07.2019 at 11.00 hrs for go to her sister village Silagam singuvalasa villge Srikakjulam rural mandal, she didn’t go there and didn’t return back. complainant made search her friends and relations houses, didn’t found missing women. | AA26: Total | AB26: =IF(S26="UI",DATEDIF(H26,TODAY(),"D"),"") -> 2642 | AC26: =IF(S26="UI",IF(AB26>365,"Above 1 Year",IF(AND(AB26<=365,AB26>180),"Above 6 Months",IF(AND(AB26<=180,AB26>90),"Above 3 Months",IF(AND(AB26<=90,AB26>60),"Above 60 Days",IF(AND(AB26<=60,AB26>45),"45 to 60 Days","Below 45 Days"))))),"") -> Above 1 Year | AD26: =IF(Y26<>"",DATEDIF(Y26,TODAY(),"D"),"") | AE26: =IF(AD26<>"",IF(AD26>365,"Above 1 Year",IF(AND(AD26<=365,AD26>180),"Above 6 Months",IF(AND(AD26<=180,AD26>90),"Above 3 Months",IF(AND(AD26<=90,AD26>60),"Above 60 Days",IF(AND(AD26<=60,AD26>45),"45 to 60 Days","Below 45 Days"))))),"") | AF26: D-4(Missing) | AG26: Srikakulam Rural,'216/2019' | AH26: =IF(X26="SC/PRC/CC No. Awaited","",AC26) -> Above 1 Year
A27: 26 | B27: Srikakulam Sub-Division | C27: Srikakulam Rural Circle | E27: Srikakulam Rural | F27: '231/2019' | G27: 420 IPC, 66-C ITA-2000-2008 | H27: 43679 | I27: Aug | J27: 2019 | K27: Cyber Crime offences | M27: Cyber Crime offences | N27: IPC | O27: Non-Grave | S27: UI | W27: For Suspect Verification | X27: For Suspect Verification | Z27: Occurred on 11.06.2019 at 18.00 hours, reported on 02.08.2019 at 20.00 hours, where in the complainant by name Bathula Venkatamohan sathyarao S/o Late Gangayya,age 56 years, Thelaga by cste, Thilak nagar, Srikakulam rural mandal, reported that, one un known person call to him from phone no 01246771300, your not generate your credit card pin no Since 6 months and I am generate your pin number, tell me your credit card last four numbers and OTP number, complainant also gave his credit card last four numbers and OTP number, after 5 minits complainant received one SMS, that is you are purchased one mobi cwick system and debited your credit card account Rs. 38,500/-, complainant gave report to Superintendent of Police Srikakulam on spandahana on 29.07.2019. | AA27: Total | AB27: =IF(S27="UI",DATEDIF(H27,TODAY(),"D"),"") -> 2632 | AC27: =IF(S27="UI",IF(AB27>365,"Above 1 Year",IF(AND(AB27<=365,AB27>180),"Above 6 Months",IF(AND(AB27<=180,AB27>90),"Above 3 Months",IF(AND(AB27<=90,AB27>60),"Above 60 Days",IF(AND(AB27<=60,AB27>45),"45 to 60 Days","Below 45 Days"))))),"") -> Above 1 Year | AD27: =IF(Y27<>"",DATEDIF(Y27,TODAY(),"D"),"") | AE27: =IF(AD27<>"",IF(AD27>365,"Above 1 Year",IF(AND(AD27<=365,AD27>180),"Above 6 Months",IF(AND(AD27<=180,AD27>90),"Above 3 Months",IF(AND(AD27<=90,AD27>60),"Above 60 Days",IF(AND(AD27<=60,AD27>45),"45 to 60 Days","Below 45 Days"))))),"") | AF27: Cyber Cell | AG27: Srikakulam Rural,'231/2019' | AH27: =IF(X27="SC/PRC/CC No. Awaited","",AC27) -> Above 1 Year
A28: 27 | B28: Srikakulam Sub-Division | C28: J.R.Puram Circle | E28: Etcherla | F28: '196/2019' | G28: Woman Missing Person | H28: 43686 | I28: Aug | J28: 2019 | K28: Missing Cases | L28: Women Missing | M28: Missing Cases | N28: Missing | O28: Non-Grave | S28: UI | W28: Want of clues | X28: Want of clues | Z28: Occurred 07.08.2019 at 1000 hours at Ibrahimbad village and reported on 09.08..2019 at 18.00 hours by the complainant Killi Udaya Bhaskara Rao, S/o Venkata Ramana , age -23 yrs, Kalinga by caste, Ibrahimbad village, Etcherla Mandal. In which, one Seepana Santhosamma, age-53 Grandmother of the complainant left the house in the temporary absence of inmates and found missing. Despite sincere enquiries at all likely places, no clue could be elicited to locate the missing women. | AA28: Total | AB28: =IF(S28="UI",DATEDIF(H28,TODAY(),"D"),"") -> 2625 | AC28: =IF(S28="UI",IF(AB28>365,"Above 1 Year",IF(AND(AB28<=365,AB28>180),"Above 6 Months",IF(AND(AB28<=180,AB28>90),"Above 3 Months",IF(AND(AB28<=90,AB28>60),"Above 60 Days",IF(AND(AB28<=60,AB28>45),"45 to 60 Days","Below 45 Days"))))),"") -> Above 1 Year | AD28: =IF(Y28<>"",DATEDIF(Y28,TODAY(),"D"),"") | AE28: =IF(AD28<>"",IF(AD28>365,"Above 1 Year",IF(AND(AD28<=365,AD28>180),"Above 6 Months",IF(AND(AD28<=180,AD28>90),"Above 3 Months",IF(AND(AD28<=90,AD28>60),"Above 60 Days",IF(AND(AD28<=60,AD28>45),"45 to 60 Days","Below 45 Days"))))),"") | AF28: D-4(Missing) | AG28: Etcherla,'196/2019' | AH28: =IF(X28="SC/PRC/CC No. Awaited","",AC28) -> Above 1 Year
A29: 28 | B29: Srikakulam Sub-Division | C29: J.R.Puram Circle | E29: Etcherla | F29: '206/2019' | G29: Man Missing Person | H29: 43701 | I29: Aug | J29: 2019 | K29: Missing Cases | L29: Man Missing | M29: Missing Cases | N29: Missing | O29: Non-Grave | S29: UI | W29: Want of clues | X29: Want of clues | Z29: This is a case of man missing occurred prior to 24.08.2019 at Peyyalavanipeta village, Etcherla Mandal and reported on 24.08.2019 at 19.00 hrs by the complainant Tammineni Madhsudhanarao s/o Chinnarao, 39 yrs, kalinga by caste, peyyalavanipeta village, Etcherla mandal in which one Tammineni Chinnarao s/o late Rajarao, 71 yrs, kalinga by caste, peyyalavanipeta village, Etcherla mandal father of the complainant left the house in the temporary absence of inmates and found missing. Despite sincere enquiries at all likely places, no clue could be elicited to locate the missing man. | AA29: Total | AB29: =IF(S29="UI",DATEDIF(H29,TODAY(),"D"),"") -> 2610 | AC29: =IF(S29="UI",IF(AB29>365,"Above 1 Year",IF(AND(AB29<=365,AB29>180),"Above 6 Months",IF(AND(AB29<=180,AB29>90),"Above 3 Months",IF(AND(AB29<=90,AB29>60),"Above 60 Days",IF(AND(AB29<=60,AB29>45),"45 to 60 Days","Below 45 Days"))))),"") -> Above 1 Year | AD29: =IF(Y29<>"",DATEDIF(Y29,TODAY(),"D"),"") | AE29: =IF(AD29<>"",IF(AD29>365,"Above 1 Year",IF(AND(AD29<=365,AD29>180),"Above 6 Months",IF(AND(AD29<=180,AD29>90),"Above 3 Months",IF(AND(AD29<=90,AD29>60),"Above 60 Days",IF(AND(AD29<=60,AD29>45),"45 to 60 Days","Below 45 Days"))))),"") | AF29: D-4(Missing) | AG29: Etcherla,'206/2019' | AH29: =IF(X29="SC/PRC/CC No. Awaited","",AC29) -> Above 1 Year
A30: 29 | B30: Tekkali Sub-Division | C30: Narasannapeta Circle | E30: Narasannapeta | F30: '264/2019' | G30: 420 IPC, 76(1) CFA | H30: 43702 | I30: Aug | J30: 2019 | K30: Cheating | M30: White Collar Offences | N30: IPC | O30: Non-Grave | P30: 44341 | S30: UI | W30: SC/PRC/CC No. Awaited | X30: SC/PRC/CC No. Awaited | Y30: 44341 | Z30: This is a case of cheating that occurred prior to 25.08.2019 and reported on 25.08.2019 at 20.00 hrs, in which the complainant Korukonda Simhachalam S/o late Surayya, 40 yrs, Kapu by caste, Kotarupalli village, Narasannapeta Mandal reported that the accused Polaki Ramana S/o Suryanarayana and 3 others of Kotarupalli village believe deceitful words with him and collecting money Rs. 90,000/- by chit fund and did not returned to him thereby cheated him. | AA30: Total | AB30: =IF(S30="UI",DATEDIF(H30,TODAY(),"D"),"") -> 2609 | AC30: =IF(S30="UI",IF(AB30>365,"Above 1 Year",IF(AND(AB30<=365,AB30>180),"Above 6 Months",IF(AND(AB30<=180,AB30>90),"Above 3 Months",IF(AND(AB30<=90,AB30>60),"Above 60 Days",IF(AND(AB30<=60,AB30>45),"45 to 60 Days","Below 45 Days"))))),"") -> Above 1 Year | AD30: =IF(Y30<>"",DATEDIF(Y30,TODAY(),"D"),"") -> 1970 | AE30: =IF(AD30<>"",IF(AD30>365,"Above 1 Year",IF(AND(AD30<=365,AD30>180),"Above 6 Months",IF(AND(AD30<=180,AD30>90),"Above 3 Months",IF(AND(AD30<=90,AD30>60),"Above 60 Days",IF(AND(AD30<=60,AD30>45),"45 to 60 Days","Below 45 Days"))))),"") -> Above 1 Year | AF30: D-6(White collar) | AG30: Narasannapeta,'264/2019' | AH30: =IF(X30="SC/PRC/CC No. Awaited","",AC30)
A31: 30 | B31: Srikakulam Sub-Division | C31: J.R.Puram Circle | E31: Etcherla | F31: '216/2019' | G31: Man Missing Person | H31: 43714 | I31: Sep | J31: 2019 | K31: Missing Cases | L31: Man Missing | M31: Missing Cases | N31: Missing | O31: Non-Grave | S31: UI | W31: Want of clues | X31: Want of clues | Z31: This is a case of Missing of mans, that occurred on 06..09..2019 13.00 hours at kuppili gedda, kuppili village, Etcherla and reported on 06..09..2019 at 20.00 hours by the complainant Balivada Dhananjayarao s/o Ramarao, Age 48 years, karnam by caste, VRO, Kuppili village, Srikakulam Mandal. In which, 4 person go to beach for photos, one person Bora Ramana reddy, s/o Appanna, 22 yrs was get into the river and at the time big waves from bay of Bengal and he was danger in the river., Nimma santhosh s/o dalappadu, 21 yrs, both are reddika by caste, kuppili village was try to save him, but they both are missing that place. till in the late evening and thereby found missing. On enquiries in and around the sea area, whereabouts of the missing 2 persons could not be traced out. | AA31: Total | AB31: =IF(S31="UI",DATEDIF(H31,TODAY(),"D"),"") -> 2597 | AC31: =IF(S31="UI",IF(AB31>365,"Above 1 Year",IF(AND(AB31<=365,AB31>180),"Above 6 Months",IF(AND(AB31<=180,AB31>90),"Above 3 Months",IF(AND(AB31<=90,AB31>60),"Above 60 Days",IF(AND(AB31<=60,AB31>45),"45 to 60 Days","Below 45 Days"))))),"") -> Above 1 Year | AD31: =IF(Y31<>"",DATEDIF(Y31,TODAY(),"D"),"") | AE31: =IF(AD31<>"",IF(AD31>365,"Above 1 Year",IF(AND(AD31<=365,AD31>180),"Above 6 Months",IF(AND(AD31<=180,AD31>90),"Above 3 Months",IF(AND(AD31<=90,AD31>60),"Above 60 Days",IF(AND(AD31<=60,AD31>45),"45 to 60 Days","Below 45 Days"))))),"") | AF31: D-4(Missing) | AG31: Etcherla,'216/2019' | AH31: =IF(X31="SC/PRC/CC No. Awaited","",AC31) -> Above 1 Year
A32: 31 | B32: Srikakulam Sub-Division | C32: 0 | E32: Srikakulam II Town | F32: '192/2019' | G32: 66-C ITA-2000-2008 | H32: 43721 | I32: Sep | J32: 2019 | K32: Cyber Crime offences | M32: Cyber Crime offences | N32: IPC | O32: Non-Grave | S32: UI | W32: For Suspect Verification | X32: Want of clues | Z32: Occurred prior to 13.09.2019 at APGVP bank, beside saraswati mahal and reported on 13.09.2019 at 19.30 hrs wherein the complainant Cheekati krishnaveni W/o chanti, age 27 yrs, Velama caste, DCCB colony, srikakulam reported that she is having bank account No: 73050902382 at APGVP Bank, beside Saraswati theatre, her account having Rs 40,000/- in the name o RD amount. on 10.09.2019 she came to know that there is no balance in her account then she went to the bank and enquired about it, then she came know that total Rs 27,500/- was withdrawn from her account on dates 20.08.2019, 28.08.2019, 30.08.2019 without her notice. Then she came to police station and gave the report | AA32: Total | AB32: =IF(S32="UI",DATEDIF(H32,TODAY(),"D"),"") -> 2590 | AC32: =IF(S32="UI",IF(AB32>365,"Above 1 Year",IF(AND(AB32<=365,AB32>180),"Above 6 Months",IF(AND(AB32<=180,AB32>90),"Above 3 Months",IF(AND(AB32<=90,AB32>60),"Above 60 Days",IF(AND(AB32<=60,AB32>45),"45 to 60 Days","Below 45 Days"))))),"") -> Above 1 Year | AD32: =IF(Y32<>"",DATEDIF(Y32,TODAY(),"D"),"") | AE32: =IF(AD32<>"",IF(AD32>365,"Above 1 Year",IF(AND(AD32<=365,AD32>180),"Above 6 Months",IF(AND(AD32<=180,AD32>90),"Above 3 Months",IF(AND(AD32<=90,AD32>60),"Above 60 Days",IF(AND(AD32<=60,AD32>45),"45 to 60 Days","Below 45 Days"))))),"") | AF32: Cyber Cell | AG32: Srikakulam II Town,'192/2019' | AH32: =IF(X32="SC/PRC/CC No. Awaited","",AC32) -> Above 1 Year
A33: 32 | B33: Srikakulam Sub-Division | C33: Srikakulam Rural Circle | E33: Srikakulam Rural | F33: '267/2019' | G33: 420 IPC, 66-D ITA-2000-2008 | H33: 43721 | I33: Sep | J33: 2019 | K33: Cyber Crime offences | M33: Cyber Crime offences | N33: IPC | O33: Non-Grave | S33: UI | W33: For Suspect Verification | X33: For Suspect Verification | Z33: Occurred on prior to 12.08.2019, at Gedhelavanipeta village Srikakulam rural mandal, reported on 13.09.2019 at 09.00 hours, where in the complainant Sadhu VenkataramaRAO S/o Apparao age 38 years, caste by Velama, Gedhelavanipeta village, Srikakulam rural mandal, reported that accused Miss Meria Alena send one mail to complainant, that is she is cancer patient, she died in few days, she contained 2.5 billions dollars, you build an orphanage and provide an ATM card to complainant withdrawal Rs. 10,000/- in his possession has made fraudulent remarks and 17 lakes in the account of defamation by her agent by name Mr. Adems Jones in various accounts. | AA33: Total | AB33: =IF(S33="UI",DATEDIF(H33,TODAY(),"D"),"") -> 2590 | AC33: =IF(S33="UI",IF(AB33>365,"Above 1 Year",IF(AND(AB33<=365,AB33>180),"Above 6 Months",IF(AND(AB33<=180,AB33>90),"Above 3 Months",IF(AND(AB33<=90,AB33>60),"Above 60 Days",IF(AND(AB33<=60,AB33>45),"45 to 60 Days","Below 45 Days"))))),"") -> Above 1 Year | AD33: =IF(Y33<>"",DATEDIF(Y33,TODAY(),"D"),"") | AE33: =IF(AD33<>"",IF(AD33>365,"Above 1 Year",IF(AND(AD33<=365,AD33>180),"Above 6 Months",IF(AND(AD33<=180,AD33>90),"Above 3 Months",IF(AND(AD33<=90,AD33>60),"Above 60 Days",IF(AND(AD33<=60,AD33>45),"45 to 60 Days","Below 45 Days"))))),"") | AF33: Cyber Cell | AG33: Srikakulam Rural,'267/2019' | AH33: =IF(X33="SC/PRC/CC No. Awaited","",AC33) -> Above 1 Year
A34: 33 | B34: Srikakulam Sub-Division | C34: 0 | E34: Srikakulam II Town | F34: '194/2019' | G34: 66-D,66-C ITA-2000-2008 | H34: 43722 | I34: Sep | J34: 2019 | K34: Cyber Crime offences | M34: Cyber Crime offences | N34: IPC | O34: Non-Grave | S34: UI | W34: For Suspect Verification | X34: Want of clues | Z34: This is a case of cheating and Information Technology Act, where in the complainant Boddu Rana, S/o Rama Krishna, age about 33 years, Caste by Vadabalija, Dammala street, Golkonda revu street, Srikakulam town reported that, he is working as a Manager in Hotel Nagavali, Srikakulam town. On 14.09.2019 at 15.51 hrs he got a phone call from Pune named Mr.Rakesh Sharma to the land line number of the Hotel and he made reservation to book 3 rooms A/C DLX for 3 nights from 15.09.2019 to 18.09.2019 after that the customer asked the complainant’s A/C number to pay advance, then the complainant gave his Google Pay number to him, then the customer asked to the complainant about his Google pay pin, then the complainant told his Pin, after Rs. 30,000/- amount was withdrawn from his account. Then h | AA34: Total | AB34: =IF(S34="UI",DATEDIF(H34,TODAY(),"D"),"") -> 2589 | AC34: =IF(S34="UI",IF(AB34>365,"Above 1 Year",IF(AND(AB34<=365,AB34>180),"Above 6 Months",IF(AND(AB34<=180,AB34>90),"Above 3 Months",IF(AND(AB34<=90,AB34>60),"Above 60 Days",IF(AND(AB34<=60,AB34>45),"45 to 60 Days","Below 45 Days"))))),"") -> Above 1 Year | AD34: =IF(Y34<>"",DATEDIF(Y34,TODAY(),"D"),"") | AE34: =IF(AD34<>"",IF(AD34>365,"Above 1 Year",IF(AND(AD34<=365,AD34>180),"Above 6 Months",IF(AND(AD34<=180,AD34>90),"Above 3 Months",IF(AND(AD34<=90,AD34>60),"Above 60 Days",IF(AND(AD34<=60,AD34>45),"45 to 60 Days","Below 45 Days"))))),"") | AF34: Cyber Cell | AG34: Srikakulam II Town,'194/2019' | AH34: =IF(X34="SC/PRC/CC No. Awaited","",AC34) -> Above 1 Year
A35: 34 | B35: Srikakulam Sub-Division | C35: Srikakulam Rural Circle | E35: Srikakulam Rural | F35: '268/2019' | G35: 420 IPC, 66-D ITA-2000-2008 | H35: 43723 | I35: Sep | J35: 2019 | K35: Cyber Crime offences | M35: Cyber Crime offences | N35: IPC | O35: Non-Grave | S35: UI | W35: For Suspect Verification | X35: For Suspect Verification | Z35: Occurred on prior to 09.09.2019, at Thilak nagar, Chapuram panchayathi, Srikakulam amandl, reported on 15.09.2019 at 16.00 hours, where in the Complainant Rejeti Sowmya D/o Vijayananda Rao, 38 yrs, BC-B converted Christians R/o Tilak nagar, Chapuram Panchayathi, Srikakulam (M) by addressing to the kind Superintendent of Police, Srikakulam and submitted the same on the day of “Spandana”. In which, the petitioner stated that, accused by name Dr. Gopal V Mike who is a face book friend, lured the Complainant to marry her by taking advantage of her separation from her husband and also made the petitioner feel greedy he would give an amount of Rs. 3.1 million dollars by exchanging it into Indian currency, which was got from his father as his father marry another lady soon after death | AA35: Total | AB35: =IF(S35="UI",DATEDIF(H35,TODAY(),"D"),"") -> 2588 | AC35: =IF(S35="UI",IF(AB35>365,"Above 1 Year",IF(AND(AB35<=365,AB35>180),"Above 6 Months",IF(AND(AB35<=180,AB35>90),"Above 3 Months",IF(AND(AB35<=90,AB35>60),"Above 60 Days",IF(AND(AB35<=60,AB35>45),"45 to 60 Days","Below 45 Days"))))),"") -> Above 1 Year | AD35: =IF(Y35<>"",DATEDIF(Y35,TODAY(),"D"),"") | AE35: =IF(AD35<>"",IF(AD35>365,"Above 1 Year",IF(AND(AD35<=365,AD35>180),"Above 6 Months",IF(AND(AD35<=180,AD35>90),"Above 3 Months",IF(AND(AD35<=90,AD35>60),"Above 60 Days",IF(AND(AD35<=60,AD35>45),"45 to 60 Days","Below 45 Days"))))),"") | AF35: Cyber Cell | AG35: Srikakulam Rural,'268/2019' | AH35: =IF(X35="SC/PRC/CC No. Awaited","",AC35) -> Above 1 Year
A36: 35 | B36: Srikakulam Sub-Division | C36: J.R.Puram Circle | E36: Etcherla | F36: '238/2019' | G36: 379,409,219,430,420 IPC, 2,3 PDPPA | H36: 43731 | I36: Sep | J36: 2019 | K36: Sand cases | M36: Enforcement | N36: Enforcement | O36: Non-Grave | S36: UI | W36: Court Stay Order | X36: Court Stay Order | Y36: 43731 | Z36: This is case of public servant in judicial proceedings and criminal breach of trust and mischief by injury to works of irrigation occurred on prior to 23.09.2019 and reported on 23.09.2019 at 18.00 hrs by the complainant Modalavalasa Chiranjeevi s/o late Apprao, 57 yrs, kalinga by caste, Fareedpeta village, Etcherla mandal in which the accused Bodduru Yerraih s/o asirayya, Chowdry Narayana murty@ Babji s/o late satyanarayana, Chowdry Dhanalaxmi w/o Narayana murty, kalinga by caste, S.M.Puram village, Etcherla mandal were Deputy Director of mines and Geology, srikakulam i/c according permission issuing Temporary permit for 150000 cum of gravel to bodduru Yerraiah s/o late asirayya. The entire proceedings took place without following law and committed criminal offence the excavation much be | AA36: Total | AB36: =IF(S36="UI",DATEDIF(H36,TODAY(),"D"),"") -> 2580 | AC36: =IF(S36="UI",IF(AB36>365,"Above 1 Year",IF(AND(AB36<=365,AB36>180),"Above 6 Months",IF(AND(AB36<=180,AB36>90),"Above 3 Months",IF(AND(AB36<=90,AB36>60),"Above 60 Days",IF(AND(AB36<=60,AB36>45),"45 to 60 Days","Below 45 Days"))))),"") -> Above 1 Year | AD36: =IF(Y36<>"",DATEDIF(Y36,TODAY(),"D"),"") -> 2580 | AE36: =IF(AD36<>"",IF(AD36>365,"Above 1 Year",IF(AND(AD36<=365,AD36>180),"Above 6 Months",IF(AND(AD36<=180,AD36>90),"Above 3 Months",IF(AND(AD36<=90,AD36>60),"Above 60 Days",IF(AND(AD36<=60,AD36>45),"45 to 60 Days","Below 45 Days"))))),"") -> Above 1 Year | AF36: D-1 | AG36: Etcherla,'238/2019' | AH36: =IF(X36="SC/PRC/CC No. Awaited","",AC36) -> Above 1 Year
A37: 36 | B37: Srikakulam Sub-Division | C37: Srikakulam Rural Circle | E37: Srikakulam I Town | F37: '143/2019' | G37: 457,380 IPC | H37: 43749 | I37: Oct | J37: 2019 | K37: HB by Night | M37: Property Offences | N37: IPC | O37: Non-Grave | P37: 45989 | Q37: Yes | S37: UI | W37: Charge Sheet returned form court | X37: Charge Sheet returned form court | Y37: 45989 | Z37: Occurred in between 07.10.2019 at about 1630 hours and 11.10.2019 at about 1100 hours at MIG-398, APHB colony, Srikakulam town and reported on 11.10.2019 at 1600 hours by the complainant Mugu Hari Krishna s/o Rama Rao, age 35 years, Caste by Vadabalija, MIG-398, APHB colony, Srikakulam town reported that in between 07.10.2019 at about 0430 pm and 11.10.2019 at about 1100 am, some unknown culprits got ingress into his house, in the absence of in-mates, break opened the almirah and committed theft of Gold Pustulathadu weight-3 ¼ tola, Gold Chain weight -1 ¼ tola and Gold Ring weight – ½ tola, total Gold worth Rs. 80,000/- and Cash Rs. 15,000/-and made away with the stolen booty. | AA37: Total | AB37: =IF(S37="UI",DATEDIF(H37,TODAY(),"D"),"") -> 2562 | AC37: =IF(S37="UI",IF(AB37>365,"Above 1 Year",IF(AND(AB37<=365,AB37>180),"Above 6 Months",IF(AND(AB37<=180,AB37>90),"Above 3 Months",IF(AND(AB37<=90,AB37>60),"Above 60 Days",IF(AND(AB37<=60,AB37>45),"45 to 60 Days","Below 45 Days"))))),"") -> Above 1 Year | AD37: =IF(Y37<>"",DATEDIF(Y37,TODAY(),"D"),"") -> 322 | AE37: =IF(AD37<>"",IF(AD37>365,"Above 1 Year",IF(AND(AD37<=365,AD37>180),"Above 6 Months",IF(AND(AD37<=180,AD37>90),"Above 3 Months",IF(AND(AD37<=90,AD37>60),"Above 60 Days",IF(AND(AD37<=60,AD37>45),"45 to 60 Days","Below 45 Days"))))),"") -> Above 6 Months | AF37: D-3 | AG37: Srikakulam I Town,'143/2019' | AH37: =IF(X37="SC/PRC/CC No. Awaited","",AC37) -> Above 1 Year
A38: 37 | B38: Srikakulam Sub-Division | C38: Amadalavalasa Circle | E38: Sarubujjili | F38: '130/2019' | G38: 420 IPC, 66-D,66-C ITA-2000-2008 | H38: 43753 | I38: Oct | J38: 2019 | K38: Cyber Crime offences | M38: Cyber Crime offences | N38: IPC | O38: Non-Grave | S38: UI | W38: Want of clues | X38: Want of clues | Z38: Occurred on 09-10-2019 at 16.00 hrs at Vennelavalasa Village, of Sarubujjili Mandal and reported on 15-10-2019 at 18.00 Hrs. in which the complainant Nalli Ananda Raju, S/o John, age: 54 yrs, SC-Mala by caste, Novodaya School Quarters, Vennelavalasa Village, Sarubujjili Mandal reported that his daughter Nalli Snigtha, age:22 years received a mail from Carriear Job.com that register for Rs. 49/- for Job alert information. She trusted that mail and login in to that mail link through her mobile No 8179331264 and she used the complainant bank details for this registration and asked the ATM card No and OTP. The complainant tell the OTP, but the transaction failed while she tried seven time for the registration but its also failed. Finally she contact 7428869227 mobile number which is pr | AA38: Total | AB38: =IF(S38="UI",DATEDIF(H38,TODAY(),"D"),"") -> 2558 | AC38: =IF(S38="UI",IF(AB38>365,"Above 1 Year",IF(AND(AB38<=365,AB38>180),"Above 6 Months",IF(AND(AB38<=180,AB38>90),"Above 3 Months",IF(AND(AB38<=90,AB38>60),"Above 60 Days",IF(AND(AB38<=60,AB38>45),"45 to 60 Days","Below 45 Days"))))),"") -> Above 1 Year | AD38: =IF(Y38<>"",DATEDIF(Y38,TODAY(),"D"),"") | AE38: =IF(AD38<>"",IF(AD38>365,"Above 1 Year",IF(AND(AD38<=365,AD38>180),"Above 6 Months",IF(AND(AD38<=180,AD38>90),"Above 3 Months",IF(AND(AD38<=90,AD38>60),"Above 60 Days",IF(AND(AD38<=60,AD38>45),"45 to 60 Days","Below 45 Days"))))),"") | AF38: Cyber Cell | AG38: Sarubujjili,'130/2019' | AH38: =IF(X38="SC/PRC/CC No. Awaited","",AC38) -> Above 1 Year
A39: 38 | B39: Tekkali Sub-Division | C39: Narasannapeta Circle | E39: Polaki | F39: '189/2019' | G39: Man Missing Person | H39: 43758 | I39: Oct | J39: 2019 | K39: Missing Cases | L39: Man Missing | M39: Missing Cases | N39: Missing | O39: Non-Grave | S39: UI | W39: Want of clues | X39: Want of clues | Z39: Occurred on 26.08.2019 at 17.00 hrs at Urjam village , Polaki and reported on 20.10.2019 at 1900 hrs, wherein the complainant kanitha ramesh S/o rama raio, age- 24 Years, caste by kalinga, Urjam Village, polaki mandal reported that his father Kamitha Rama rao s/o late Appara rao , age- 60 years, caste by kalinga, Urjam village, polaki mandal , My son left from home Competitive examination coaching and did not return to home and he whereabouts are not known. | AA39: Total | AB39: =IF(S39="UI",DATEDIF(H39,TODAY(),"D"),"") -> 2553 | AC39: =IF(S39="UI",IF(AB39>365,"Above 1 Year",IF(AND(AB39<=365,AB39>180),"Above 6 Months",IF(AND(AB39<=180,AB39>90),"Above 3 Months",IF(AND(AB39<=90,AB39>60),"Above 60 Days",IF(AND(AB39<=60,AB39>45),"45 to 60 Days","Below 45 Days"))))),"") -> Above 1 Year | AD39: =IF(Y39<>"",DATEDIF(Y39,TODAY(),"D"),"") | AE39: =IF(AD39<>"",IF(AD39>365,"Above 1 Year",IF(AND(AD39<=365,AD39>180),"Above 6 Months",IF(AND(AD39<=180,AD39>90),"Above 3 Months",IF(AND(AD39<=90,AD39>60),"Above 60 Days",IF(AND(AD39<=60,AD39>45),"45 to 60 Days","Below 45 Days"))))),"") | AF39: D-4(Missing) | AG39: Polaki,'189/2019' | AH39: =IF(X39="SC/PRC/CC No. Awaited","",AC39) -> Above 1 Year
A40: 39 | B40: Tekkali Sub-Division | C40: Kothuru Circle | E40: Hiramandalam | F40: '122/2019' | G40: Woman Missing Person | H40: 43763 | I40: Oct | J40: 2019 | K40: Missing Cases | L40: Women Missing | M40: Missing Cases | N40: Missing | O40: Non-Grave | S40: UI | W40: Want of clues | X40: Want of clues | Z40: Occurred on 18.10.2019 at about 10.00 hours at Gandhinagar Street, Hiramandalam village and Mandal and reported on 25.10.2019 at 14.30 hrs by the complainant Burla Srinu, s/o Suryanarayana, age 28 yrs, caste by SC Madaiga, Gandhinagar Street, Hiramandalam village and Mandal reported that, his sister Burla Roja aged about 25 yrs has been working as a Grama Volunteer of Relli Street, Hiramandalam village and she daily went to her volunteer duties. As well as on 18.10.2019 at about 10.00 hrs his sister left from his house by saying that she went to her volunteer duties, but did not return to his house since 06.00 PM on the same day, the complainant and his relatives searched in all surrounding places, relative and friends houses but did not any information and then the complainant came to the | AA40: Total | AB40: =IF(S40="UI",DATEDIF(H40,TODAY(),"D"),"") -> 2548 | AC40: =IF(S40="UI",IF(AB40>365,"Above 1 Year",IF(AND(AB40<=365,AB40>180),"Above 6 Months",IF(AND(AB40<=180,AB40>90),"Above 3 Months",IF(AND(AB40<=90,AB40>60),"Above 60 Days",IF(AND(AB40<=60,AB40>45),"45 to 60 Days","Below 45 Days"))))),"") -> Above 1 Year | AD40: =IF(Y40<>"",DATEDIF(Y40,TODAY(),"D"),"") | AE40: =IF(AD40<>"",IF(AD40>365,"Above 1 Year",IF(AND(AD40<=365,AD40>180),"Above 6 Months",IF(AND(AD40<=180,AD40>90),"Above 3 Months",IF(AND(AD40<=90,AD40>60),"Above 60 Days",IF(AND(AD40<=60,AD40>45),"45 to 60 Days","Below 45 Days"))))),"") | AF40: D-4(Missing) | AG40: Hiramandalam,'122/2019' | AH40: =IF(X40="SC/PRC/CC No. Awaited","",AC40) -> Above 1 Year
A41: 40 | B41: Srikakulam Sub-Division | C41: Srikakulam Rural Circle | E41: Srikakulam I Town | F41: '155/2019' | G41: 420 IPC, 66-C ITA-2000-2008 | H41: 43763 | I41: Oct | J41: 2019 | K41: Cyber Crime offences | M41: Cyber Crime offences | N41: IPC | O41: Non-Grave | S41: UI | W41: Want of clues | X41: Want of clues | Z41: Occurred on 23-10-2019 at 11:10 hours and reported today i.e on 25-10-2019 at 20:30 hours that the complainant doing as a seeman and have an account in Kotak Mahendra Bank , Srikakulam and I have a Google pay account also on 23-10-2019 at 11:10 hours i have received an unknown call from unknown number and that he said he calls from Amazon and I booked an item on it and refund he want to my google pay pin hence I told that pin number then after I received a message to withdraw an amount of Rs. 50,000/- when I received the message i approached the bank in between time he taken from my google pay account Rs.50,000/- totally i lost Rs 1,00,000/- to unknown persons hence lodged a report for taking necessary action against the person Basing on the report registered a case in Cr.No | AA41: Total | AB41: =IF(S41="UI",DATEDIF(H41,TODAY(),"D"),"") -> 2548 | AC41: =IF(S41="UI",IF(AB41>365,"Above 1 Year",IF(AND(AB41<=365,AB41>180),"Above 6 Months",IF(AND(AB41<=180,AB41>90),"Above 3 Months",IF(AND(AB41<=90,AB41>60),"Above 60 Days",IF(AND(AB41<=60,AB41>45),"45 to 60 Days","Below 45 Days"))))),"") -> Above 1 Year | AD41: =IF(Y41<>"",DATEDIF(Y41,TODAY(),"D"),"") | AE41: =IF(AD41<>"",IF(AD41>365,"Above 1 Year",IF(AND(AD41<=365,AD41>180),"Above 6 Months",IF(AND(AD41<=180,AD41>90),"Above 3 Months",IF(AND(AD41<=90,AD41>60),"Above 60 Days",IF(AND(AD41<=60,AD41>45),"45 to 60 Days","Below 45 Days"))))),"") | AF41: Cyber Cell | AG41: Srikakulam I Town,'155/2019' | AH41: =IF(X41="SC/PRC/CC No. Awaited","",AC41) -> Above 1 Year
A42: 41 | B42: Srikakulam Sub-Division | C42: 0 | E42: Srikakulam II Town | F42: '270/2019' | G42: Man Missing Person | H42: 43799 | I42: Nov | J42: 2019 | K42: Missing Cases | L42: Man Missing | M42: Missing Cases | N42: Missing | O42: Non-Grave | S42: UI | W42: Want of clues | X42: Want of clues | Z42: This is a case of man missing, occurred on 07.10.2019 at 10.00 hrs, at Balaga Mettu, Srikakulam town, and reported on 30.11.2019 at 19.00 hrs, wherein the complainant Perumalla Viswanadh, S/o late Jatlayya, age 80 years, Caste by SC Mala, Balaga Mettu, Srikakulam town reported that his younger son Perumalla Sankar, S/o Viswanadham, age 45 years, Caste by SC Mala, Balaga mettu, Srikakulam town left from his house for masonry work, but he did not come back. The complainant searched about him surrounding places. But he was not found. Hence he lodged a report to P.S. | AA42: Total | AB42: =IF(S42="UI",DATEDIF(H42,TODAY(),"D"),"") -> 2512 | AC42: =IF(S42="UI",IF(AB42>365,"Above 1 Year",IF(AND(AB42<=365,AB42>180),"Above 6 Months",IF(AND(AB42<=180,AB42>90),"Above 3 Months",IF(AND(AB42<=90,AB42>60),"Above 60 Days",IF(AND(AB42<=60,AB42>45),"45 to 60 Days","Below 45 Days"))))),"") -> Above 1 Year | AD42: =IF(Y42<>"",DATEDIF(Y42,TODAY(),"D"),"") | AE42: =IF(AD42<>"",IF(AD42>365,"Above 1 Year",IF(AND(AD42<=365,AD42>180),"Above 6 Months",IF(AND(AD42<=180,AD42>90),"Above 3 Months",IF(AND(AD42<=90,AD42>60),"Above 60 Days",IF(AND(AD42<=60,AD42>45),"45 to 60 Days","Below 45 Days"))))),"") | AF42: D-4(Missing) | AG42: Srikakulam II Town,'270/2019' | AH42: =IF(X42="SC/PRC/CC No. Awaited","",AC42) -> Above 1 Year
A43: 42 | B43: Srikakulam Sub-Division | C43: 0 | E43: Srikakulam II Town | F43: '284/2019' | G43: 420 IPC, 66-C,66-D ITA-2000-2008 | H43: 43809 | I43: Dec | J43: 2019 | K43: Cyber Crime offences | M43: Cyber Crime offences | N43: IPC | O43: Non-Grave | S43: UI | W43: For Suspect Verification | X43: Want of clues | Z43: This is a case of cheating and Information Technology Act, occurred prior to 10.12.2019 at 11.00 hrs, at Podugu Narayanamma colony, Srikakulam town and reported on 10.12.2019 at 11.00 hrs, wherein the complainant Surada Krishna Rao, S/o Bhogiraju, Age 30 years, Caste by Vadabalija, Podugu Narayanamma colony, Srikakulam town reported that he received two coupons from Shop clues online shopping through post, that he was selected in lucky draw as a winner from shop clues customers for prize money Rs. 12,00,000/ for the purpose of Shop clues 9th anniversary. The accused Manoranjan Mondal conceive the complainant through phone call that he has to pay tax amount to receive said money. On that the complainant occasionally send amount Rs. 63,000/- to the accused account. Later he came to know | AA43: Total | AB43: =IF(S43="UI",DATEDIF(H43,TODAY(),"D"),"") -> 2502 | AC43: =IF(S43="UI",IF(AB43>365,"Above 1 Year",IF(AND(AB43<=365,AB43>180),"Above 6 Months",IF(AND(AB43<=180,AB43>90),"Above 3 Months",IF(AND(AB43<=90,AB43>60),"Above 60 Days",IF(AND(AB43<=60,AB43>45),"45 to 60 Days","Below 45 Days"))))),"") -> Above 1 Year | AD43: =IF(Y43<>"",DATEDIF(Y43,TODAY(),"D"),"") | AE43: =IF(AD43<>"",IF(AD43>365,"Above 1 Year",IF(AND(AD43<=365,AD43>180),"Above 6 Months",IF(AND(AD43<=180,AD43>90),"Above 3 Months",IF(AND(AD43<=90,AD43>60),"Above 60 Days",IF(AND(AD43<=60,AD43>45),"45 to 60 Days","Below 45 Days"))))),"") | AF43: Cyber Cell | AG43: Srikakulam II Town,'284/2019' | AH43: =IF(X43="SC/PRC/CC No. Awaited","",AC43) -> Above 1 Year
A44: 43 | B44: Srikakulam Sub-Division | C44: 0 | E44: Srikakulam II Town | F44: '294/2019' | G44: 420 IPC, 66-D,66-C ITA-2000-2008 | H44: 43819 | I44: Dec | J44: 2019 | K44: Cyber Crime offences | M44: Cyber Crime offences | N44: IPC | O44: Non-Grave | S44: UI | W44: For Suspect Verification | X44: Want of clues | Z44: Occurred prior to 23.11.2019 at 14.00 hrs at Bavaji Matam, Balaga, srikakulam and reported on 20.12.2019 at 13.00 hrs, wherein the complainant Kanuku Tirupati rao S/o late Rama Krishna, age 25 yrs, Padmasali caste, Bavaji matam, Balaga reported that he made a phone calls from 7409487550, 7409268043, 7789969728, 6398613692 in the name of Naukari.com by HR managers Avini and four others and get offered a job offer in VESUVIUS INDIA LTD, then he paid registration fees Rs 2500/- through online and attended interview through phone call, then he paid Rs 7500/- for certificate verification through online. Later he paid Rs 35,000/- for getting offer letter and received it on the name of VESUVIUS INDIA LTD. On 09.12.2019, he went to Vesuvius india ltd company at Visakapatnam and met with H | AA44: Total | AB44: =IF(S44="UI",DATEDIF(H44,TODAY(),"D"),"") -> 2492 | AC44: =IF(S44="UI",IF(AB44>365,"Above 1 Year",IF(AND(AB44<=365,AB44>180),"Above 6 Months",IF(AND(AB44<=180,AB44>90),"Above 3 Months",IF(AND(AB44<=90,AB44>60),"Above 60 Days",IF(AND(AB44<=60,AB44>45),"45 to 60 Days","Below 45 Days"))))),"") -> Above 1 Year | AD44: =IF(Y44<>"",DATEDIF(Y44,TODAY(),"D"),"") | AE44: =IF(AD44<>"",IF(AD44>365,"Above 1 Year",IF(AND(AD44<=365,AD44>180),"Above 6 Months",IF(AND(AD44<=180,AD44>90),"Above 3 Months",IF(AND(AD44<=90,AD44>60),"Above 60 Days",IF(AND(AD44<=60,AD44>45),"45 to 60 Days","Below 45 Days"))))),"") | AF44: Cyber Cell | AG44: Srikakulam II Town,'294/2019' | AH44: =IF(X44="SC/PRC/CC No. Awaited","",AC44) -> Above 1 Year
A45: 44 | B45: Srikakulam Sub-Division | C45: 0 | E45: Srikakulam II Town | F45: '12/2020' | G45: 457,380 IPC | H45: 43847 | I45: Jan | J45: 2020 | K45: HB By Night | M45: Property Offences | N45: IPC | O45: Non-Grave | S45: UI | W45: Want of clues | X45: Want of clues | Z45: Occurred in between 16.01.2020 at 19.00 hrs to 17.01.2020 at 08.30 hrs, at H.No. 16-4-84/A, P.N. Colony, Zero line, Srikakulam town and reported on 17.01.2020 at 13.00 hrs, wherein the complainant Aravilli Vidya Praveen, S/o A.V.N. Acharyulu, Age 35 years, Caste by Brahmin, 16-4-84/A, P.N.Colony, Zero line, Srikakulam town reported that he went along with his family members to his native place for Pongal celebrations on 16.01.2020 at 19.00 hrs, and he got a phone call from his owner on 17.01.2020 at 08.30 hrs, that his house was committed to theft by unknown culprits. On that he came his house and found that his house locks were broken, and some silver items were missing, i.e., one Silver plate (Wg. 250 gr), one silver beaker (Wg. 250 gr), 2 Silver lamp stands (Wg. 100gr), one silver glas | AA45: Total | AB45: =IF(S45="UI",DATEDIF(H45,TODAY(),"D"),"") -> 2464 | AC45: =IF(S45="UI",IF(AB45>365,"Above 1 Year",IF(AND(AB45<=365,AB45>180),"Above 6 Months",IF(AND(AB45<=180,AB45>90),"Above 3 Months",IF(AND(AB45<=90,AB45>60),"Above 60 Days",IF(AND(AB45<=60,AB45>45),"45 to 60 Days","Below 45 Days"))))),"") -> Above 1 Year | AD45: =IF(Y45<>"",DATEDIF(Y45,TODAY(),"D"),"") | AE45: =IF(AD45<>"",IF(AD45>365,"Above 1 Year",IF(AND(AD45<=365,AD45>180),"Above 6 Months",IF(AND(AD45<=180,AD45>90),"Above 3 Months",IF(AND(AD45<=90,AD45>60),"Above 60 Days",IF(AND(AD45<=60,AD45>45),"45 to 60 Days","Below 45 Days"))))),"") | AF45: D-3 | AG45: Srikakulam II Town,'12/2020' | AH45: =IF(X45="SC/PRC/CC No. Awaited","",AC45) -> Above 1 Year
A46: 45 | B46: Srikakulam Sub-Division | C46: 0 | D46: CI-Srikakulam II Town | E46: Srikakulam II Town | F46: '13/2020' | G46: 457,380 IPC | H46: 43847 | I46: Jan | J46: 2020 | K46: HB By Night | M46: Property Offences | N46: IPC | O46: Grave | S46: UI | W46: Want of clues | X46: Want of clues | Z46: Occurred in between 13.01.2020 at 19.30 hrs and 17.01.2020 at 15.00 hrs, at Plot No.176, 4th line. P.N. Colony, Srikakulam town and reported on 17.01.2020 at 19.00 hrs, wherein the complainant Kancharapu Sriramulu, S/o Narsimhulu, Age 40 years, is residing in a rent house at Plot No. 176, 4th line, P.N.Colony, Srikakulam town reported that he went to Pongal festival with his family members on 13.01.2020 at 19.30 hrs to his native place Davalapetapeta, G.Sigadam Mandal and returned back to his rent house, Srikakulam town and he found that, his house is committed for theft by unknown culprits and noticed that some unknown person entered into his house and door locks and iron cabinetry locks were broken. Then he searched the iron cabinetry and found so many gold and silver articles were | AA46: Total | AB46: =IF(S46="UI",DATEDIF(H46,TODAY(),"D"),"") -> 2464 | AC46: =IF(S46="UI",IF(AB46>365,"Above 1 Year",IF(AND(AB46<=365,AB46>180),"Above 6 Months",IF(AND(AB46<=180,AB46>90),"Above 3 Months",IF(AND(AB46<=90,AB46>60),"Above 60 Days",IF(AND(AB46<=60,AB46>45),"45 to 60 Days","Below 45 Days"))))),"") -> Above 1 Year | AD46: =IF(Y46<>"",DATEDIF(Y46,TODAY(),"D"),"") | AE46: =IF(AD46<>"",IF(AD46>365,"Above 1 Year",IF(AND(AD46<=365,AD46>180),"Above 6 Months",IF(AND(AD46<=180,AD46>90),"Above 3 Months",IF(AND(AD46<=90,AD46>60),"Above 60 Days",IF(AND(AD46<=60,AD46>45),"45 to 60 Days","Below 45 Days"))))),"") | AF46: D-3 | AG46: Srikakulam II Town,'13/2020' | AH46: =IF(X46="SC/PRC/CC No. Awaited","",AC46) -> Above 1 Year
A47: 46 | B47: Tekkali Sub-Division | C47: Tekkali Rural Circle | E47: Kotabommali | F47: '13/2020' | G47: 420,409 r/w 34 IPC | H47: 43851 | I47: Jan | J47: 2020 | K47: Criminal Breach Of Trust | M47: White Collar Offences | N47: IPC | O47: Non-Grave | P47: 45202 | Q47: Yes | S47: UI | W47: Charge Sheet returned form court | X47: SC/PRC/CC No. Awaited | Y47: 45202 | Z47: Occurred Prior to 21.10.2020 at Yetubdra Cold Storage, Gatlapadu village H/O Vandrada village of Kotabommali mandal, reported 21.01.2020 at 16.00hrs by Sri P. Rameshbabu, Tahsildar, Kotabommali mandal in which on the complaint filed by Korra Sahu proprietor, M/s Sri Satyasai General stores, Gajapathi dist. Odisha state the Vigilance and Enforcement officers, Srikakulam Surprised visit the Cold Storage and noticed the owners of cold storage A1) Korada Venkata manikanta, A2) Karada Prem sai, A3) Potnuru srinivasa Gupta A4) Father of A1, and A5) Goddu Jogarao (clerk) Misappropriated 441 bags of Tamarind, each one bag containing 40kgs, worth Rs 5,61,818, which stored by Sri Korra sahu. The accused with out knowledge of Korra sahu sold away the tamarind stock and misappropriated. | AA47: Total | AB47: =IF(S47="UI",DATEDIF(H47,TODAY(),"D"),"") -> 2460 | AC47: =IF(S47="UI",IF(AB47>365,"Above 1 Year",IF(AND(AB47<=365,AB47>180),"Above 6 Months",IF(AND(AB47<=180,AB47>90),"Above 3 Months",IF(AND(AB47<=90,AB47>60),"Above 60 Days",IF(AND(AB47<=60,AB47>45),"45 to 60 Days","Below 45 Days"))))),"") -> Above 1 Year | AD47: =IF(Y47<>"",DATEDIF(Y47,TODAY(),"D"),"") -> 1109 | AE47: =IF(AD47<>"",IF(AD47>365,"Above 1 Year",IF(AND(AD47<=365,AD47>180),"Above 6 Months",IF(AND(AD47<=180,AD47>90),"Above 3 Months",IF(AND(AD47<=90,AD47>60),"Above 60 Days",IF(AND(AD47<=60,AD47>45),"45 to 60 Days","Below 45 Days"))))),"") -> Above 1 Year | AF47: D-6(White collar) | AG47: Kotabommali,'13/2020' | AH47: =IF(X47="SC/PRC/CC No. Awaited","",AC47)
A48: 47 | B48: Srikakulam Sub-Division | C48: Amadalavalasa Circle | E48: Sarubujjili | F48: '16/2020' | G48: 420 IPC, 66-C,66-D ITA-2000-2008 | H48: 43854 | I48: Jan | J48: 2020 | K48: Cyber Crime offences | M48: Cyber Crime offences | N48: IPC | O48: Non-Grave | S48: UI | W48: Want of clues | X48: Want of clues | Z48: Occurred on 22-01-2020 at 17.35 hrs at L.N.Peta Village & Mandal and reported on 24-01-2020 at 15.00 Hrs. in which the complainant Sanjeev kumar Panigrahi S/o Ramnadh Panigrahi, 32 yrs, C/Oria Brahmina, L.N.Peta (V), (M), Srikakulam Dist reported that one unknown person sent a link massage from mobile No.8101282912 in the name of Phonepe verification, the complaint clicked on the msg and submitted the aadhar card and bank account details and submitted OTP on 21-01-2020, on 22-01-2020 at about 17.35 hrs the complainant received two messages debited the amount of 2 msgs of withdrawals of Rs.29999/- & Rs.4590 total Rs. 34,589/- in from the account of the complainant. As the above cheated the complaint by un known accused in online. | AA48: Total | AB48: =IF(S48="UI",DATEDIF(H48,TODAY(),"D"),"") -> 2457 | AC48: =IF(S48="UI",IF(AB48>365,"Above 1 Year",IF(AND(AB48<=365,AB48>180),"Above 6 Months",IF(AND(AB48<=180,AB48>90),"Above 3 Months",IF(AND(AB48<=90,AB48>60),"Above 60 Days",IF(AND(AB48<=60,AB48>45),"45 to 60 Days","Below 45 Days"))))),"") -> Above 1 Year | AD48: =IF(Y48<>"",DATEDIF(Y48,TODAY(),"D"),"") | AE48: =IF(AD48<>"",IF(AD48>365,"Above 1 Year",IF(AND(AD48<=365,AD48>180),"Above 6 Months",IF(AND(AD48<=180,AD48>90),"Above 3 Months",IF(AND(AD48<=90,AD48>60),"Above 60 Days",IF(AND(AD48<=60,AD48>45),"45 to 60 Days","Below 45 Days"))))),"") | AF48: Cyber Cell | AG48: Sarubujjili,'16/2020' | AH48: =IF(X48="SC/PRC/CC No. Awaited","",AC48) -> Above 1 Year
A49: 48 | B49: Srikakulam Sub-Division | C49: 0 | E49: Srikakulam II Town | F49: '19/2020' | G49: 420 IPC, 66-D,66-C ITA-2000-2008 | H49: 43854 | I49: Jan | J49: 2020 | K49: Cyber Crime offences | M49: Cyber Crime offences | N49: IPC | O49: Non-Grave | S49: UI | W49: For Suspect Verification | X49: Want of clues | Z49: Occurred prior to 24.01.2020 at 18.00 hrs, at Gara street, Srikakulam town and reported on 24.01.2020 at 18.00 hrs, wherein the complainant Piriya Mounika, D/o Narasimhulu, Age 23 years, Caste by Segidi, Gara street, Srikakulam town reported that she opened a job site in Noukari for work from house in her mobile intranet and she got a call from Noukari and got pdf files that if she typed the files from her house, they offered salary Rs.30,000/- per month to her. One month later, after completion of the work, she did not get any salary, in that she called to helpline on 15.01.2020, on that the accused A1- ADV. Anirudh Krishnan and A2- ADV. Karan replied that, they are the lawyer in that company and told that she submitted the work with some mistakes. Hence she liable to pay Rs. 80,000/- | AA49: Total | AB49: =IF(S49="UI",DATEDIF(H49,TODAY(),"D"),"") -> 2457 | AC49: =IF(S49="UI",IF(AB49>365,"Above 1 Year",IF(AND(AB49<=365,AB49>180),"Above 6 Months",IF(AND(AB49<=180,AB49>90),"Above 3 Months",IF(AND(AB49<=90,AB49>60),"Above 60 Days",IF(AND(AB49<=60,AB49>45),"45 to 60 Days","Below 45 Days"))))),"") -> Above 1 Year | AD49: =IF(Y49<>"",DATEDIF(Y49,TODAY(),"D"),"") | AE49: =IF(AD49<>"",IF(AD49>365,"Above 1 Year",IF(AND(AD49<=365,AD49>180),"Above 6 Months",IF(AND(AD49<=180,AD49>90),"Above 3 Months",IF(AND(AD49<=90,AD49>60),"Above 60 Days",IF(AND(AD49<=60,AD49>45),"45 to 60 Days","Below 45 Days"))))),"") | AF49: Cyber Cell | AG49: Srikakulam II Town,'19/2020' | AH49: =IF(X49="SC/PRC/CC No. Awaited","",AC49) -> Above 1 Year
A50: 49 | B50: Srikakulam Sub-Division | C50: Srikakulam Rural Circle | E50: Srikakulam Rural | F50: '44/2020' | G50: 379,420 IPC, 66-C,66-D ITA-2000-2008 | H50: 43878 | I50: Feb | J50: 2020 | K50: Cyber Crime offences | M50: Cyber Crime offences | N50: IPC | O50: Non-Grave | S50: UI | W50: For Suspect Verification | X50: For Suspect Verification | Z50: Occurred on 16.02.2020 at 14.55 hrs at plot no 22, Bhavani nagar, Chapurma (panchayathi) Srikakulam (M) and reported on 17.02.2020 at 10.00 hrs by the complainant Dabbeeru Srinivasrao s/o late Laxminarasimharao age 53 years, sistu karna by caste, plot no 22, Bhavani nagar, Chapuram Panchayathi, Srikakulam(M), wherein the accused caller 8001428248 contacted the complainant over phone, introducing himself and told to complainant your pay tm kyc is suspended you are download Quick support app and open in Google chrome, collected the pay tm CVV number and password in the guise of updating the KYC of the complainant in deceitful manner and also committed theft of an amount of Rs. 3,57,693/- from his SB account by transferring mode. | AA50: Total | AB50: =IF(S50="UI",DATEDIF(H50,TODAY(),"D"),"") -> 2433 | AC50: =IF(S50="UI",IF(AB50>365,"Above 1 Year",IF(AND(AB50<=365,AB50>180),"Above 6 Months",IF(AND(AB50<=180,AB50>90),"Above 3 Months",IF(AND(AB50<=90,AB50>60),"Above 60 Days",IF(AND(AB50<=60,AB50>45),"45 to 60 Days","Below 45 Days"))))),"") -> Above 1 Year | AD50: =IF(Y50<>"",DATEDIF(Y50,TODAY(),"D"),"") | AE50: =IF(AD50<>"",IF(AD50>365,"Above 1 Year",IF(AND(AD50<=365,AD50>180),"Above 6 Months",IF(AND(AD50<=180,AD50>90),"Above 3 Months",IF(AND(AD50<=90,AD50>60),"Above 60 Days",IF(AND(AD50<=60,AD50>45),"45 to 60 Days","Below 45 Days"))))),"") | AF50: Cyber Cell | AG50: Srikakulam Rural,'44/2020' | AH50: =IF(X50="SC/PRC/CC No. Awaited","",AC50) -> Above 1 Year
A51: 50 | B51: Tekkali Sub-Division | C51: Narasannapeta Circle | E51: Narasannapeta | F51: '38/2020' | G51: Woman Missing Person | H51: 43889 | I51: Feb | J51: 2020 | K51: Missing Cases | L51: Women Missing | M51: Missing Cases | N51: Missing | O51: Non-Grave | S51: UI | W51: Want of clues | X51: Want of clues | Z51: This is a case of woman missing that occurred on 20.01.2020 at about 07.00 hrs., at Bonthal veedhi, Narasannapeta town and reported on 28.02.2020 at 16.00 hrs., wherein the complainant Keviti Santharao, S/o Atchayya, 50 yrs, Jalari by caste, Bonthala veedhi, Narasannapeta town reported that his wife Keveti Sheshamma @ Shasamma, 44 yrs, effected to HIV since 10 years ago. On 20.01.2020 morning his wife left from house and informed to his mother viz. Thavitamma that she to go to parental house. After one week he go to mother in law house found his wife was not there. Later made searches about his wife but in vain, found thereby missing. | AA51: Total | AB51: =IF(S51="UI",DATEDIF(H51,TODAY(),"D"),"") -> 2422 | AC51: =IF(S51="UI",IF(AB51>365,"Above 1 Year",IF(AND(AB51<=365,AB51>180),"Above 6 Months",IF(AND(AB51<=180,AB51>90),"Above 3 Months",IF(AND(AB51<=90,AB51>60),"Above 60 Days",IF(AND(AB51<=60,AB51>45),"45 to 60 Days","Below 45 Days"))))),"") -> Above 1 Year | AD51: =IF(Y51<>"",DATEDIF(Y51,TODAY(),"D"),"") | AE51: =IF(AD51<>"",IF(AD51>365,"Above 1 Year",IF(AND(AD51<=365,AD51>180),"Above 6 Months",IF(AND(AD51<=180,AD51>90),"Above 3 Months",IF(AND(AD51<=90,AD51>60),"Above 60 Days",IF(AND(AD51<=60,AD51>45),"45 to 60 Days","Below 45 Days"))))),"") | AF51: D-4(Missing) | AG51: Narasannapeta,'38/2020' | AH51: =IF(X51="SC/PRC/CC No. Awaited","",AC51) -> Above 1 Year
A52: 51 | B52: Tekkali Sub-Division | C52: Tekkali Rural Circle | E52: Kotabommali | F52: '74/2020' | G52: 174 CrPC | H52: 43903 | I52: Mar | J52: 2020 | K52: 174 CrPC | M52: 174 CrPC | N52: 174 CrPC | O52: Non-Grave | S52: UI | W52: Want of clues | X52: Want of clues | Z52: Occurred on 13.03.2020 at about 11.00hrs, Vamsadara canal Bridge towards Jaggayyapeta, Akkayyavalasa village Kotabommali Mandal, reported on the same day at 12.00hrs. in which the complainant Byri satyavathi VRO Kothapeta village of Kotabommali mandal, reported that one unknown male dead body age about 50yrs was found in water of vamsadara canal, further suspecting that the dead body of deceased was accidentally drowned in water of Vamsadara canal. Deceased wearing white and red colour checks Lungi, Green colour cut bunion, | AA52: Total | AB52: =IF(S52="UI",DATEDIF(H52,TODAY(),"D"),"") -> 2408 | AC52: =IF(S52="UI",IF(AB52>365,"Above 1 Year",IF(AND(AB52<=365,AB52>180),"Above 6 Months",IF(AND(AB52<=180,AB52>90),"Above 3 Months",IF(AND(AB52<=90,AB52>60),"Above 60 Days",IF(AND(AB52<=60,AB52>45),"45 to 60 Days","Below 45 Days"))))),"") -> Above 1 Year | AD52: =IF(Y52<>"",DATEDIF(Y52,TODAY(),"D"),"") | AE52: =IF(AD52<>"",IF(AD52>365,"Above 1 Year",IF(AND(AD52<=365,AD52>180),"Above 6 Months",IF(AND(AD52<=180,AD52>90),"Above 3 Months",IF(AND(AD52<=90,AD52>60),"Above 60 Days",IF(AND(AD52<=60,AD52>45),"45 to 60 Days","Below 45 Days"))))),"") | AF52: D-4(174 CrPC) | AG52: Kotabommali,'74/2020' | AH52: =IF(X52="SC/PRC/CC No. Awaited","",AC52) -> Above 1 Year
A53: 52 | B53: Tekkali Sub-Division | C53: Narasannapeta Circle | E53: Narasannapeta | F53: '201/2020' | G53: Man Missing Person | H53: 43936 | I53: Apr | J53: 2020 | K53: Missing Cases | L53: Man Missing | M53: Missing Cases | N53: Missing | O53: Non-Grave | S53: UI | W53: Want of clues | X53: Want of clues | Z53: This is man missing on 23.03.2020 at 10.00 Hrs at Makivalasa Village, Narasannapeta Mandal and reported on 15.04.2020 at 14.00 Hrs wherein the complainant Viz., Reddi Simhachalam S/o Asirayya, Age 40 Yrs, Velama by caste, Makivalasa Village, Narasannapeta Mandal reported that his father namely Reddy Asirayya S/o Lt Appanna, Age 69 Yrs, has been suffering from mentally imbalance, left from house and did not return to home, thereby found missing. The complainant and relatives made searches about missing man but in vain. | AA53: Total | AB53: =IF(S53="UI",DATEDIF(H53,TODAY(),"D"),"") -> 2375 | AC53: =IF(S53="UI",IF(AB53>365,"Above 1 Year",IF(AND(AB53<=365,AB53>180),"Above 6 Months",IF(AND(AB53<=180,AB53>90),"Above 3 Months",IF(AND(AB53<=90,AB53>60),"Above 60 Days",IF(AND(AB53<=60,AB53>45),"45 to 60 Days","Below 45 Days"))))),"") -> Above 1 Year | AD53: =IF(Y53<>"",DATEDIF(Y53,TODAY(),"D"),"") | AE53: =IF(AD53<>"",IF(AD53>365,"Above 1 Year",IF(AND(AD53<=365,AD53>180),"Above 6 Months",IF(AND(AD53<=180,AD53>90),"Above 3 Months",IF(AND(AD53<=90,AD53>60),"Above 60 Days",IF(AND(AD53<=60,AD53>45),"45 to 60 Days","Below 45 Days"))))),"") | AF53: D-4(Missing) | AG53: Narasannapeta,'201/2020' | AH53: =IF(X53="SC/PRC/CC No. Awaited","",AC53) -> Above 1 Year
A54: 53 | B54: Srikakulam Sub-Division | C54: Amadalavalasa Circle | E54: Amadalavalasa | F54: '266/2020' | G54: Man Missing Person | H54: 43950 | I54: Apr | J54: 2020 | K54: Missing Cases | L54: Man Missing | M54: Missing Cases | N54: Missing | O54: Non-Grave | S54: UI | W54: Want of clues | X54: Want of clues | Z54: This is a case of man missing occurred on 12.04.2020 at 2100 hrs at Cheemalavalas (v), Amadalavalasa (m) wherein the complt. Pathina laxmi Narasamma, W/o. Appalanaidu, 35 yrs, Kalinga, Cheemalavalasa (v), Amadalavalasa (m) reported that her husband Pathina Appalanaidu, S/o Nilayya, 40 yrs, left from their housed for come on down the street and did not return home and he was found missing and his whereabouts are not known. | AA54: Total | AB54: =IF(S54="UI",DATEDIF(H54,TODAY(),"D"),"") -> 2361 | AC54: =IF(S54="UI",IF(AB54>365,"Above 1 Year",IF(AND(AB54<=365,AB54>180),"Above 6 Months",IF(AND(AB54<=180,AB54>90),"Above 3 Months",IF(AND(AB54<=90,AB54>60),"Above 60 Days",IF(AND(AB54<=60,AB54>45),"45 to 60 Days","Below 45 Days"))))),"") -> Above 1 Year | AD54: =IF(Y54<>"",DATEDIF(Y54,TODAY(),"D"),"") | AE54: =IF(AD54<>"",IF(AD54>365,"Above 1 Year",IF(AND(AD54<=365,AD54>180),"Above 6 Months",IF(AND(AD54<=180,AD54>90),"Above 3 Months",IF(AND(AD54<=90,AD54>60),"Above 60 Days",IF(AND(AD54<=60,AD54>45),"45 to 60 Days","Below 45 Days"))))),"") | AF54: D-4(Missing) | AG54: Amadalavalasa,'266/2020' | AH54: =IF(X54="SC/PRC/CC No. Awaited","",AC54) -> Above 1 Year
A55: 54 | B55: Srikakulam Sub-Division | C55: Srikakulam Rural Circle | E55: Srikakulam I Town | F55: '792/2020' | G55: 420 IPC, 66-C,66-D ITA-2000-2008 | H55: 43954 | I55: May | J55: 2020 | K55: Cyber Crime offences | M55: Cyber Crime offences | N55: IPC | O55: Non-Grave | S55: UI | W55: Want of clues | X55: Want of clues | Z55: occurred on 10-04-2020 at 1000 hrs at LBS colony, Plot no 412, Hanuman Enclaves, Srikakulam and reported on 03-05-2020 at 2015 hrs where in the complainant Thandasa Karthik S/o Late Jagadeswara Rao, 26 yrs, Caste by Vadddi, LBS Colony, Plot No 412, Hanuman Enclaves, Srikakulam reported that the accused Anil Kumar @ Manoranjan Mohantha Guntur his Verna Car advertised in OLX app for sales , the complainant approached to purchase and contact through phone and deal an amount Rs 2,10,000/- after he send an amount Rs 35, 500/- through phone pay to (7797985178) . On the same day at 2000 hrs that the accused call through his phone no 9306743706 for remaining amount Rs 1, 70,500/-, and he said I am reaching near to Ranastalam, send remaining amount through phone pay and hand over the | AA55: Total | AB55: =IF(S55="UI",DATEDIF(H55,TODAY(),"D"),"") -> 2357 | AC55: =IF(S55="UI",IF(AB55>365,"Above 1 Year",IF(AND(AB55<=365,AB55>180),"Above 6 Months",IF(AND(AB55<=180,AB55>90),"Above 3 Months",IF(AND(AB55<=90,AB55>60),"Above 60 Days",IF(AND(AB55<=60,AB55>45),"45 to 60 Days","Below 45 Days"))))),"") -> Above 1 Year | AD55: =IF(Y55<>"",DATEDIF(Y55,TODAY(),"D"),"") | AE55: =IF(AD55<>"",IF(AD55>365,"Above 1 Year",IF(AND(AD55<=365,AD55>180),"Above 6 Months",IF(AND(AD55<=180,AD55>90),"Above 3 Months",IF(AND(AD55<=90,AD55>60),"Above 60 Days",IF(AND(AD55<=60,AD55>45),"45 to 60 Days","Below 45 Days"))))),"") | AF55: Cyber Cell | AG55: Srikakulam I Town,'792/2020' | AH55: =IF(X55="SC/PRC/CC No. Awaited","",AC55) -> Above 1 Year
A56: 55 | B56: Srikakulam Sub-Division | C56: Srikakulam Rural Circle | E56: Srikakulam I Town | F56: '1013/2020' | G56: 420 IPC, 66-C ITA-2000-2008 | H56: 43973 | I56: May | J56: 2020 | K56: Cyber Crime offences | M56: Cyber Crime offences | N56: IPC | O56: Non-Grave | S56: UI | W56: Want of clues | X56: Want of clues | Z56: Occurred on prior to 22-05-2020 at State Bank of India, Main Branch, Srikakulam town and reported on 22-05-220 at 1430 in which the complainant Potnuru Rama Rao S/o Kameswara Rao, 33 yrs,Vysaya by caste, Arasavallai, Near Ammavari Temple,Srikakulam reported that he had an account in SBI main Branck Srikakulam bearing A/C No 30379983462 , on 08-04-2020 an unknown persons transfer the amount of Rs 999/-from his account through UPI and same day after 10 minits again transfer the amout Rs 2999/- in a same manner. Then he approached to bank authorities than bank manger said that this is UPI transtation, so that the amout credit to your account. Then Again on 13-04-2020 Rs 19999/- transfer the amount from his account through UPI and also again same day 18000/- tranfered. After that h | AA56: Total | AB56: =IF(S56="UI",DATEDIF(H56,TODAY(),"D"),"") -> 2338 | AC56: =IF(S56="UI",IF(AB56>365,"Above 1 Year",IF(AND(AB56<=365,AB56>180),"Above 6 Months",IF(AND(AB56<=180,AB56>90),"Above 3 Months",IF(AND(AB56<=90,AB56>60),"Above 60 Days",IF(AND(AB56<=60,AB56>45),"45 to 60 Days","Below 45 Days"))))),"") -> Above 1 Year | AD56: =IF(Y56<>"",DATEDIF(Y56,TODAY(),"D"),"") | AE56: =IF(AD56<>"",IF(AD56>365,"Above 1 Year",IF(AND(AD56<=365,AD56>180),"Above 6 Months",IF(AND(AD56<=180,AD56>90),"Above 3 Months",IF(AND(AD56<=90,AD56>60),"Above 60 Days",IF(AND(AD56<=60,AD56>45),"45 to 60 Days","Below 45 Days"))))),"") | AF56: Cyber Cell | AG56: Srikakulam I Town,'1013/2020' | AH56: =IF(X56="SC/PRC/CC No. Awaited","",AC56) -> Above 1 Year
A57: 56 | B57: Srikakulam Sub-Division | C57: Srikakulam Rural Circle | E57: Srikakulam Rural | F57: '457/2020' | G57: 420 IPC, 66-D ITA-2000-2008 | H57: 43973 | I57: May | J57: 2020 | K57: Cyber Crime offences | M57: Cyber Crime offences | N57: IPC | O57: Non-Grave | S57: UI | W57: For Suspect Verification | X57: For Suspect Verification | Z57: Occurred on 16.05.2020 at 1704 hrs at SBI Bank, Ramalaxmana Branch, Srikakulam and reported on the same day at 1600 hrs by the complainant Sadhu Kameswara Rao S/o Krishna, 27 yrs, P.Velama, Sadhupeta (V) Kallepalli (Panchaaythi), Srikakulam(M) wherein an unknown culprit who is the user of mobile No. 7866846228 made phone call to the complainant and introduced himself as Bank Manager and made the complainant to believe that, the ATM of the complainant was blocked, in order to apply for a new ATM, the culprit asked the complainant to download a “quick support App” in deceitful manner and when the complainant down loaded the said App into his mobile, the culprit transferred an amount of Rs. 88, 859/- from his SB AC.No. 32045070671 (SBI Bank, Ramalaxmana Branch) as well as Rs. 9 | AA57: Total | AB57: =IF(S57="UI",DATEDIF(H57,TODAY(),"D"),"") -> 2338 | AC57: =IF(S57="UI",IF(AB57>365,"Above 1 Year",IF(AND(AB57<=365,AB57>180),"Above 6 Months",IF(AND(AB57<=180,AB57>90),"Above 3 Months",IF(AND(AB57<=90,AB57>60),"Above 60 Days",IF(AND(AB57<=60,AB57>45),"45 to 60 Days","Below 45 Days"))))),"") -> Above 1 Year | AD57: =IF(Y57<>"",DATEDIF(Y57,TODAY(),"D"),"") | AE57: =IF(AD57<>"",IF(AD57>365,"Above 1 Year",IF(AND(AD57<=365,AD57>180),"Above 6 Months",IF(AND(AD57<=180,AD57>90),"Above 3 Months",IF(AND(AD57<=90,AD57>60),"Above 60 Days",IF(AND(AD57<=60,AD57>45),"45 to 60 Days","Below 45 Days"))))),"") | AF57: Cyber Cell | AG57: Srikakulam Rural,'457/2020' | AH57: =IF(X57="SC/PRC/CC No. Awaited","",AC57) -> Above 1 Year
A58: 57 | B58: Srikakulam Sub-Division | C58: Amadalavalasa Circle | E58: Amadalavalasa | F58: '411/2020' | G58: 420 IPC, 66-D,66-C ITA-2000-2008 | H58: 43986 | I58: Jun | J58: 2020 | K58: Cyber Crime offences | M58: Cyber Crime offences | N58: IPC | O58: Non-Grave | S58: UI | W58: For Suspect Verification | X58: For Suspect Verification | Z58: This is a case of cheating by personation by using communication device Occurred in between 31.05.2020 to 01.06.2020 at I.J Naidu Colony, Amadalavalasa and reported on 04.06.2020 at 1000 hrs in which the complainant Gurugubelli Avinash, S/o Murali, 19 yrs, Kalinga, I.J Naidu colony, Amadalavalasa reported that on 31.05.2020 on face book one add., iphone 11 series only at Rs. 40000/- then he opened that link i.e https://www.luxurylogisticsint.com then he chatted to one unknown person in Messenger/what’s app. The complainant trusts their words and he sent to different accounts around 70000/- through Google pay app at different times, said amount and they used to chat him frequently through what’s app No. 9494419678. The complainant realized that they cheated him online fraud and reported | AA58: Total | AB58: =IF(S58="UI",DATEDIF(H58,TODAY(),"D"),"") -> 2325 | AC58: =IF(S58="UI",IF(AB58>365,"Above 1 Year",IF(AND(AB58<=365,AB58>180),"Above 6 Months",IF(AND(AB58<=180,AB58>90),"Above 3 Months",IF(AND(AB58<=90,AB58>60),"Above 60 Days",IF(AND(AB58<=60,AB58>45),"45 to 60 Days","Below 45 Days"))))),"") -> Above 1 Year | AD58: =IF(Y58<>"",DATEDIF(Y58,TODAY(),"D"),"") | AE58: =IF(AD58<>"",IF(AD58>365,"Above 1 Year",IF(AND(AD58<=365,AD58>180),"Above 6 Months",IF(AND(AD58<=180,AD58>90),"Above 3 Months",IF(AND(AD58<=90,AD58>60),"Above 60 Days",IF(AND(AD58<=60,AD58>45),"45 to 60 Days","Below 45 Days"))))),"") | AF58: Cyber Cell | AG58: Amadalavalasa,'411/2020' | AH58: =IF(X58="SC/PRC/CC No. Awaited","",AC58) -> Above 1 Year
A59: 58 | B59: Srikakulam Sub-Division | C59: 0 | E59: Srikakulam II Town | F59: '1091/2020' | G59: 420 IPC, 66-D,66-C ITA-2000-2008 | H59: 43994 | I59: Jun | J59: 2020 | K59: Cyber Crime offences | M59: Cyber Crime offences | N59: IPC | O59: Non-Grave | S59: UI | W59: For Suspect Verification | X59: Want of clues | Z59: Occurred in between 11.06.2020 at 09.30 hrs and 12.06.2020 at 07.00 hrs, at Gujarathipeta, Srikakulam town, and reported on 12.06.2020 at 20.00 hrs, wherein the complainant Vemuri Bala Krishna, S/o Suryanarayana, Age 66 years, Caste by Brahmin, Gujarathipeta, Srikakulam town reported that he had SBI bank account at Ramalaxmana branch, Srikakulam town, he received phone call from unknown person phone number 9908987015 to his phone number 944838707, on 11.06.2020 at about 09.30 hrs and he told that he is calling him for ATM enquiry and one OTP will come, then he has to tell that OTP, after receiving OTP, the complainant told that OTP to the unknown person, then he received a message from bank that Rs. 4999/- was withdrawn from his account. Then the complainant called to that unknow person a | AA59: Total | AB59: =IF(S59="UI",DATEDIF(H59,TODAY(),"D"),"") -> 2317 | AC59: =IF(S59="UI",IF(AB59>365,"Above 1 Year",IF(AND(AB59<=365,AB59>180),"Above 6 Months",IF(AND(AB59<=180,AB59>90),"Above 3 Months",IF(AND(AB59<=90,AB59>60),"Above 60 Days",IF(AND(AB59<=60,AB59>45),"45 to 60 Days","Below 45 Days"))))),"") -> Above 1 Year | AD59: =IF(Y59<>"",DATEDIF(Y59,TODAY(),"D"),"") | AE59: =IF(AD59<>"",IF(AD59>365,"Above 1 Year",IF(AND(AD59<=365,AD59>180),"Above 6 Months",IF(AND(AD59<=180,AD59>90),"Above 3 Months",IF(AND(AD59<=90,AD59>60),"Above 60 Days",IF(AND(AD59<=60,AD59>45),"45 to 60 Days","Below 45 Days"))))),"") | AF59: Cyber Cell | AG59: Srikakulam II Town,'1091/2020' | AH59: =IF(X59="SC/PRC/CC No. Awaited","",AC59) -> Above 1 Year
A60: 59 | B60: Tekkali Sub-Division | C60: Narasannapeta Circle | E60: Narasannapeta | F60: '407/2020' | G60: Man Missing Person | H60: 43998 | I60: Jun | J60: 2020 | K60: Missing Cases | L60: Man Missing | M60: Missing Cases | N60: Missing | O60: Non-Grave | S60: UI | W60: Want of clues | X60: Want of clues | Z60: This is a case of Man missing that occurred on 05.06.2020 at about 05.00 hrs at Hadco colony, Narasannapeta town and reported on 16.06.2020 at 09.00 hrs, wherein the complainant Kotipalli Satyannarayana, S/o late Papayya, 65 yrs, Telukala by caste, Tekkalipadu (v), Jalumuru (m) reported that his maternal uncle viz. Palamuri Ramamurthy, S/o Gurumurthy, 75 yrs, went to natural calls and did return. Later made enquiries about his maternal uncle but in vain found thereby missing. | AA60: Total | AB60: =IF(S60="UI",DATEDIF(H60,TODAY(),"D"),"") -> 2313 | AC60: =IF(S60="UI",IF(AB60>365,"Above 1 Year",IF(AND(AB60<=365,AB60>180),"Above 6 Months",IF(AND(AB60<=180,AB60>90),"Above 3 Months",IF(AND(AB60<=90,AB60>60),"Above 60 Days",IF(AND(AB60<=60,AB60>45),"45 to 60 Days","Below 45 Days"))))),"") -> Above 1 Year | AD60: =IF(Y60<>"",DATEDIF(Y60,TODAY(),"D"),"") | AE60: =IF(AD60<>"",IF(AD60>365,"Above 1 Year",IF(AND(AD60<=365,AD60>180),"Above 6 Months",IF(AND(AD60<=180,AD60>90),"Above 3 Months",IF(AND(AD60<=90,AD60>60),"Above 60 Days",IF(AND(AD60<=60,AD60>45),"45 to 60 Days","Below 45 Days"))))),"") | AF60: D-4(Missing) | AG60: Narasannapeta,'407/2020' | AH60: =IF(X60="SC/PRC/CC No. Awaited","",AC60) -> Above 1 Year
A61: 60 | B61: Srikakulam Sub-Division | C61: Srikakulam Rural Circle | E61: Gara | F61: '265/2020' | G61: 420,419 IPC, 66-D ITA-2000-2008 | H61: 44007 | I61: Jun | J61: 2020 | K61: Cyber Crime offences | M61: Cyber Crime offences | N61: IPC | O61: Non-Grave | S61: UI | W61: Want of clues | X61: Want of clues | Z61: Occurred prior to 25.06.2020 online by staying at Pusarlapadu village of Gara Mandal and reported on 25.06.2020 at 11.00 hrs., in which the complainant Aravala Saisurya Anurag s/o Mohanarao, 20 years, Aravala by caste, Pusarlapadu village, Gara Mandal reported that he pursued B.Tech. and searching for job. Due to covid-19 he is staying at home and while searching for jobs on quikar.com observed job advertisement of MYC company. In which the company offered typing work of Captcha codes per every 10,000 codes they will pay Rs. 30,000/- and gave relaxation for 1000 type mistakes for every 10,000 codes, otherwise, he has to pay fine of Rs. 6900/- for type mistakes beyond 1000 in every 10,000 codes and also if he resile back from the job agreement. On completion of agreement | AA61: Total | AB61: =IF(S61="UI",DATEDIF(H61,TODAY(),"D"),"") -> 2304 | AC61: =IF(S61="UI",IF(AB61>365,"Above 1 Year",IF(AND(AB61<=365,AB61>180),"Above 6 Months",IF(AND(AB61<=180,AB61>90),"Above 3 Months",IF(AND(AB61<=90,AB61>60),"Above 60 Days",IF(AND(AB61<=60,AB61>45),"45 to 60 Days","Below 45 Days"))))),"") -> Above 1 Year | AD61: =IF(Y61<>"",DATEDIF(Y61,TODAY(),"D"),"") | AE61: =IF(AD61<>"",IF(AD61>365,"Above 1 Year",IF(AND(AD61<=365,AD61>180),"Above 6 Months",IF(AND(AD61<=180,AD61>90),"Above 3 Months",IF(AND(AD61<=90,AD61>60),"Above 60 Days",IF(AND(AD61<=60,AD61>45),"45 to 60 Days","Below 45 Days"))))),"") | AF61: Cyber Cell | AG61: Gara,'265/2020' | AH61: =IF(X61="SC/PRC/CC No. Awaited","",AC61) -> Above 1 Year
A62: 61 | B62: Kasibugga Sub-Division | C62: Itchapuram Circle | E62: Kaviti | F62: '195/2020' | G62: Man Missing Person | H62: 44035 | I62: Jul | J62: 2020 | K62: Missing Cases | L62: Man Missing | M62: Missing Cases | N62: Missing | O62: Non-Grave | S62: UI | W62: Want of clues | X62: Want of clues | Z62: This is case of man missing., occurred on 19.07.2020 at 08:AM at his residence of Kumapuram village of Kaviti Mandal and reported on 23.07.2020 at 18:30hrs by the Ketha Giri, S/o Laxminarayan, age 30 yrs, with content that his father left for market from his house and has not returned so far. After making several enquiries in and around of his residence and his relatives and found missing. His father was worn black colored pant and biscuit colored shirt and normal complexion and height is 153 C.M mentioned in report for identification. On this day he came to P.S and lodged written report to trace out his father. | AA62: Total | AB62: =IF(S62="UI",DATEDIF(H62,TODAY(),"D"),"") -> 2276 | AC62: =IF(S62="UI",IF(AB62>365,"Above 1 Year",IF(AND(AB62<=365,AB62>180),"Above 6 Months",IF(AND(AB62<=180,AB62>90),"Above 3 Months",IF(AND(AB62<=90,AB62>60),"Above 60 Days",IF(AND(AB62<=60,AB62>45),"45 to 60 Days","Below 45 Days"))))),"") -> Above 1 Year | AD62: =IF(Y62<>"",DATEDIF(Y62,TODAY(),"D"),"") | AE62: =IF(AD62<>"",IF(AD62>365,"Above 1 Year",IF(AND(AD62<=365,AD62>180),"Above 6 Months",IF(AND(AD62<=180,AD62>90),"Above 3 Months",IF(AND(AD62<=90,AD62>60),"Above 60 Days",IF(AND(AD62<=60,AD62>45),"45 to 60 Days","Below 45 Days"))))),"") | AF62: D-4(Missing) | AG62: Kaviti,'195/2020' | AH62: =IF(X62="SC/PRC/CC No. Awaited","",AC62) -> Above 1 Year
A63: 62 | B63: Srikakulam Sub-Division | C63: Srikakulam Rural Circle | E63: Srikakulam Rural | F63: '587/2020' | G63: 420 IPC, 66-D ITA-2000-2008 | H63: 44041 | I63: Jul | J63: 2020 | K63: Cyber Crime offences | M63: Cyber Crime offences | N63: IPC | O63: Non-Grave | S63: UI | W63: For Suspect Verification | X63: For Suspect Verification | Z63: Occurred on 27.07.2020 at 16.07 hrs at Voppangi village, Srikakulam and reported on 29.07.2020 at 16.00 hrs by the complainant Golivi Dhivya w/o Simhachalam, age 29 years, caste by Velama, Gondu veedhi, Vopangi village, Srikakulam, reported that on 25.07.2020 morning she was ordered one multiple Sari for Rs.1999/- in Amazon App through her mobile Airtel No.9666628285 and at the evening it was cancelled by her but she did not receive cancellation I.D No. from Amazon authorities. She tried to consult with the Amazon customer-care through App but that number did not work and hence on the next day i.e. on 26.07.2020 evening she was searched for help-line number of Amazon through Google web and contacted with Ph.No.8392051429 available in Amazon.in help and enquired about the refund of her sari | AA63: Total | AB63: =IF(S63="UI",DATEDIF(H63,TODAY(),"D"),"") -> 2270 | AC63: =IF(S63="UI",IF(AB63>365,"Above 1 Year",IF(AND(AB63<=365,AB63>180),"Above 6 Months",IF(AND(AB63<=180,AB63>90),"Above 3 Months",IF(AND(AB63<=90,AB63>60),"Above 60 Days",IF(AND(AB63<=60,AB63>45),"45 to 60 Days","Below 45 Days"))))),"") -> Above 1 Year | AD63: =IF(Y63<>"",DATEDIF(Y63,TODAY(),"D"),"") | AE63: =IF(AD63<>"",IF(AD63>365,"Above 1 Year",IF(AND(AD63<=365,AD63>180),"Above 6 Months",IF(AND(AD63<=180,AD63>90),"Above 3 Months",IF(AND(AD63<=90,AD63>60),"Above 60 Days",IF(AND(AD63<=60,AD63>45),"45 to 60 Days","Below 45 Days"))))),"") | AF63: Cyber Cell | AG63: Srikakulam Rural,'587/2020' | AH63: =IF(X63="SC/PRC/CC No. Awaited","",AC63) -> Above 1 Year
A64: 63 | B64: Srikakulam Sub-Division | C64: Srikakulam Rural Circle | E64: Srikakulam Rural | F64: '602/2020' | G64: 420 IPC, 66-D ITA-2000-2008 | H64: 44049 | I64: Aug | J64: 2020 | K64: Cyber Crime offences | M64: Cyber Crime offences | N64: IPC | O64: Non-Grave | S64: UI | W64: For Suspect Verification | X64: For Suspect Verification | Z64: Occurred on prior to 04.08.2020, at Visakha A colony, Srikakulam mandal and reported on 06.08.2020 at 10.00 hours, where in the complainant Amit kumar Yadav s/o Somdutt Yadav, age 26 years, caste by Ahir, R/o. H.No 2-12, at Visakha A colony, Srikakulam mandal and dist, N/o Gugaria village, THE-BEHROR, Alwar dist, Rajasthan state, he was working as Trained Graduate Teacher at Kendhriya vidhyalayam situated at Peddapadu village, Srkakulam, On 25.07.2020 while he was verifying his face book , observed an advertisement from BAJAJ FINANCE application by filling his name and phone number for sanction of five lakes loan. On 30.07.2020 he received a phone call from mobile number 8167640245 to his mobile number 9306685487 introduce himself as Bajaj Execute office from Mumbai spoke in Hindi an | AA64: Total | AB64: =IF(S64="UI",DATEDIF(H64,TODAY(),"D"),"") -> 2262 | AC64: =IF(S64="UI",IF(AB64>365,"Above 1 Year",IF(AND(AB64<=365,AB64>180),"Above 6 Months",IF(AND(AB64<=180,AB64>90),"Above 3 Months",IF(AND(AB64<=90,AB64>60),"Above 60 Days",IF(AND(AB64<=60,AB64>45),"45 to 60 Days","Below 45 Days"))))),"") -> Above 1 Year | AD64: =IF(Y64<>"",DATEDIF(Y64,TODAY(),"D"),"") | AE64: =IF(AD64<>"",IF(AD64>365,"Above 1 Year",IF(AND(AD64<=365,AD64>180),"Above 6 Months",IF(AND(AD64<=180,AD64>90),"Above 3 Months",IF(AND(AD64<=90,AD64>60),"Above 60 Days",IF(AND(AD64<=60,AD64>45),"45 to 60 Days","Below 45 Days"))))),"") | AF64: Cyber Cell | AG64: Srikakulam Rural,'602/2020' | AH64: =IF(X64="SC/PRC/CC No. Awaited","",AC64) -> Above 1 Year
A65: 64 | B65: Tekkali Sub-Division | C65: 0 | E65: Tekkali PS | F65: '482/2020' | G65: 174 CrPC | H65: 44050 | I65: Aug | J65: 2020 | K65: 174 CrPC | M65: 174 CrPC | N65: 174 CrPC | O65: Non-Grave | S65: UI | W65: Want of clues | X65: Want of clues | Z65: This is a case of Un natural death(death due to hanging), Refer un-natural death case due to hanging (.) Occurred prior to 06-08-2020 at 22.00hours and reported on 07-08-2020 at 09.00hours, wherein the Complt., Shri Matta Jogarao, S/o Thammayya, 42yrs, SC (Mala) by caste of Nandigam (v) & (m), VRO/K.Kothuru (v) of Tekkali (m) reported that he has been received a phone call from Shri Pranabkumar Biswal, owner of NRL Dhaba situated beside NH-16 road, K.Kothuru (v), Tekkali (m) and stated that due to lock-down period ie about 4 months ago, one person was proceeding from Chennai to West Bengal by walking meanwhile he stopped at his NRL Dhaba and requested to provide food due to suffering from weakness as well as swelling of his both legs, Accordingly, he provided food. Soon after, the s | AA65: Total | AB65: =IF(S65="UI",DATEDIF(H65,TODAY(),"D"),"") -> 2261 | AC65: =IF(S65="UI",IF(AB65>365,"Above 1 Year",IF(AND(AB65<=365,AB65>180),"Above 6 Months",IF(AND(AB65<=180,AB65>90),"Above 3 Months",IF(AND(AB65<=90,AB65>60),"Above 60 Days",IF(AND(AB65<=60,AB65>45),"45 to 60 Days","Below 45 Days"))))),"") -> Above 1 Year | AD65: =IF(Y65<>"",DATEDIF(Y65,TODAY(),"D"),"") | AE65: =IF(AD65<>"",IF(AD65>365,"Above 1 Year",IF(AND(AD65<=365,AD65>180),"Above 6 Months",IF(AND(AD65<=180,AD65>90),"Above 3 Months",IF(AND(AD65<=90,AD65>60),"Above 60 Days",IF(AND(AD65<=60,AD65>45),"45 to 60 Days","Below 45 Days"))))),"") | AF65: D-4(174 CrPC) | AG65: Tekkali PS,'482/2020' | AH65: =IF(X65="SC/PRC/CC No. Awaited","",AC65) -> Above 1 Year
A66: 65 | B66: Srikakulam Sub-Division | C66: J.R.Puram Circle | E66: J.R.Puram | F66: '598/2020' | G66: 304(A) IPC | H66: 44054 | I66: Aug | J66: 2020 | K66: Fatal Road Accidents | M66: Road Accidents | N66: IPC | O66: Non-Grave | S66: UI | W66: Being Charged | X66: SC/PRC/CC No. Awaited | Y66: 46300 | Z66: Occurred on 11.08.2020 at about 14:00 hours on NH 16 road, near Varisam village junction, Ranasthalam mandal and reported on the same day at 15:00 hours by the complainant Puligurthu Subrahmanyam, Village Revenue Officer, Pydibheemavaram village. In which he stated that, he was a received a message while he was in duty, that is a unknown vehicle was dashed against one unknown person at Varisam junction on Srikakulam-Visakhapatnam NH 16 road and flee away from the spot. Immediately he rushed to spot and verified that, a male beggar, aged about 50-55 years was got fatal injuries on his head and other parts of the body and died on the road. He reported the matter to police for taking necessary action. | AA66: Total | AB66: =IF(S66="UI",DATEDIF(H66,TODAY(),"D"),"") -> 2257 | AC66: =IF(S66="UI",IF(AB66>365,"Above 1 Year",IF(AND(AB66<=365,AB66>180),"Above 6 Months",IF(AND(AB66<=180,AB66>90),"Above 3 Months",IF(AND(AB66<=90,AB66>60),"Above 60 Days",IF(AND(AB66<=60,AB66>45),"45 to 60 Days","Below 45 Days"))))),"") -> Above 1 Year | AD66: =IF(Y66<>"",DATEDIF(Y66,TODAY(),"D"),"") -> 11 | AE66: =IF(AD66<>"",IF(AD66>365,"Above 1 Year",IF(AND(AD66<=365,AD66>180),"Above 6 Months",IF(AND(AD66<=180,AD66>90),"Above 3 Months",IF(AND(AD66<=90,AD66>60),"Above 60 Days",IF(AND(AD66<=60,AD66>45),"45 to 60 Days","Below 45 Days"))))),"") -> Below 45 Days | AF66: DTRB | AG66: J.R.Puram,'598/2020' | AH66: =IF(X66="SC/PRC/CC No. Awaited","",AC66)
A67: 66 | B67: Srikakulam Sub-Division | C67: Amadalavalasa Circle | E67: Ponduru | F67: '430/2020' | G67: 354(a) IPC | H67: 44067 | I67: Aug | J67: 2020 | K67: Outraging the modesty of women | M67: Crime Against Women | N67: IPC | O67: Non-Grave | S67: UI | W67: Court Orders Pending | X67: Court Orders Pending | Y67: 45899 | Z67: Occurred prior to 24.08.20 at 10.30hrs at Ponduru PS, Ponduru mandal and reported on the same day at 11.00hrs by one Boddepalli Meenakshi W/o lt Ramana, age 35 years, kalinga by caste, R/o Rapaka jn Pomduru village and mandal and native of Dhavalapeta village of G.sigadam mandal in which she reported that the sub inspector of police Ponduru PS intentionally welcomed her to his house to fulfill his sexual desire in order to not to file criminal cases against her and her father Annepu Apparao who were caught red handedly while in possession of illicit liquor. | AA67: Total | AB67: =IF(S67="UI",DATEDIF(H67,TODAY(),"D"),"") -> 2244 | AC67: =IF(S67="UI",IF(AB67>365,"Above 1 Year",IF(AND(AB67<=365,AB67>180),"Above 6 Months",IF(AND(AB67<=180,AB67>90),"Above 3 Months",IF(AND(AB67<=90,AB67>60),"Above 60 Days",IF(AND(AB67<=60,AB67>45),"45 to 60 Days","Below 45 Days"))))),"") -> Above 1 Year | AD67: =IF(Y67<>"",DATEDIF(Y67,TODAY(),"D"),"") -> 412 | AE67: =IF(AD67<>"",IF(AD67>365,"Above 1 Year",IF(AND(AD67<=365,AD67>180),"Above 6 Months",IF(AND(AD67<=180,AD67>90),"Above 3 Months",IF(AND(AD67<=90,AD67>60),"Above 60 Days",IF(AND(AD67<=60,AD67>45),"45 to 60 Days","Below 45 Days"))))),"") -> Above 1 Year | AF67: D-5(CAW) | AG67: Ponduru,'430/2020' | AH67: =IF(X67="SC/PRC/CC No. Awaited","",AC67) -> Above 1 Year
A68: 67 | B68: Srikakulam Sub-Division | C68: Amadalavalasa Circle | E68: Amadalavalasa | F68: '508/2020' | G68: 420 IPC, 66-C,66-D ITA-2000-2008 | H68: 44087 | I68: Sep | J68: 2020 | K68: Cyber Crime offences | M68: Cyber Crime offences | N68: IPC | O68: Non-Grave | S68: UI | W68: Want of clues | X68: Want of clues | Z68: Occurred on 09-09-2020 at 11:46 hours to 11:53 hours at Railway Quarters , Mettakkivalasa , Amadalavalasa Town, that the complainant by name J Nagabhushana rao, S/o Viswanadh, Age 40 yrs, SC-Caste, Railway Quarters, Amadalavalasa that the complainant have debit 19-08-2020 at 10:58 hours reward Rs. 1,999/- showing on his mobile on 09-09-2020 the complainant calls to SBI Customer care then told him to contact Phone pay hence the complainant contact with phone pay customer care with the numbers of 08068727374, 7318816085, 8388060742 and 7679415275 that phone pay customer said to type Naga2000@UCO and type 88888 in along with UPI PIN and doing 11111 also same hence the complainant debit Rs. 99,999/- after 15 minutes he found that is fraud call then after he told downloading the “ Any Desk “ an | AA68: Total | AB68: =IF(S68="UI",DATEDIF(H68,TODAY(),"D"),"") -> 2224 | AC68: =IF(S68="UI",IF(AB68>365,"Above 1 Year",IF(AND(AB68<=365,AB68>180),"Above 6 Months",IF(AND(AB68<=180,AB68>90),"Above 3 Months",IF(AND(AB68<=90,AB68>60),"Above 60 Days",IF(AND(AB68<=60,AB68>45),"45 to 60 Days","Below 45 Days"))))),"") -> Above 1 Year | AD68: =IF(Y68<>"",DATEDIF(Y68,TODAY(),"D"),"") | AE68: =IF(AD68<>"",IF(AD68>365,"Above 1 Year",IF(AND(AD68<=365,AD68>180),"Above 6 Months",IF(AND(AD68<=180,AD68>90),"Above 3 Months",IF(AND(AD68<=90,AD68>60),"Above 60 Days",IF(AND(AD68<=60,AD68>45),"45 to 60 Days","Below 45 Days"))))),"") | AF68: Cyber Cell | AG68: Amadalavalasa,'508/2020' | AH68: =IF(X68="SC/PRC/CC No. Awaited","",AC68) -> Above 1 Year
A69: 68 | B69: Srikakulam Sub-Division | C69: Srikakulam Rural Circle | E69: Srikakulam I Town | F69: '1324/2020' | G69: 419,420 IPC, 66-D ITA-2000-2008 | H69: 44102 | I69: Sep | J69: 2020 | K69: Cyber Crime offences | M69: Cyber Crime offences | N69: IPC | O69: Non-Grave | S69: UI | W69: Want of clues | X69: Want of clues | Z69: On Occured 22-09-2020 at 1540 p.m and the reported the 28-09-2020 at 1700 hours , the complainant Bagadhi Divakar s/o Bagadhi Narsinga rao, age 50 years, caste by Kalinga, Adityanilayam, Arsavelli main road, Srikakulam received phone call information No. 9682024765 from an unknown person believing himself as calling from Customer care, Axis Bank, made him to reveal the number on his credit card and believe his words he also informed the OTP Number, later an amount of Rs.58,499/- (rupees fifty eight thousand four hundred and ninety nine only) was transferred to the account of Merchant Navy PAYTM RAZ* Global toys Paytm Wallet from his account on 22-09-2020 from 15-40 hrs to 16-02 hrs by using electronic device. Hence the complainant lodged a report toestablish the identity of fraudst | AA69: Total | AB69: =IF(S69="UI",DATEDIF(H69,TODAY(),"D"),"") -> 2209 | AC69: =IF(S69="UI",IF(AB69>365,"Above 1 Year",IF(AND(AB69<=365,AB69>180),"Above 6 Months",IF(AND(AB69<=180,AB69>90),"Above 3 Months",IF(AND(AB69<=90,AB69>60),"Above 60 Days",IF(AND(AB69<=60,AB69>45),"45 to 60 Days","Below 45 Days"))))),"") -> Above 1 Year | AD69: =IF(Y69<>"",DATEDIF(Y69,TODAY(),"D"),"") | AE69: =IF(AD69<>"",IF(AD69>365,"Above 1 Year",IF(AND(AD69<=365,AD69>180),"Above 6 Months",IF(AND(AD69<=180,AD69>90),"Above 3 Months",IF(AND(AD69<=90,AD69>60),"Above 60 Days",IF(AND(AD69<=60,AD69>45),"45 to 60 Days","Below 45 Days"))))),"") | AF69: Cyber Cell | AG69: Srikakulam I Town,'1324/2020' | AH69: =IF(X69="SC/PRC/CC No. Awaited","",AC69) -> Above 1 Year
A70: 69 | B70: Srikakulam Sub-Division | C70: Srikakulam Rural Circle | E70: Srikakulam I Town | F70: '1346/2020' | G70: Man Missing Person | H70: 44114 | I70: Oct | J70: 2020 | K70: Missing Cases | L70: Man Missing | M70: Missing Cases | N70: Missing | O70: Non-Grave | S70: UI | W70: Want of clues | X70: Want of clues | Z70: Occurred on 10-03-2020 at 18-00 hrs Subbalakshmi Apartment, Flat No.401, Mondeti Veedhi, Srikakulam wherein the complainant Jami Kavya W/o Madhusudhana Rao, age 24 yrs, Vysya by caste, Subbalakshmi Apartment, Flat No.401, Mondeti Veedhi, Srikakulam lodged a report stating that her husband Jami Madhusudhana Rao S/o Vasudevarao, age 38 yrs left from the above address by saying to go to Tirupathi, the missing person stayed in contact with her for 10 days after leaving from home, now he is not in phone contact and he didn’t return home so far and found missing and he is whereabouts are not known (.) She alleged that her mother-in-law and sister-in-law know about his missing (.) Efforts are being continued to trace the missing man (.) Case is U.I. for want of clues(.) | AA70: Total | AB70: =IF(S70="UI",DATEDIF(H70,TODAY(),"D"),"") -> 2197 | AC70: =IF(S70="UI",IF(AB70>365,"Above 1 Year",IF(AND(AB70<=365,AB70>180),"Above 6 Months",IF(AND(AB70<=180,AB70>90),"Above 3 Months",IF(AND(AB70<=90,AB70>60),"Above 60 Days",IF(AND(AB70<=60,AB70>45),"45 to 60 Days","Below 45 Days"))))),"") -> Above 1 Year | AD70: =IF(Y70<>"",DATEDIF(Y70,TODAY(),"D"),"") | AE70: =IF(AD70<>"",IF(AD70>365,"Above 1 Year",IF(AND(AD70<=365,AD70>180),"Above 6 Months",IF(AND(AD70<=180,AD70>90),"Above 3 Months",IF(AND(AD70<=90,AD70>60),"Above 60 Days",IF(AND(AD70<=60,AD70>45),"45 to 60 Days","Below 45 Days"))))),"") | AF70: D-4(Missing) | AG70: Srikakulam I Town,'1346/2020' | AH70: =IF(X70="SC/PRC/CC No. Awaited","",AC70) -> Above 1 Year
A71: 70 | B71: Tekkali Sub-Division | C71: Kothuru Circle | E71: Hiramandalam | F71: '268/2020' | G71: Woman Missing Person | H71: 44115 | I71: Oct | J71: 2020 | K71: Missing Cases | L71: Women Missing | M71: Missing Cases | N71: Missing | O71: Non-Grave | S71: UI | W71: Want of clues | X71: Want of clues | Z71: Occurred on 09.10.2020 at about 14.00 hours, at Patha Hiramandalam village, Hiramandalam Mandal and reported on11.10.2020 at 16.30 hrs by the complainant Kummari.Raja Rao, s/o late Tulasayya, age 55 yrs, caste by Kummari, Chidivalasa village, Polaki Mandal was reported that, his Second daughter and His Son-in-law Lives Ptaha Hiramandalam, Hiramandalam mandal.on 09.10.2020 at about his son-in-law told him by phone that your daughter Korlapu Rajulamma, D/o Raja Rao, age 30, went out with your grand daughter and not come back to home ,then the complaint and his son-in-law yried to trace her surronding areas and relative houses but not traced then complaint on 11.10.2020 came to ps and gave raport. Basing on the report of the complainant SI of Police registered a Case in Cr.No.268/2020 U/H | AA71: Total | AB71: =IF(S71="UI",DATEDIF(H71,TODAY(),"D"),"") -> 2196 | AC71: =IF(S71="UI",IF(AB71>365,"Above 1 Year",IF(AND(AB71<=365,AB71>180),"Above 6 Months",IF(AND(AB71<=180,AB71>90),"Above 3 Months",IF(AND(AB71<=90,AB71>60),"Above 60 Days",IF(AND(AB71<=60,AB71>45),"45 to 60 Days","Below 45 Days"))))),"") -> Above 1 Year | AD71: =IF(Y71<>"",DATEDIF(Y71,TODAY(),"D"),"") | AE71: =IF(AD71<>"",IF(AD71>365,"Above 1 Year",IF(AND(AD71<=365,AD71>180),"Above 6 Months",IF(AND(AD71<=180,AD71>90),"Above 3 Months",IF(AND(AD71<=90,AD71>60),"Above 60 Days",IF(AND(AD71<=60,AD71>45),"45 to 60 Days","Below 45 Days"))))),"") | AF71: D-4(Missing) | AG71: Hiramandalam,'268/2020' | AH71: =IF(X71="SC/PRC/CC No. Awaited","",AC71) -> Above 1 Year
A72: 71 | B72: Srikakulam Sub-Division | C72: Srikakulam Rural Circle | E72: Srikakulam I Town | F72: '1372/2020' | G72: 420 IPC, 66-D ITA-2000-2008 | H72: 44159 | I72: Nov | J72: 2020 | K72: Cyber Crime offences | M72: Cyber Crime offences | N72: IPC | O72: Non-Grave | S72: UI | W72: Want of clues | X72: Want of clues | Z72: This is a case of cheating by personation by means of electronic device that occurred on 02-10-2020 at Old APHB Colony, Z.P. back side, Srikakulam and reported on 24-11-2020 at 18-00 hrs wherein the complainant stated that he made facebook friendship with Shama Tilkar, Scotland of United Kingdom and believed his deceitful words the complainant credited an amount of Rs. 7,15,000/- in various times to his accounts bearing Nos 1) 92001003628285965 of Maria H.Chettiar, Branch: Delhi 2) 920010036285965-Axis Bank, 3) A/c No. 2166010015747 United Bank Branch, Katla. 4) A/c No.37908171698 Delhi Branch, 5) 2347101007356 Navel First Mawein, PAN FZLPM8583D, 6) 1067000108198463 and the accused drawn the amount several times by using electronic device. Hence the complainant lodged a report to e | AA72: Total | AB72: =IF(S72="UI",DATEDIF(H72,TODAY(),"D"),"") -> 2152 | AC72: =IF(S72="UI",IF(AB72>365,"Above 1 Year",IF(AND(AB72<=365,AB72>180),"Above 6 Months",IF(AND(AB72<=180,AB72>90),"Above 3 Months",IF(AND(AB72<=90,AB72>60),"Above 60 Days",IF(AND(AB72<=60,AB72>45),"45 to 60 Days","Below 45 Days"))))),"") -> Above 1 Year | AD72: =IF(Y72<>"",DATEDIF(Y72,TODAY(),"D"),"") | AE72: =IF(AD72<>"",IF(AD72>365,"Above 1 Year",IF(AND(AD72<=365,AD72>180),"Above 6 Months",IF(AND(AD72<=180,AD72>90),"Above 3 Months",IF(AND(AD72<=90,AD72>60),"Above 60 Days",IF(AND(AD72<=60,AD72>45),"45 to 60 Days","Below 45 Days"))))),"") | AF72: Cyber Cell | AG72: Srikakulam I Town,'1372/2020' | AH72: =IF(X72="SC/PRC/CC No. Awaited","",AC72) -> Above 1 Year
A73: 72 | B73: Tekkali Sub-Division | C73: Narasannapeta Circle | E73: Narasannapeta | F73: '555/2020' | G73: Man Missing Person | H73: 44194 | I73: Dec | J73: 2020 | K73: Missing Cases | L73: Man Missing | M73: Missing Cases | N73: Missing | O73: Non-Grave | S73: UI | W73: Want of clues | X73: Want of clues | Z73: This is a case of Man Missing that occurred on 05.09.2020 at about 11.30 hrs at Sivanagar colony, Narasannapeta town and reported on 29.12.2020 at 10.00 hrs, wherein the complainant Penuguguru Naveena, W/o Chinnarao, 33 years, Nayibrahmin by caste, Sivanagar colony, Narasannapeta town reported that her husband viz. Penuguduru Chinnarao, S/o late Suryanarayana, age about 40 years, left from house without intimation and did not return. Later made searches about her husband but in vain. Her husband wore one artificial leg, medium colour, and one tattoo mark symbol on hand as tree. Hence she requested to trace out her husband. | AA73: Total | AB73: =IF(S73="UI",DATEDIF(H73,TODAY(),"D"),"") -> 2117 | AC73: =IF(S73="UI",IF(AB73>365,"Above 1 Year",IF(AND(AB73<=365,AB73>180),"Above 6 Months",IF(AND(AB73<=180,AB73>90),"Above 3 Months",IF(AND(AB73<=90,AB73>60),"Above 60 Days",IF(AND(AB73<=60,AB73>45),"45 to 60 Days","Below 45 Days"))))),"") -> Above 1 Year | AD73: =IF(Y73<>"",DATEDIF(Y73,TODAY(),"D"),"") | AE73: =IF(AD73<>"",IF(AD73>365,"Above 1 Year",IF(AND(AD73<=365,AD73>180),"Above 6 Months",IF(AND(AD73<=180,AD73>90),"Above 3 Months",IF(AND(AD73<=90,AD73>60),"Above 60 Days",IF(AND(AD73<=60,AD73>45),"45 to 60 Days","Below 45 Days"))))),"") | AF73: D-4(Missing) | AG73: Narasannapeta,'555/2020' | AH73: =IF(X73="SC/PRC/CC No. Awaited","",AC73) -> Above 1 Year
A74: 73 | B74: Kasibugga Sub-Division | C74: 0 | E74: Kasibugga | F74: '1141/2020' | G74: 420 IPC, 66-D,66-C ITA-2000-2008 | H74: 44195 | I74: Dec | J74: 2020 | K74: Cyber Crime offences | M74: Cyber Crime offences | N74: IPC | O74: Non-Grave | S74: UI | W74: For Legal Opinion | X74: For Legal Opinion | Y74: 45930 | Z74: Occurred on 30.12.2020 in between 13.24hrs to 15.54hrs at Pedda Makkannapalli village of Palasa Mandal, and reported on same day at 21.00hrs by the complainant Teppala Ranjani D/o Harikrishna, Pedda Makkannapalli village of Palasa Mandal. Which is she reported that 1 week back she uploaded her Resume in naukri.com and Today she got 3 phone calls last call phoned a lady and said vacancy available in “Pantaloons company”. After that she asked complainant to open bestjob.com website in her phone and made fill information in and pay 25/- fee for application through Mobikiwik.com by using Debit card, then the complainant paid the amount using her father’s ATM card, automatically some money 1) 27.240,2) 11,127, 3) 54.564 which was transferred unknown account . Finely she realized she was | AA74: Total | AB74: =IF(S74="UI",DATEDIF(H74,TODAY(),"D"),"") -> 2116 | AC74: =IF(S74="UI",IF(AB74>365,"Above 1 Year",IF(AND(AB74<=365,AB74>180),"Above 6 Months",IF(AND(AB74<=180,AB74>90),"Above 3 Months",IF(AND(AB74<=90,AB74>60),"Above 60 Days",IF(AND(AB74<=60,AB74>45),"45 to 60 Days","Below 45 Days"))))),"") -> Above 1 Year | AD74: =IF(Y74<>"",DATEDIF(Y74,TODAY(),"D"),"") -> 381 | AE74: =IF(AD74<>"",IF(AD74>365,"Above 1 Year",IF(AND(AD74<=365,AD74>180),"Above 6 Months",IF(AND(AD74<=180,AD74>90),"Above 3 Months",IF(AND(AD74<=90,AD74>60),"Above 60 Days",IF(AND(AD74<=60,AD74>45),"45 to 60 Days","Below 45 Days"))))),"") -> Above 1 Year | AF74: Cyber Cell | AG74: Kasibugga,'1141/2020' | AH74: =IF(X74="SC/PRC/CC No. Awaited","",AC74) -> Above 1 Year
A75: 74 | B75: Tekkali Sub-Division | C75: Narasannapeta Circle | E75: Narasannapeta | F75: '3/2021' | G75: Man Missing Person | H75: 44201 | I75: Jan | J75: 2021 | K75: Missing Cases | L75: Man Missing | M75: Missing Cases | N75: Missing | O75: Non-Grave | S75: UI | W75: Want of clues | X75: Want of clues | Z75: This is a case of Man Missing that occurred on 01.01.2021 at about 09.00hrs at Pasaru veedhi, Narasannapeta town and reported on 05.01.2021 at 19.00hrs, wherein the complainant Mahmad Shaha Begam w/o Shahen Sha, 35yrs, Caste by Muslim, Pasaru veedhi, Narasannapeta town reported that her husband Sheik Shahen sha s/o Abdul Rehman, 42yrs left from house by informing that he would go to outside and did not return. Later they made searches about her husband but in vain thereby found missing. At the time of departure her husband wore Pant and shirt, height about 5.8 feet, he is medium complexion. | AA75: Total | AB75: =IF(S75="UI",DATEDIF(H75,TODAY(),"D"),"") -> 2110 | AC75: =IF(S75="UI",IF(AB75>365,"Above 1 Year",IF(AND(AB75<=365,AB75>180),"Above 6 Months",IF(AND(AB75<=180,AB75>90),"Above 3 Months",IF(AND(AB75<=90,AB75>60),"Above 60 Days",IF(AND(AB75<=60,AB75>45),"45 to 60 Days","Below 45 Days"))))),"") -> Above 1 Year | AD75: =IF(Y75<>"",DATEDIF(Y75,TODAY(),"D"),"") | AE75: =IF(AD75<>"",IF(AD75>365,"Above 1 Year",IF(AND(AD75<=365,AD75>180),"Above 6 Months",IF(AND(AD75<=180,AD75>90),"Above 3 Months",IF(AND(AD75<=90,AD75>60),"Above 60 Days",IF(AND(AD75<=60,AD75>45),"45 to 60 Days","Below 45 Days"))))),"") | AF75: D-4(Missing) | AG75: Narasannapeta,'3/2021' | AH75: =IF(X75="SC/PRC/CC No. Awaited","",AC75) -> Above 1 Year
A76: 75 | B76: Kasibugga Sub-Division | C76: 0 | E76: Kasibugga | F76: '12/2021' | G76: 20(b) NDPSA | H76: 44208 | I76: Jan | J76: 2021 | K76: NDPS | M76: NDPS | N76: NDPS | O76: Non-Grave | P76: 45915 | Q76: Yes | S76: UI | W76: Charge Sheet returned form court | X76: Charge Sheet returned form court | Y76: 45915 | Z76: Occurred on 12.01.2021 at 13.00hrs,at Laxmipuram toll plaza, NH- 16 road, in between Srikakulam to Ichapuram road of Palasa Mandal, and reported the 12.01.2021 at 15.30 hrs, As per the reliable information about gutka, Inspector and staff along with Revenue staff went to that place, and conducting vehicle checking, while one Bolero bearing no UP 15 ET 8751 came the from Srikakulam side driver of vehicle stopped his vehicle and run away from that place by seeing police with uniform. Then Inspector of Police reached the vehicle and found some ganja smell coming from the vehicle, he suspected and examined the vehicle and found 43 packets of Ganja total weight 90.548 kgs and 20 packets of grain hull. Later total material sized and registered the Case Cr.no 12/2021 u/s 20 (b) NDPS A | AA76: Total | AB76: =IF(S76="UI",DATEDIF(H76,TODAY(),"D"),"") -> 2103 | AC76: =IF(S76="UI",IF(AB76>365,"Above 1 Year",IF(AND(AB76<=365,AB76>180),"Above 6 Months",IF(AND(AB76<=180,AB76>90),"Above 3 Months",IF(AND(AB76<=90,AB76>60),"Above 60 Days",IF(AND(AB76<=60,AB76>45),"45 to 60 Days","Below 45 Days"))))),"") -> Above 1 Year | AD76: =IF(Y76<>"",DATEDIF(Y76,TODAY(),"D"),"") -> 396 | AE76: =IF(AD76<>"",IF(AD76>365,"Above 1 Year",IF(AND(AD76<=365,AD76>180),"Above 6 Months",IF(AND(AD76<=180,AD76>90),"Above 3 Months",IF(AND(AD76<=90,AD76>60),"Above 60 Days",IF(AND(AD76<=60,AD76>45),"45 to 60 Days","Below 45 Days"))))),"") -> Above 1 Year | AF76: C-3(NDPS) | AG76: Kasibugga,'12/2021' | AH76: =IF(X76="SC/PRC/CC No. Awaited","",AC76) -> Above 1 Year
A77: 76 | B77: Kasibugga Sub-Division | C77: 0 | E77: Kasibugga | F77: '18/2021' | G77: 447,427 r/w 34 IPC | H77: 44213 | I77: Jan | J77: 2021 | K77: Other IPC | M77: Other IPC | N77: IPC | O77: Non-Grave | S77: UI | W77: Pending records from other depts., | X77: Revenue records awaited | Y77: 46182 | Z77: Occurred on 17.01.2021 at 11:00 hours, at in survy no 176/5 and 179/15, Kottaparasamba village, and reported on the same day at 16:00 hours, the complainant Ronanki Apparao S/o late Appanna, 71yrs, Kalinga by caste, Kottaparasamba village, Palasa Mandal, Srikakulam District, he reported that he is living at Kottaparasamba village, Palasa-Kasibugga Municipality , his son Ronanki Kodanda Rao was worked in the Indian Air force, he was applied to the District collector for house sight in the year of 2010 through his commanding officer, and the MRO, Palasa sanctioned 3 cents of house site in survey No 176/5 & 179/15 in the year of 2012, similarly the complainant daughter’s husband Jayaram also worked in the Indian Army and he also granted 3 cents of house site, and also obtained plan approval | AA77: Total | AB77: =IF(S77="UI",DATEDIF(H77,TODAY(),"D"),"") -> 2098 | AC77: =IF(S77="UI",IF(AB77>365,"Above 1 Year",IF(AND(AB77<=365,AB77>180),"Above 6 Months",IF(AND(AB77<=180,AB77>90),"Above 3 Months",IF(AND(AB77<=90,AB77>60),"Above 60 Days",IF(AND(AB77<=60,AB77>45),"45 to 60 Days","Below 45 Days"))))),"") -> Above 1 Year | AD77: =IF(Y77<>"",DATEDIF(Y77,TODAY(),"D"),"") -> 129 | AE77: =IF(AD77<>"",IF(AD77>365,"Above 1 Year",IF(AND(AD77<=365,AD77>180),"Above 6 Months",IF(AND(AD77<=180,AD77>90),"Above 3 Months",IF(AND(AD77<=90,AD77>60),"Above 60 Days",IF(AND(AD77<=60,AD77>45),"45 to 60 Days","Below 45 Days"))))),"") -> Above 3 Months | AF77: D-6(Other IPC) | AG77: Kasibugga,'18/2021' | AH77: =IF(X77="SC/PRC/CC No. Awaited","",AC77) -> Above 1 Year
A78: 77 | B78: Srikakulam Sub-Division | C78: Srikakulam Rural Circle | E78: Gara | F78: '12/2021' | G78: 420 IPC, 66-D ITA-2000-2008 | H78: 44216 | I78: Jan | J78: 2021 | K78: Cyber Crime offences | M78: Cyber Crime offences | N78: IPC | O78: Non-Grave | S78: UI | W78: For Suspect Verification | X78: For Suspect Verification | Z78: This is a case of cheating by personation by using Net Banking and PhonePe that occurred on in between the dates from 31-12-2020 to 14-1-2021 through online by the complainant and reported on 20-1-2021 at 18.00 hours, wherein the complainant Pappu Vijayalaxmi, W/o Laxmana Rao, age: 49 years, Vadabalija by caste, Peddapallipeta village, Gara Mandal reported that the alleged accused Sandheep Pande cheated her by Net-Banking and phonePe transactions deposited the cash in different dates for sanction of dealership in Hindustan Patrol gas agency. The complainant send cash through her bank account and her daughters Kavitha and Joshna bank accounts on different days from 31-12-2020 to 14-1-2021 by net banking and PhonePe to the Account No. 726801010050450 in the name of Hindustan Petroleum Corpo | AA78: Total | AB78: =IF(S78="UI",DATEDIF(H78,TODAY(),"D"),"") -> 2095 | AC78: =IF(S78="UI",IF(AB78>365,"Above 1 Year",IF(AND(AB78<=365,AB78>180),"Above 6 Months",IF(AND(AB78<=180,AB78>90),"Above 3 Months",IF(AND(AB78<=90,AB78>60),"Above 60 Days",IF(AND(AB78<=60,AB78>45),"45 to 60 Days","Below 45 Days"))))),"") -> Above 1 Year | AD78: =IF(Y78<>"",DATEDIF(Y78,TODAY(),"D"),"") | AE78: =IF(AD78<>"",IF(AD78>365,"Above 1 Year",IF(AND(AD78<=365,AD78>180),"Above 6 Months",IF(AND(AD78<=180,AD78>90),"Above 3 Months",IF(AND(AD78<=90,AD78>60),"Above 60 Days",IF(AND(AD78<=60,AD78>45),"45 to 60 Days","Below 45 Days"))))),"") | AF78: Cyber Cell | AG78: Gara,'12/2021' | AH78: =IF(X78="SC/PRC/CC No. Awaited","",AC78) -> Above 1 Year
A79: 78 | B79: Srikakulam Sub-Division | C79: Srikakulam Rural Circle | E79: Srikakulam I Town | F79: '32/2021' | G79: 471,420 r/w 34 IPC | H79: 44242 | I79: Feb | J79: 2021 | K79: Cheating | M79: White Collar Offences | N79: IPC | O79: Non-Grave | P79: 45952 | S79: UI | W79: Charge Sheet returned form court | X79: SC/PRC/CC No. Awaited | Y79: 45952 | Z79: This is a case of cheating by using as genuine a forged document. which occurred prior to 7-10-2017 at Telugu Musalayya Colony , Arasvelli, Srikakulam , and report 15-02-2021 at 1900 Hours .wherein the complainant lodged a report stated that he along with Karajana Bhaskara Rao S/o Ramamurty, SC , Prakashnagar, Kotabommali village purchased house site approved plot No.11 to an extent of 266 sq.yards (5 ½ cent) in Adityanagar Layout, Srikakulam from Gembali Sravani w/o Srinivasa Rao of Veeraghattam village which approved by Srikakulam Municipality vide L.P.No. 108/1998 (R.S.with Survey Nos.506-6,501-1,501-2,500-1,500-2, T.S.No.436-6,446-1,446-2,447-1,447-2) and the same was registered vide document no. 7127/2017, dt.22-11-2017. But during the enquiry, the General Administration (Vigilanc | AA79: Total | AB79: =IF(S79="UI",DATEDIF(H79,TODAY(),"D"),"") -> 2069 | AC79: =IF(S79="UI",IF(AB79>365,"Above 1 Year",IF(AND(AB79<=365,AB79>180),"Above 6 Months",IF(AND(AB79<=180,AB79>90),"Above 3 Months",IF(AND(AB79<=90,AB79>60),"Above 60 Days",IF(AND(AB79<=60,AB79>45),"45 to 60 Days","Below 45 Days"))))),"") -> Above 1 Year | AD79: =IF(Y79<>"",DATEDIF(Y79,TODAY(),"D"),"") -> 359 | AE79: =IF(AD79<>"",IF(AD79>365,"Above 1 Year",IF(AND(AD79<=365,AD79>180),"Above 6 Months",IF(AND(AD79<=180,AD79>90),"Above 3 Months",IF(AND(AD79<=90,AD79>60),"Above 60 Days",IF(AND(AD79<=60,AD79>45),"45 to 60 Days","Below 45 Days"))))),"") -> Above 6 Months | AF79: D-6(White collar) | AG79: Srikakulam I Town,'32/2021' | AH79: =IF(X79="SC/PRC/CC No. Awaited","",AC79)
A80: 79 | B80: Srikakulam Sub-Division | C80: J.R.Puram Circle | E80: Etcherla | F80: '57/2021' | G80: 452,323,147,324,427,307,148 r/w 149 IPC | H80: 44250 | I80: Feb | J80: 2021 | K80: Attempt To Murder | M80: Bodily Offiences | N80: IPC | O80: Non-Grave | P80: 44327 | S80: UI | W80: SC/PRC/CC No. Awaited | X80: SC/PRC/CC No. Awaited | Y80: 44327 | Z80: Occurred on 23.2.2021 at about 11.30 hrs at Budagatlapalem (V), Etcherla (M) and reported on the same day at 19.30 hrs by the Complt; Gopilli Guruvesu, s/o Guruvulu, 36 yrs, Vadabalija by caste, fisherman of Budagatalapalem (V) that one Alipilli Rambabu s/o Chinna Ramudu was elected as Village Sarpanch with the support of TDP party in the recent Panchayat elections by defeating his rival candidate Ambati Rambabu s/o lt. Danesu of same village on 21.2.2021.Keeping in mind the political ill feelings, the followers of winning candidate (TDP) started insulting the counter party (YSR) on their defeat and proclaimed to do away the life of any person of their opposition. In such manner, on 23.2.2021 at about 11.30 hrs the A-01 Allupalli Rambabu s/o Chinna ramudu, 33 yrs, vadabalija by caste, Bud | AA80: Total | AB80: =IF(S80="UI",DATEDIF(H80,TODAY(),"D"),"") -> 2061 | AC80: =IF(S80="UI",IF(AB80>365,"Above 1 Year",IF(AND(AB80<=365,AB80>180),"Above 6 Months",IF(AND(AB80<=180,AB80>90),"Above 3 Months",IF(AND(AB80<=90,AB80>60),"Above 60 Days",IF(AND(AB80<=60,AB80>45),"45 to 60 Days","Below 45 Days"))))),"") -> Above 1 Year | AD80: =IF(Y80<>"",DATEDIF(Y80,TODAY(),"D"),"") -> 1984 | AE80: =IF(AD80<>"",IF(AD80>365,"Above 1 Year",IF(AND(AD80<=365,AD80>180),"Above 6 Months",IF(AND(AD80<=180,AD80>90),"Above 3 Months",IF(AND(AD80<=90,AD80>60),"Above 60 Days",IF(AND(AD80<=60,AD80>45),"45 to 60 Days","Below 45 Days"))))),"") -> Above 1 Year | AF80: D-6(Bodily) | AG80: Etcherla,'57/2021' | AH80: =IF(X80="SC/PRC/CC No. Awaited","",AC80)
A81: 80 | B81: Srikakulam Sub-Division | C81: J.R.Puram Circle | E81: Etcherla | F81: '58/2021' | G81: 307,147,148,323,427,324,452 r/w 149 IPC | H81: 44250 | I81: Feb | J81: 2021 | K81: Attempt To Murder | M81: Bodily Offiences | N81: IPC | O81: Non-Grave | P81: 44331 | S81: UI | W81: SC/PRC/CC No. Awaited | X81: SC/PRC/CC No. Awaited | Y81: 44331 | Z81: This is counter case to Cr.No. 57/2021. Occurred on 23.2.2021 at about 11.30 hrs at Budagatlapalem (V), Etcherla (M) and reported on the same day at 20.30 hrs by the Complt; Alupalli Thatarao, s/o Laxmayya, 42 yrs, Vadabalija by caste, fisherman of Budagatalapalem (V) that one Alipilli Rambabu s/o Chinna Ramudu of their Party was elected as Village Sarpanch with the support of TDP followers in the recent Panchayat elections by defeating his rival candidate Ambati Rambabu s/o lt. Danesu (YSR) of same village on 21.2.2021. In this context, the followers of YSR could not digest their defeat and so started abusing against TDP followers since declaration of election. In the process, on 23.2.2021 at about 11.30 hrs one of the followers of YSR party viz. Gopilli Guravesu s/o Guruvulu (YSR) h | AA81: Total | AB81: =IF(S81="UI",DATEDIF(H81,TODAY(),"D"),"") -> 2061 | AC81: =IF(S81="UI",IF(AB81>365,"Above 1 Year",IF(AND(AB81<=365,AB81>180),"Above 6 Months",IF(AND(AB81<=180,AB81>90),"Above 3 Months",IF(AND(AB81<=90,AB81>60),"Above 60 Days",IF(AND(AB81<=60,AB81>45),"45 to 60 Days","Below 45 Days"))))),"") -> Above 1 Year | AD81: =IF(Y81<>"",DATEDIF(Y81,TODAY(),"D"),"") -> 1980 | AE81: =IF(AD81<>"",IF(AD81>365,"Above 1 Year",IF(AND(AD81<=365,AD81>180),"Above 6 Months",IF(AND(AD81<=180,AD81>90),"Above 3 Months",IF(AND(AD81<=90,AD81>60),"Above 60 Days",IF(AND(AD81<=60,AD81>45),"45 to 60 Days","Below 45 Days"))))),"") -> Above 1 Year | AF81: D-6(Bodily) | AG81: Etcherla,'58/2021' | AH81: =IF(X81="SC/PRC/CC No. Awaited","",AC81)
A82: 81 | B82: Srikakulam Sub-Division | C82: J.R.Puram Circle | E82: J.R.Puram | F82: '45/2021' | G82: 420,468,379,120b,471 r/w 109 IPC, 3 (2) (e) PDPPA | H82: 44261 | I82: Mar | J82: 2021 | K82: Cheating | M82: White Collar Offences | N82: IPC | O82: Non-Grave | P82: 45852 | S82: UI | W82: SC/PRC/CC No. Awaited | X82: SC/PRC/CC No. Awaited | Y82: 45852 | Z82: Occurred on 06.03.2021 at about 15:00 hrs at Pydibeemavaram sand check post and reported at 18:00 hrs on 06.03.2021 in which the S.I has intercepted 02 lorries bearing registration Nos. AP-04-TW-2799 and AP-31-TH-5558 on their way to Visakhapatnam from Berhampur of Odisha state with sand. On verification it was established that the drivers, cleaners and owners of lorries have conspired together to cheat to get wrongful gain, committed theft of sand and transported the sand with post dated E way bills and transit pass issued by the Tahsildar, Bugada of Odisha state. | AA82: Total | AB82: =IF(S82="UI",DATEDIF(H82,TODAY(),"D"),"") -> 2050 | AC82: =IF(S82="UI",IF(AB82>365,"Above 1 Year",IF(AND(AB82<=365,AB82>180),"Above 6 Months",IF(AND(AB82<=180,AB82>90),"Above 3 Months",IF(AND(AB82<=90,AB82>60),"Above 60 Days",IF(AND(AB82<=60,AB82>45),"45 to 60 Days","Below 45 Days"))))),"") -> Above 1 Year | AD82: =IF(Y82<>"",DATEDIF(Y82,TODAY(),"D"),"") -> 459 | AE82: =IF(AD82<>"",IF(AD82>365,"Above 1 Year",IF(AND(AD82<=365,AD82>180),"Above 6 Months",IF(AND(AD82<=180,AD82>90),"Above 3 Months",IF(AND(AD82<=90,AD82>60),"Above 60 Days",IF(AND(AD82<=60,AD82>45),"45 to 60 Days","Below 45 Days"))))),"") -> Above 1 Year | AF82: D-6(White collar) | AG82: J.R.Puram,'45/2021' | AH82: =IF(X82="SC/PRC/CC No. Awaited","",AC82)
A83: 82 | B83: Srikakulam Sub-Division | C83: Srikakulam Rural Circle | E83: Gara | F83: '55/2021' | G83: Man Missing Person | H83: 44280 | I83: Mar | J83: 2021 | K83: Missing Cases | L83: Man Missing | M83: Missing Cases | N83: Missing | O83: Non-Grave | S83: UI | W83: Want of clues | X83: Want of clues | Z83: This is a case of man missing that occurred in the month of October, 2016 at Ampolu village, Gara Mandal and reported on 25-3-2021 at 18-00 hours wherein the complainant Durru Lakshmi, W/o Kameswara Rao, 38 years, Srisaina by caste, Ampolu village, Gara Mandal reported that her parentage house at Ampolu village, Gara Mandal she studied up to 10th class and performed marriage with one Durru Kameswara Rao of Vadapalem village in the year of 2005. Her uncle Durru Ramarao, who is father of her husband has been worked as Govt. Job in Govt. Junior college, Calingapatnam and he was died in the year of 2004 due to ill-health. Later her uncle job given to her husband Kameswararao as attender and working at Govt. Junior college, Polaki Mandal. Later some days, working in Arts college, Srikakulam | AA83: Total | AB83: =IF(S83="UI",DATEDIF(H83,TODAY(),"D"),"") -> 2031 | AC83: =IF(S83="UI",IF(AB83>365,"Above 1 Year",IF(AND(AB83<=365,AB83>180),"Above 6 Months",IF(AND(AB83<=180,AB83>90),"Above 3 Months",IF(AND(AB83<=90,AB83>60),"Above 60 Days",IF(AND(AB83<=60,AB83>45),"45 to 60 Days","Below 45 Days"))))),"") -> Above 1 Year | AD83: =IF(Y83<>"",DATEDIF(Y83,TODAY(),"D"),"") | AE83: =IF(AD83<>"",IF(AD83>365,"Above 1 Year",IF(AND(AD83<=365,AD83>180),"Above 6 Months",IF(AND(AD83<=180,AD83>90),"Above 3 Months",IF(AND(AD83<=90,AD83>60),"Above 60 Days",IF(AND(AD83<=60,AD83>45),"45 to 60 Days","Below 45 Days"))))),"") | AF83: D-4(Missing) | AG83: Gara,'55/2021' | AH83: =IF(X83="SC/PRC/CC No. Awaited","",AC83) -> Above 1 Year
A84: 83 | B84: Srikakulam Sub-Division | C84: Srikakulam Rural Circle | E84: Srikakulam Rural | F84: '123/2021' | G84: 420 IPC, 66-D ITA-2000-2008 | H84: 44310 | I84: Apr | J84: 2021 | K84: Cyber Crime offences | M84: Cyber Crime offences | N84: IPC | O84: Non-Grave | S84: UI | W84: For Suspect Verification | X84: For Suspect Verification | Z84: Occurred on 22.04.2020 at 1300 hrs to14.00 hours at house of the complainant, sunrise towers, Peddapadu road, Srikakulam Mandal, reported on 24.04.2021 at 14.00 hours, by the complainant Dharbamulla Niveditha D/o Pinakapani, age 29 years, Door. No. F 16 sunrise towers, Peddapadu road, Srikakulam Mandal, she was living by doing as a software engineer at Bangalore, she have old TV, almarah and bench and she says selling that on OLX, she uploaded that her mother’s phone number on OLX, she have received one phone call from the accused cell number 8099246839, the accused introduced himself, his name Deepak sharma, he have second hand shop, he bought old items believed to complainant, he send money Rs. 10000/- threw Google pay/Phone pay/Paytm and asked phone number, the complainant give pay tm | AA84: Total | AB84: =IF(S84="UI",DATEDIF(H84,TODAY(),"D"),"") -> 2001 | AC84: =IF(S84="UI",IF(AB84>365,"Above 1 Year",IF(AND(AB84<=365,AB84>180),"Above 6 Months",IF(AND(AB84<=180,AB84>90),"Above 3 Months",IF(AND(AB84<=90,AB84>60),"Above 60 Days",IF(AND(AB84<=60,AB84>45),"45 to 60 Days","Below 45 Days"))))),"") -> Above 1 Year | AD84: =IF(Y84<>"",DATEDIF(Y84,TODAY(),"D"),"") | AE84: =IF(AD84<>"",IF(AD84>365,"Above 1 Year",IF(AND(AD84<=365,AD84>180),"Above 6 Months",IF(AND(AD84<=180,AD84>90),"Above 3 Months",IF(AND(AD84<=90,AD84>60),"Above 60 Days",IF(AND(AD84<=60,AD84>45),"45 to 60 Days","Below 45 Days"))))),"") | AF84: Cyber Cell | AG84: Srikakulam Rural,'123/2021' | AH84: =IF(X84="SC/PRC/CC No. Awaited","",AC84) -> Above 1 Year
A85: 84 | B85: Srikakulam Sub-Division | C85: Srikakulam Rural Circle | E85: Srikakulam Rural | F85: '138/2021' | G85: 306 IPC | H85: 44324 | I85: May | J85: 2021 | K85: other IPC | M85: Other IPC | N85: IPC | O85: Non-Grave | P85: 45621 | S85: UI | W85: SC/PRC/CC No. Awaited | X85: SC/PRC/CC No. Awaited | Y85: 45621 | Z85: Occurred on 08.05.2021 at 08.30 hours, at the house of deceased of Govindhanagar colony, Chapurampanchayathi of Srikakulam Rural Mandal and reported on same day at 14.00 hours, wherein the complainant Dumpala Venkatavaraprasad s/o Jagannadham, age 53 years, caste by kalinga, Turakapeta village, Nandhigam Mandal, reported that, wherein the the deceased Dumpala Venugopalakrishna age 47 years who is brother of the complainant was married to the accused Kaviti @ Dumpala Kalavathi age 40 years, Govindhanagar colony, Chapurampanchayathi of Srikakulam Rural Mandal and they has one daughter namely Yasaswini age 15 years, soon after his marriage, the accused subjected the deceased to cruelty mentally, without talking to his parents and repeatedly quarreling with deceases. The deceased committe | AA85: Total | AB85: =IF(S85="UI",DATEDIF(H85,TODAY(),"D"),"") -> 1987 | AC85: =IF(S85="UI",IF(AB85>365,"Above 1 Year",IF(AND(AB85<=365,AB85>180),"Above 6 Months",IF(AND(AB85<=180,AB85>90),"Above 3 Months",IF(AND(AB85<=90,AB85>60),"Above 60 Days",IF(AND(AB85<=60,AB85>45),"45 to 60 Days","Below 45 Days"))))),"") -> Above 1 Year | AD85: =IF(Y85<>"",DATEDIF(Y85,TODAY(),"D"),"") -> 690 | AE85: =IF(AD85<>"",IF(AD85>365,"Above 1 Year",IF(AND(AD85<=365,AD85>180),"Above 6 Months",IF(AND(AD85<=180,AD85>90),"Above 3 Months",IF(AND(AD85<=90,AD85>60),"Above 60 Days",IF(AND(AD85<=60,AD85>45),"45 to 60 Days","Below 45 Days"))))),"") -> Above 1 Year | AF85: D-6(Other IPC) | AG85: Srikakulam Rural,'138/2021' | AH85: =IF(X85="SC/PRC/CC No. Awaited","",AC85)
A86: 85 | B86: Srikakulam Sub-Division | C86: Amadalavalasa Circle | E86: Amadalavalasa | F86: '90/2021' | G86: Man Missing Person | H86: 44333 | I86: May | J86: 2021 | K86: Missing Cases | L86: Man Missing | M86: Missing Cases | N86: Missing | O86: Non-Grave | S86: UI | W86: Want of clues | X86: Want of clues | Z86: Occurred On 07.05.2021 at about 09:00 hours House of the complainant, Korlakota village, Amadalavalasa Manal and reported on 17.05.2021 at 18.30 hrs. In which the complainant Pedada Satyannarayana reported that his father had forgetfulness due to old age factor. On 07.05.2021 at about 09:00 hours his father left from their house for attending natural calls and did not returned to their house till today. Immediately he and his family members seeking about his father in and around villages, friends & relatives houses, but his father Pedada Anandarao where about not known, hence, his father found missing etc. | AA86: Total | AB86: =IF(S86="UI",DATEDIF(H86,TODAY(),"D"),"") -> 1978 | AC86: =IF(S86="UI",IF(AB86>365,"Above 1 Year",IF(AND(AB86<=365,AB86>180),"Above 6 Months",IF(AND(AB86<=180,AB86>90),"Above 3 Months",IF(AND(AB86<=90,AB86>60),"Above 60 Days",IF(AND(AB86<=60,AB86>45),"45 to 60 Days","Below 45 Days"))))),"") -> Above 1 Year | AD86: =IF(Y86<>"",DATEDIF(Y86,TODAY(),"D"),"") | AE86: =IF(AD86<>"",IF(AD86>365,"Above 1 Year",IF(AND(AD86<=365,AD86>180),"Above 6 Months",IF(AND(AD86<=180,AD86>90),"Above 3 Months",IF(AND(AD86<=90,AD86>60),"Above 60 Days",IF(AND(AD86<=60,AD86>45),"45 to 60 Days","Below 45 Days"))))),"") | AF86: D-4(Missing) | AG86: Amadalavalasa,'90/2021' | AH86: =IF(X86="SC/PRC/CC No. Awaited","",AC86) -> Above 1 Year
A87: 86 | B87: Srikakulam Sub-Division | C87: Amadalavalasa Circle | E87: Amadalavalasa | F87: '98/2021' | G87: 420 IPC, 66-C,66-D ITA-2000-2008 | H87: 44347 | I87: May | J87: 2021 | K87: Cyber Crime offences | M87: Cyber Crime offences | N87: IPC | O87: Non-Grave | P87: 45569 | S87: UI | W87: SC/PRC/CC No. Awaited | X87: SC/PRC/CC No. Awaited | Y87: 45569 | Z87: Occurred On prior to 29.05.2021 at house of the complainant, B.R. Nagar, Amadalavalasa and reported on 31.05.2021 at 17:00 hours. In which the complainant G. Leela Mohanbabu reported that recently he changed his sim No.9441121009 from BSNL to Airtel by portability, mean while he contacted with 08348579282 which is showed as Airtel office staff and according to their instructions over phone he reached Rs.10 for Sim update, on that the unknown person hacked his mobile and draw the amount Rs.2,69,492/- from his SBI A/C.No.11398770644 on 29.05.2021 through internet banking, there by the unknown person cheated complainant fraudulently etc. | AA87: Total | AB87: =IF(S87="UI",DATEDIF(H87,TODAY(),"D"),"") -> 1964 | AC87: =IF(S87="UI",IF(AB87>365,"Above 1 Year",IF(AND(AB87<=365,AB87>180),"Above 6 Months",IF(AND(AB87<=180,AB87>90),"Above 3 Months",IF(AND(AB87<=90,AB87>60),"Above 60 Days",IF(AND(AB87<=60,AB87>45),"45 to 60 Days","Below 45 Days"))))),"") -> Above 1 Year | AD87: =IF(Y87<>"",DATEDIF(Y87,TODAY(),"D"),"") -> 742 | AE87: =IF(AD87<>"",IF(AD87>365,"Above 1 Year",IF(AND(AD87<=365,AD87>180),"Above 6 Months",IF(AND(AD87<=180,AD87>90),"Above 3 Months",IF(AND(AD87<=90,AD87>60),"Above 60 Days",IF(AND(AD87<=60,AD87>45),"45 to 60 Days","Below 45 Days"))))),"") -> Above 1 Year | AF87: Cyber Cell | AG87: Amadalavalasa,'98/2021' | AH87: =IF(X87="SC/PRC/CC No. Awaited","",AC87)
A88: 87 | B88: Tekkali Sub-Division | C88: Kothuru Circle | E88: Kothuru | F88: '84/2021' | G88: 420,419 IPC, 66-C,66-D ITA-2000-2008 | H88: 44347 | I88: May | J88: 2021 | K88: Cyber Crime offences | M88: Cyber Crime offences | N88: IPC | O88: Non-Grave | S88: UI | W88: Want of clues | X88: Want of clues | Z88: Occurred on 30.05.2021 at about 13.00 hrs at Kothuru Village & Mandal and reported on 31.05.2021 at 18.00 hrs in which the complainant Devarasetti Giridhararao S/o. Late Madhavarao, age 46 yrs, Vysya by caste, Kothuru Village & Mandal reported that some unknown fraudster contacted him over phone call from 8348579282 to his BSNL number 9441087153 and told that he contacted him for KYC verification and asked his e-mail address then he provided his e-mail address after that he asked his alternate phone number. As soon as he informed the alternate number, he received nine digit password to his phone number which was automatically resent after which the following amounts viz. Rs.49,999/-, Rs.49,900/- & Rs.25,000/- were withdrawn respectively from his account without knowledge and the withdrawal | AA88: Total | AB88: =IF(S88="UI",DATEDIF(H88,TODAY(),"D"),"") -> 1964 | AC88: =IF(S88="UI",IF(AB88>365,"Above 1 Year",IF(AND(AB88<=365,AB88>180),"Above 6 Months",IF(AND(AB88<=180,AB88>90),"Above 3 Months",IF(AND(AB88<=90,AB88>60),"Above 60 Days",IF(AND(AB88<=60,AB88>45),"45 to 60 Days","Below 45 Days"))))),"") -> Above 1 Year | AD88: =IF(Y88<>"",DATEDIF(Y88,TODAY(),"D"),"") | AE88: =IF(AD88<>"",IF(AD88>365,"Above 1 Year",IF(AND(AD88<=365,AD88>180),"Above 6 Months",IF(AND(AD88<=180,AD88>90),"Above 3 Months",IF(AND(AD88<=90,AD88>60),"Above 60 Days",IF(AND(AD88<=60,AD88>45),"45 to 60 Days","Below 45 Days"))))),"") | AF88: Cyber Cell | AG88: Kothuru,'84/2021' | AH88: =IF(X88="SC/PRC/CC No. Awaited","",AC88) -> Above 1 Year
A89: 88 | B89: Srikakulam Sub-Division | C89: Srikakulam Rural Circle | E89: Gara | F89: '102/2021' | G89: 66-C ITA-2000-2008 | H89: 44357 | I89: Jun | J89: 2021 | K89: Cyber Crime offences | M89: Cyber Crime offences | N89: IPC | O89: Non-Grave | S89: UI | W89: Want of clues | X89: Want of clues | Z89: This is a case of fraudulently make use of hacked ATM Card with OTP by information technology that occurred on 08-6-2021 at about 13-15 hours at State Bank of India main branch, Srikakulam Town and reported on 10-6-2021 at 12-00 hours, wherein the complainant Gondu Jyothsna, D/o Raghuram, age: 35 years, Velama by caste, Advocate, Ampolu village, Gara Mandal reported that the complainant holding an account No. 31341311441 in SBI, Main Branch, Srikakulam. She would like to inform you that an unauthorized person has been hacked her ATM card bearing No. 5446700052820996. An unknown person used her ATM card along with OTP and made an online purchase at Bangalore. That she came to know the above said fact when she received message from the Bank on 08-6-2021 as the culprit purchased online for | AA89: Total | AB89: =IF(S89="UI",DATEDIF(H89,TODAY(),"D"),"") -> 1954 | AC89: =IF(S89="UI",IF(AB89>365,"Above 1 Year",IF(AND(AB89<=365,AB89>180),"Above 6 Months",IF(AND(AB89<=180,AB89>90),"Above 3 Months",IF(AND(AB89<=90,AB89>60),"Above 60 Days",IF(AND(AB89<=60,AB89>45),"45 to 60 Days","Below 45 Days"))))),"") -> Above 1 Year | AD89: =IF(Y89<>"",DATEDIF(Y89,TODAY(),"D"),"") | AE89: =IF(AD89<>"",IF(AD89>365,"Above 1 Year",IF(AND(AD89<=365,AD89>180),"Above 6 Months",IF(AND(AD89<=180,AD89>90),"Above 3 Months",IF(AND(AD89<=90,AD89>60),"Above 60 Days",IF(AND(AD89<=60,AD89>45),"45 to 60 Days","Below 45 Days"))))),"") | AF89: Cyber Cell | AG89: Gara,'102/2021' | AH89: =IF(X89="SC/PRC/CC No. Awaited","",AC89) -> Above 1 Year
A90: 89 | B90: Tekkali Sub-Division | C90: Narasannapeta Circle | E90: Polaki | F90: '79/2021' | G90: 326,323,324,307 r/w 34 IPC | H90: 44374 | I90: Jun | J90: 2021 | K90: Attempt To Murder | M90: Bodily Offiences | N90: IPC | O90: Non-Grave | P90: 44655 | Q90: Yes | S90: UI | W90: Charge Sheet returned form court | X90: Charge Sheet returned form court | Y90: 44655 | Z90: Occurred on 27.06.2021 at about 10:30 hrs, Urjam village, Polaki Mandal and reported on same day at 19:05hrs , where in the complainant by name Sampatirao Telugu Rayadu S/o Simhachalam, Age 32 yrs, Kalinga by caste, Gangivalasa village, Polaki Mandal stated that he is working as bank manager in HDFC Bank in visakhapatanam. The complainant wife’s( Sampathirao Krishnaveni) grand faher i.e Killi Latchanna and accused’s(Sampathirao satyam) father-in-law (Killi Rajanna) are own brothers. The complainant wife parents gave house site(12 cents ) as “Pasupu Kunkuma” at the time of marriage and the said site was registered on his wife name i.e Sampathirao krishnaveni in the year of 2017 but in that house site some of land was occupied by Samapthirao Satyam and his son Annam Raju. On 25.06.2021 | AA90: Total | AB90: =IF(S90="UI",DATEDIF(H90,TODAY(),"D"),"") -> 1937 | AC90: =IF(S90="UI",IF(AB90>365,"Above 1 Year",IF(AND(AB90<=365,AB90>180),"Above 6 Months",IF(AND(AB90<=180,AB90>90),"Above 3 Months",IF(AND(AB90<=90,AB90>60),"Above 60 Days",IF(AND(AB90<=60,AB90>45),"45 to 60 Days","Below 45 Days"))))),"") -> Above 1 Year | AD90: =IF(Y90<>"",DATEDIF(Y90,TODAY(),"D"),"") -> 1656 | AE90: =IF(AD90<>"",IF(AD90>365,"Above 1 Year",IF(AND(AD90<=365,AD90>180),"Above 6 Months",IF(AND(AD90<=180,AD90>90),"Above 3 Months",IF(AND(AD90<=90,AD90>60),"Above 60 Days",IF(AND(AD90<=60,AD90>45),"45 to 60 Days","Below 45 Days"))))),"") -> Above 1 Year | AF90: D-6(Bodily) | AG90: Polaki,'79/2021' | AH90: =IF(X90="SC/PRC/CC No. Awaited","",AC90) -> Above 1 Year
A91: 90 | B91: Srikakulam Sub-Division | C91: Srikakulam Rural Circle | E91: Srikakulam Rural | F91: '193/2021' | G91: 468,471,420 r/w 34 IPC | H91: 44375 | I91: Jun | J91: 2021 | K91: Cheating | M91: White Collar Offences | N91: IPC | O91: Non-Grave | P91: 45756 | Q91: Yes | S91: UI | W91: Charge Sheet returned form court | X91: Charge Sheet returned form court | Y91: 45756 | Z91: Occurred on prior to 11.11.2020, at Sub- registere office, Srikakulam, reported on 28.06.2021 at 19.00 hours, by the complainant Dabbiru Sivakumar s/oDurgaprasadh, age 45 years, caste by sistikarnam, door no.49-53-7/6 f-6, 2nd follr, swathi apartment, seethamdara, BS layout, Visakapatnam, reported that, he was living by doing as sales manager in Aadhar housing faineance ltd. Visakhapatnam, his father namely Dabbiru Dhurgaprasada rao purchased a house site through Ajanta real estates and finance, Srikakulam in an extent of 220sq.yds covered in Sy.No 32/7,32/11( plot no 232), old Sy.No 214, in Vakalavalasa village, limits, Srikakulam Mandal, the said site was got registered in the name of father of complainant vide document no. 2630/1997 dtd. 10.11.1997, the accused joint register, SRO off | AA91: Total | AB91: =IF(S91="UI",DATEDIF(H91,TODAY(),"D"),"") -> 1936 | AC91: =IF(S91="UI",IF(AB91>365,"Above 1 Year",IF(AND(AB91<=365,AB91>180),"Above 6 Months",IF(AND(AB91<=180,AB91>90),"Above 3 Months",IF(AND(AB91<=90,AB91>60),"Above 60 Days",IF(AND(AB91<=60,AB91>45),"45 to 60 Days","Below 45 Days"))))),"") -> Above 1 Year | AD91: =IF(Y91<>"",DATEDIF(Y91,TODAY(),"D"),"") -> 555 | AE91: =IF(AD91<>"",IF(AD91>365,"Above 1 Year",IF(AND(AD91<=365,AD91>180),"Above 6 Months",IF(AND(AD91<=180,AD91>90),"Above 3 Months",IF(AND(AD91<=90,AD91>60),"Above 60 Days",IF(AND(AD91<=60,AD91>45),"45 to 60 Days","Below 45 Days"))))),"") -> Above 1 Year | AF91: D-6(White collar) | AG91: Srikakulam Rural,'193/2021' | AH91: =IF(X91="SC/PRC/CC No. Awaited","",AC91) -> Above 1 Year
A92: 91 | B92: Srikakulam Sub-Division | C92: Srikakulam Rural Circle | E92: Srikakulam Rural | F92: '194/2021' | G92: 420 IPC, 66-D ITA-2000-2008 | H92: 44376 | I92: Jun | J92: 2021 | K92: Cyber Crime offences | M92: Cyber Crime offences | N92: IPC | O92: Non-Grave | S92: UI | W92: For Suspect Verification | X92: For Suspect Verification | Z92: Occurred on 27.06.2021 at 17.25 hrs, at Door No. 6-37, plot no.26, Indiranagar colony, Srikakulam Mandal and reported on 29.06.2021 at 18.00 hrs by the complainant Jarjapu Shiva suryaprakasarao s/o Late Prathaparao, age 68 years, caste by nagavamsam, Indiranagar colony, Srikakulam Mandal, wherein the accused namely Ramkumar who is the user of mobile Ph.No.+917699718117 send a message to complainant phone number 94407594, i.e., Dear customer your BSNL SIM ekyc has been expired today please call customer number +917699718117 immediately, your BSNL SIM will be deactivate within 24 hours thank you, made the complainant to believe that he send one link and said that download Any desk from Google play store, the complainant done the same and open any desk and gave his debit card number and etc. | AA92: Total | AB92: =IF(S92="UI",DATEDIF(H92,TODAY(),"D"),"") -> 1935 | AC92: =IF(S92="UI",IF(AB92>365,"Above 1 Year",IF(AND(AB92<=365,AB92>180),"Above 6 Months",IF(AND(AB92<=180,AB92>90),"Above 3 Months",IF(AND(AB92<=90,AB92>60),"Above 60 Days",IF(AND(AB92<=60,AB92>45),"45 to 60 Days","Below 45 Days"))))),"") -> Above 1 Year | AD92: =IF(Y92<>"",DATEDIF(Y92,TODAY(),"D"),"") | AE92: =IF(AD92<>"",IF(AD92>365,"Above 1 Year",IF(AND(AD92<=365,AD92>180),"Above 6 Months",IF(AND(AD92<=180,AD92>90),"Above 3 Months",IF(AND(AD92<=90,AD92>60),"Above 60 Days",IF(AND(AD92<=60,AD92>45),"45 to 60 Days","Below 45 Days"))))),"") | AF92: Cyber Cell | AG92: Srikakulam Rural,'194/2021' | AH92: =IF(X92="SC/PRC/CC No. Awaited","",AC92) -> Above 1 Year
A93: 92 | B93: Srikakulam Sub-Division | C93: J.R.Puram Circle | E93: J.R.Puram | F93: '107/2021' | G93: Man Missing Person | H93: 44379 | I93: Jul | J93: 2021 | K93: Missing Cases | L93: Man Missing | M93: Missing Cases | N93: Missing | O93: Non-Grave | S93: UI | W93: Want of clues | X93: Want of clues | Z93: Occurred on 27.02.2021 at about 12:00 hours in Kovvada Matchalesam village, Ranasthalam mandal and reported on 02.07.2021 at 10:00 hours by the complainant Allipilli Ramulamma W/o Ramudu, age 39 years, Vadabalija by caste, Kovvada matchalesam village, Ranasthalam mandal. In which she stated that, her husband Allipilli Ramudu S/o Late Latchanna, age 45 years was suffering from mentally disordered and He would go out and come home again every two or three months. On 27.02.2021 he went to somewhere else and did not return back. All the family members of the complainant were trying to trace out the Allipilli Ramudu but in vain. Finally she came to the police station and presented a report for taking necessary action. | AA93: Total | AB93: =IF(S93="UI",DATEDIF(H93,TODAY(),"D"),"") -> 1932 | AC93: =IF(S93="UI",IF(AB93>365,"Above 1 Year",IF(AND(AB93<=365,AB93>180),"Above 6 Months",IF(AND(AB93<=180,AB93>90),"Above 3 Months",IF(AND(AB93<=90,AB93>60),"Above 60 Days",IF(AND(AB93<=60,AB93>45),"45 to 60 Days","Below 45 Days"))))),"") -> Above 1 Year | AD93: =IF(Y93<>"",DATEDIF(Y93,TODAY(),"D"),"") | AE93: =IF(AD93<>"",IF(AD93>365,"Above 1 Year",IF(AND(AD93<=365,AD93>180),"Above 6 Months",IF(AND(AD93<=180,AD93>90),"Above 3 Months",IF(AND(AD93<=90,AD93>60),"Above 60 Days",IF(AND(AD93<=60,AD93>45),"45 to 60 Days","Below 45 Days"))))),"") | AF93: D-4(Missing) | AG93: J.R.Puram,'107/2021' | AH93: =IF(X93="SC/PRC/CC No. Awaited","",AC93) -> Above 1 Year
A94: 93 | B94: Srikakulam Sub-Division | C94: Srikakulam Rural Circle | E94: Gara | F94: '120/2021' | G94: 324,323 r/w 34 IPC | H94: 44380 | I94: Jul | J94: 2021 | K94: Hurt - Simple | M94: Bodily Offiences | N94: IPC | O94: Non-Grave | P94: 44455 | S94: UI | W94: SC/PRC/CC No. Awaited | X94: SC/PRC/CC No. Awaited | Y94: 44455 | Z94: Occurred on 03.07.2021 at about 14.30 hrs at Amballavalasa village, Gara Mandal and reported on the same day at 21.15 hrs, in which the complainant Darmana Sandya D/o Thrinadharao, 30 yrs SC mala, Amballavalsa village, Gara Mandal reported that the accused Duvvarapu Appayyamma and along with 5 other beat her with stick and hands due to civil dispute regarding cultivation lands, in the result she sustained swelling injuries on left leg and waist. | AA94: Total | AB94: =IF(S94="UI",DATEDIF(H94,TODAY(),"D"),"") -> 1931 | AC94: =IF(S94="UI",IF(AB94>365,"Above 1 Year",IF(AND(AB94<=365,AB94>180),"Above 6 Months",IF(AND(AB94<=180,AB94>90),"Above 3 Months",IF(AND(AB94<=90,AB94>60),"Above 60 Days",IF(AND(AB94<=60,AB94>45),"45 to 60 Days","Below 45 Days"))))),"") -> Above 1 Year | AD94: =IF(Y94<>"",DATEDIF(Y94,TODAY(),"D"),"") -> 1856 | AE94: =IF(AD94<>"",IF(AD94>365,"Above 1 Year",IF(AND(AD94<=365,AD94>180),"Above 6 Months",IF(AND(AD94<=180,AD94>90),"Above 3 Months",IF(AND(AD94<=90,AD94>60),"Above 60 Days",IF(AND(AD94<=60,AD94>45),"45 to 60 Days","Below 45 Days"))))),"") -> Above 1 Year | AF94: D-6(Bodily) | AG94: Gara,'120/2021' | AH94: =IF(X94="SC/PRC/CC No. Awaited","",AC94)
A95: 94 | B95: Srikakulam Sub-Division | C95: Srikakulam Rural Circle | E95: Srikakulam I Town | F95: '95/2021' | G95: 420 IPC, 66-D ITA-2000-2008 | H95: 44381 | I95: Jul | J95: 2021 | K95: Cyber Crime offences | M95: Cyber Crime offences | N95: IPC | O95: Non-Grave | S95: UI | W95: Want of clues | X95: Want of clues | Z95: This is a case of cheating by using Information Technology. On 04.07.2021 at 18.30 Hrs., one Manda Venkata Ramanamurthy, S/o late Sayanarayana, Age 69 Yrs., Brahmin by Caste, MIG-247, Opposite to the Z.P., Srikakulam, the retired BSNL JTO lodged a report at Srikakulam 1-Town PS stating that on 30.06.2021 evening while he was trying to re-charge their TATA Sky TV Dis Channels by paying 135/- plan, it was not renewed though the amount was debited from his account No.11152380087 and when he searched through Google and called the customer care of Tata Sky authority No.18002084164 and when the person talked with him in Hindi language and advised him to re-charge first Rs.5/- and later re-charge Rs.200/- and when the plan will be renewed and while talking with him, call dropped and again another | AA95: Total | AB95: =IF(S95="UI",DATEDIF(H95,TODAY(),"D"),"") -> 1930 | AC95: =IF(S95="UI",IF(AB95>365,"Above 1 Year",IF(AND(AB95<=365,AB95>180),"Above 6 Months",IF(AND(AB95<=180,AB95>90),"Above 3 Months",IF(AND(AB95<=90,AB95>60),"Above 60 Days",IF(AND(AB95<=60,AB95>45),"45 to 60 Days","Below 45 Days"))))),"") -> Above 1 Year | AD95: =IF(Y95<>"",DATEDIF(Y95,TODAY(),"D"),"") | AE95: =IF(AD95<>"",IF(AD95>365,"Above 1 Year",IF(AND(AD95<=365,AD95>180),"Above 6 Months",IF(AND(AD95<=180,AD95>90),"Above 3 Months",IF(AND(AD95<=90,AD95>60),"Above 60 Days",IF(AND(AD95<=60,AD95>45),"45 to 60 Days","Below 45 Days"))))),"") | AF95: Cyber Cell | AG95: Srikakulam I Town,'95/2021' | AH95: =IF(X95="SC/PRC/CC No. Awaited","",AC95) -> Above 1 Year
A96: 95 | B96: Srikakulam Sub-Division | C96: Amadalavalasa Circle | E96: Amadalavalasa | F96: '118/2021' | G96: Man Missing Person | H96: 44385 | I96: Jul | J96: 2021 | K96: Missing Cases | L96: Man Missing | M96: Missing Cases | N96: Missing | O96: Non-Grave | S96: UI | W96: Want of clues | X96: Want of clues | Z96: Occurred on 25.06.2021 at about 18.00 hours at Vanjangi village of Amadalavalasa Mandal and reported on 08.07.2021 at 13.30 hours where in the complt. Yenda Gaddeyya, s/o lt. Rajarao, 71 yrs , Kalinga, Vanjangi Village, Amadalavalasa Mandal reported that his son Yenda Dasaradha, Age 35 years left from his house on 25.06.2021 at about 18.00 for going to Hyderabad, but he is not reached his house till today i.e., on 08.07.2021 and he where about not Known and he not answered any phone calls. So please cause enquiry and do need full (.) Description particulars of missing person :- Height-167 cm, complexion-Medium, wearing cloths- light blue colored jean pant and blue colored with white stripes shirt | AA96: Total | AB96: =IF(S96="UI",DATEDIF(H96,TODAY(),"D"),"") -> 1926 | AC96: =IF(S96="UI",IF(AB96>365,"Above 1 Year",IF(AND(AB96<=365,AB96>180),"Above 6 Months",IF(AND(AB96<=180,AB96>90),"Above 3 Months",IF(AND(AB96<=90,AB96>60),"Above 60 Days",IF(AND(AB96<=60,AB96>45),"45 to 60 Days","Below 45 Days"))))),"") -> Above 1 Year | AD96: =IF(Y96<>"",DATEDIF(Y96,TODAY(),"D"),"") | AE96: =IF(AD96<>"",IF(AD96>365,"Above 1 Year",IF(AND(AD96<=365,AD96>180),"Above 6 Months",IF(AND(AD96<=180,AD96>90),"Above 3 Months",IF(AND(AD96<=90,AD96>60),"Above 60 Days",IF(AND(AD96<=60,AD96>45),"45 to 60 Days","Below 45 Days"))))),"") | AF96: D-4(Missing) | AG96: Amadalavalasa,'118/2021' | AH96: =IF(X96="SC/PRC/CC No. Awaited","",AC96) -> Above 1 Year
A97: 96 | B97: Srikakulam Sub-Division | C97: Amadalavalasa Circle | E97: Ponduru | F97: '113/2021' | G97: 420 IPC | H97: 44388 | I97: Jul | J97: 2021 | K97: Cheating | M97: White Collar Offences | N97: IPC | O97: Non-Grave | S97: UI | W97: For Arrest of Accused | X97: For Arrest of Accused | Z97: This is a Case of Cheating occurred on prior to 11.07.2021 at 1800 hrs at Kartikeya Enterprises, Ponduru village & Mandal and reported at 1800 hours on 11.07.2021 wherein the accused Pappala Divakara rao, s/o Challayya, Laxmipeta village road, Ponduru who is the owner of Kartikeya Enterprises ( Iron & Cement shop) was collected Rs. 39,03,270/- as in advance for supply the Iron and Cement from the complainant Basava Visweswararao, s/o late Rajarao, aged 38 yrs, Telaga by caste, Official colony, Ponduru and others with a view to get wrongful gain and thereby cheated the complainant and others. | AA97: Total | AB97: =IF(S97="UI",DATEDIF(H97,TODAY(),"D"),"") -> 1923 | AC97: =IF(S97="UI",IF(AB97>365,"Above 1 Year",IF(AND(AB97<=365,AB97>180),"Above 6 Months",IF(AND(AB97<=180,AB97>90),"Above 3 Months",IF(AND(AB97<=90,AB97>60),"Above 60 Days",IF(AND(AB97<=60,AB97>45),"45 to 60 Days","Below 45 Days"))))),"") -> Above 1 Year | AD97: =IF(Y97<>"",DATEDIF(Y97,TODAY(),"D"),"") | AE97: =IF(AD97<>"",IF(AD97>365,"Above 1 Year",IF(AND(AD97<=365,AD97>180),"Above 6 Months",IF(AND(AD97<=180,AD97>90),"Above 3 Months",IF(AND(AD97<=90,AD97>60),"Above 60 Days",IF(AND(AD97<=60,AD97>45),"45 to 60 Days","Below 45 Days"))))),"") | AF97: D-6(White collar) | AG97: Ponduru,'113/2021' | AH97: =IF(X97="SC/PRC/CC No. Awaited","",AC97) -> Above 1 Year
A98: 97 | B98: Srikakulam Sub-Division | C98: Srikakulam Rural Circle | E98: Gara | F98: '135/2021' | G98: 420 IPC, 66-D ITA-2000-2008 | H98: 44403 | I98: Jul | J98: 2021 | K98: Cyber Crime offences | M98: Cyber Crime offences | N98: IPC | O98: Non-Grave | S98: UI | W98: For Suspect Verification | X98: For Suspect Verification | Z98: This is a case of cheating dishonestly inducing delivery of property by using Information Technology. Occurred on 23.07.2021 at 20.16 hrs at Vadapalem village, Gara Mandal and reported on 26.07.2021 at 20.30 hrs, wherein the complainant Kintali Venkata Suryanarayana Gupta s/o Venkataramana Murthy, 55 yrs, vysya by caste, SGT, Vadapalem village, Gara Mandal reported that he have a account in SBI branch, Gara vide A/c No. 11152323925 and his mobile number (9440001655) is linked to his bank account. On 23.07.2021 at 20.16 hrs he got a message from 0736300119 number. In this massage ¿Dear customer your SBI Bank KYC has been suspended please complete your KYC immediately click the link¿, and then he read the massage and he opened the link and he login his Net banking user Name and password an | AA98: Total | AB98: =IF(S98="UI",DATEDIF(H98,TODAY(),"D"),"") -> 1908 | AC98: =IF(S98="UI",IF(AB98>365,"Above 1 Year",IF(AND(AB98<=365,AB98>180),"Above 6 Months",IF(AND(AB98<=180,AB98>90),"Above 3 Months",IF(AND(AB98<=90,AB98>60),"Above 60 Days",IF(AND(AB98<=60,AB98>45),"45 to 60 Days","Below 45 Days"))))),"") -> Above 1 Year | AD98: =IF(Y98<>"",DATEDIF(Y98,TODAY(),"D"),"") | AE98: =IF(AD98<>"",IF(AD98>365,"Above 1 Year",IF(AND(AD98<=365,AD98>180),"Above 6 Months",IF(AND(AD98<=180,AD98>90),"Above 3 Months",IF(AND(AD98<=90,AD98>60),"Above 60 Days",IF(AND(AD98<=60,AD98>45),"45 to 60 Days","Below 45 Days"))))),"") | AF98: Cyber Cell | AG98: Gara,'135/2021' | AH98: =IF(X98="SC/PRC/CC No. Awaited","",AC98) -> Above 1 Year
A99: 98 | B99: Kasibugga Sub-Division | C99: 0 | E99: Kasibugga | F99: '294/2021' | G99: 354D,509 IPC, 67 ITA-2000-2008 | H99: 44405 | I99: Jul | J99: 2021 | K99: Outraging the modesty of women | M99: Crime Against Women | N99: IPC | O99: Non-Grave | S99: UI | W99: Want of clues | X99: Want of clues | Z99: Occurred prior to 28.07.2021 at 15:00 hours, at Palasa town and mandal and reported on the same day at 15:00 hours. By the complainant Pukkala Geetha w/o Laxmana rao, age 26 yrs, Vadabalija by caste, Vajrapukotturu Village and Mandal, Srikakulam district. Which is she reported that her husband had one face book through his ph no 7997889177 and his put some development works photos of Sir, Dr. Seediri Appalaraju, honorable minister of AP. some people not like that, where in the accuses 1) Labba Srinivasa rao, 2) Surya Praash jadapalli, 3) TDP Yadav, 4) Nayam kosam TDP, 5) Gopal Krishna were put through their face book account some abusing messages against her and family members. And registered a case in Cr.no 294-2021 354-D, 509 IPC and Sec 67 of information technology (amendment) a | AA99: Total | AB99: =IF(S99="UI",DATEDIF(H99,TODAY(),"D"),"") -> 1906 | AC99: =IF(S99="UI",IF(AB99>365,"Above 1 Year",IF(AND(AB99<=365,AB99>180),"Above 6 Months",IF(AND(AB99<=180,AB99>90),"Above 3 Months",IF(AND(AB99<=90,AB99>60),"Above 60 Days",IF(AND(AB99<=60,AB99>45),"45 to 60 Days","Below 45 Days"))))),"") -> Above 1 Year | AD99: =IF(Y99<>"",DATEDIF(Y99,TODAY(),"D"),"") | AE99: =IF(AD99<>"",IF(AD99>365,"Above 1 Year",IF(AND(AD99<=365,AD99>180),"Above 6 Months",IF(AND(AD99<=180,AD99>90),"Above 3 Months",IF(AND(AD99<=90,AD99>60),"Above 60 Days",IF(AND(AD99<=60,AD99>45),"45 to 60 Days","Below 45 Days"))))),"") | AF99: D-5(CAW) | AG99: Kasibugga,'294/2021' | AH99: =IF(X99="SC/PRC/CC No. Awaited","",AC99) -> Above 1 Year
A100: 99 | B100: Tekkali Sub-Division | C100: Pathapatnam Circle | E100: Meliaputti | F100: '81/2021' | G100: Man Missing Person | H100: 44407 | I100: Jul | J100: 2021 | K100: Missing Cases | L100: Man Missing | M100: Missing Cases | N100: Missing | O100: Non-Grave | S100: UI | W100: Want of clues | X100: Want of clues | Z100: Occurred on 26-07-2021 at 08.00 hrs, at Bus Stand of Juadupalli Village, Meliaputti Mandal and reported on 30.07.2021 at 10.15 Hrs. in which the complainant Padala Dilleswrarao S/o Chandrasekharao, 47 Yrs, kapu by caste, Peddapadmapuram village, Meliaputti Mandal reported that his Uncle by name Adhapakala Dharmarao S/o late Appanna, 75 Yrs, Jadupalli Village, Meliaputti Mandal, he left the house and proceeding to market and did not return back, searched surrounding villages could not get any useful information. Hence register the FIR Whereabouts are not known. Hence, he requested to take necessary action. | AA100: Total | AB100: =IF(S100="UI",DATEDIF(H100,TODAY(),"D"),"") -> 1904 | AC100: =IF(S100="UI",IF(AB100>365,"Above 1 Year",IF(AND(AB100<=365,AB100>180),"Above 6 Months",IF(AND(AB100<=180,AB100>90),"Above 3 Months",IF(AND(AB100<=90,AB100>60),"Above 60 Days",IF(AND(AB100<=60,AB100>45),"45 to 60 Days","Below 45 Days"))))),"") -> Above 1 Year | AD100: =IF(Y100<>"",DATEDIF(Y100,TODAY(),"D"),"") | AE100: =IF(AD100<>"",IF(AD100>365,"Above 1 Year",IF(AND(AD100<=365,AD100>180),"Above 6 Months",IF(AND(AD100<=180,AD100>90),"Above 3 Months",IF(AND(AD100<=90,AD100>60),"Above 60 Days",IF(AND(AD100<=60,AD100>45),"45 to 60 Days","Below 45 Days"))))),"") | AF100: D-4(Missing) | AG100: Meliaputti,'81/2021' | AH100: =IF(X100="SC/PRC/CC No. Awaited","",AC100) -> Above 1 Year
...

Sheet Actual UI Cases
A1: S.No. | B1: Police Station | C1: FIR NO | D1: ACTS & SEC | E1: FIR DT | F1: Month | G1: Year | H1: Crime Head | I1: Crime Classfication | J1: Act Type | K1: Date of charge | L1: Return of Charge Sheet | M1: Resubmit charge sheet | N1: Stage | O1: Court Disposal | P1: Date of Police Disposal | Q1: Type of Disposal | R1: Old Reason for UI | S1: Reason for UI | T1: Reason Wise Date | U1: Brief | V1: TOTAL | W1: No. of Days | X1: Time Line | Y1: Number Pending No of days | Z1: Time Line | AA1: Sheet Holder | AB1: Merge PS Names | AC1: Time Line Actual UI Cases
A2: 1 | B2: Hiramandalam | C2: '14/2016' | D2: 147, 148, 341, 342, 353, 323, 427, 435, r.w 149 IPC | E2: 42428 | F2: Feb | G2: 2016 | H2: Rioting (Unlawful Assembly) | I2: Bodily Offiences | J2: IPC | N2: UI | R2: For Arrest of Accused | S2: For Arrest of Accused | U2: Occurred on 28.02.2016 at 12.00 hrs at spiil way, spill channel, earth dam at BRR Vamsadhara Reservoir, Hiramandalam village and reported on the same day at 15.00 hrs by the complainant Sri J. Srinivasa Rao, Inspector of Police, Pathapatnam Circle, wherein the accused 1. Korada Narayana Rao, District Agricultural labour union president and 14 others and some other Rehabilitees came as unlaw ful assembly along with deadly weapons like Sticks and iron rods and obstructed the BRR Project works, surrounded, beat with hands the J.Ramarao, Tahsildar, Hiramandalam and fell down. While complaint his staff saved the Tahsildar, Hiramandalam from the hands accused. Then they damaged plastic chairs, set fire to tents. Also beat the Konari Simhachalam, while trying to stop. Hence issued report by gi | V2: Total | W2: =IF(N2="UI",DATEDIF(E2,TODAY(),"D"),"") -> 3883 | X2: =IF(N2="UI",IF(W2>365,"Above 1 Year",IF(AND(W2<=365,W2>180),"Above 6 Months",IF(AND(W2<=180,W2>90),"Above 3 Months",IF(AND(W2<=90,W2>60),"Above 60 Days",IF(AND(W2<=60,W2>45),"45 to 60 Days","Below 45 Days"))))),"") -> Above 1 Year | Y2: =IF(T2<>"",DATEDIF(T2,TODAY(),"D"),"") | Z2: =IF(Y2<>"",IF(Y2>365,"Above 1 Year",IF(AND(Y2<=365,Y2>180),"Above 6 Months",IF(AND(Y2<=180,Y2>90),"Above 3 Months",IF(AND(Y2<=90,Y2>60),"Above 60 Days",IF(AND(Y2<=60,Y2>45),"45 to 60 Days","Below 45 Days"))))),"") | AA2: D-6(Bodily) | AB2: Hiramandalam,'14/2016' | AC2: =IF(S2="SC/PRC/CC No. Awaited","",X2) -> Above 1 Year
A3: 2 | B3: Hiramandalam | C3: '54/2017' | D3: 148,147,353,506 r/w 149 IPC, 7 CLA-1932 | E3: 42957 | F3: Aug | G3: 2017 | H3: Rioting (Unlawful Assembly) | I3: Bodily Offiences | J3: IPC | N3: UI | R3: For Arrest of Accused | S3: For Arrest of Accused | U3: The Complainant Report Copy was Enclosed herewith Uploaded for the favour of Perusal. 1) Gavara Govinda Rao, s/o lt. Tellanna, 50 years, Kapu, Garlapadu village, Hiramandalam Mandal. 2) Madapana Ganapathi Rao S/o Laxminarayana, age 38 yrs, Kapu, Garlapadu village, Hiramandalam Mandal. 3) Agathamudi Jayamma, w/o Balanaidu, 50 yrs, Kapu, Garlapadu village, Hiramandalam Mandal. 4) Gedela laxmi, w/o lt. Gaddem Naidu, 30 yrs, Kapu, Garlapadu village, Hiramandalam Mandal. 5) Buri Krishnaveni, w/o Seshagiri, 30 years, Kapu, Garlapadu village,Hiramandalam Mandal. 6)Madapana Appa Rao, s/o Mukhalingam, 50 years, Kapu, Garlapadu village, Hiramandalam Mandal. 7) Vanjarapu. Rama Rao, s/o lt. Appanna, 65 years, Kapu, Garlapadu village, Hiramandalam Mandal. 8) Palli Jagannadha Rao, s/o La | V3: Total | W3: =IF(N3="UI",DATEDIF(E3,TODAY(),"D"),"") -> 3354 | X3: =IF(N3="UI",IF(W3>365,"Above 1 Year",IF(AND(W3<=365,W3>180),"Above 6 Months",IF(AND(W3<=180,W3>90),"Above 3 Months",IF(AND(W3<=90,W3>60),"Above 60 Days",IF(AND(W3<=60,W3>45),"45 to 60 Days","Below 45 Days"))))),"") -> Above 1 Year | Y3: =IF(T3<>"",DATEDIF(T3,TODAY(),"D"),"") | Z3: =IF(Y3<>"",IF(Y3>365,"Above 1 Year",IF(AND(Y3<=365,Y3>180),"Above 6 Months",IF(AND(Y3<=180,Y3>90),"Above 3 Months",IF(AND(Y3<=90,Y3>60),"Above 60 Days",IF(AND(Y3<=60,Y3>45),"45 to 60 Days","Below 45 Days"))))),"") | AA3: D-6(Bodily) | AB3: Hiramandalam,'54/2017' | AC3: =IF(S3="SC/PRC/CC No. Awaited","",X3) -> Above 1 Year
A4: 3 | B4: Hiramandalam | C4: '56/2017' | D4: 147, 148, 353, 506, 188 r.w 149 IPC & Sec.7 (1)(a) of Criminal Law Amendment Act-1932 | E4: 42963 | F4: Aug | G4: 2017 | H4: Rioting (Unlawful Assembly) | I4: Bodily Offiences | J4: IPC | N4: UI | R4: For Arrest of Accused | S4: For Arrest of Accused | U4: Occurred on 16.08.2017 at about 11.00 hrs and reported same day at 14.00 hrs by the Complainant Sri.M.Kali Prasad, Tahasildar & Mandal Executive Magistrate of Hiramandalam and stated that at Tulagam fields the Accused about 100 members of displaced villagers of Tulagam, Duggupuram and Padali Villagers were came with supported with Gorle Ram Sankar under along with rehabilitiees were came and taken them with deadly weapons and stowed sticks and raised slogans and told them stop the works of Vamsadhara Reservoir BRR Project and warned immediately stop the works and otherwise we attack workers and vehicles go back and they were obstructing the public servants their legitimate duties and then the complainant reported against the accused persons. | V4: Total | W4: =IF(N4="UI",DATEDIF(E4,TODAY(),"D"),"") -> 3348 | X4: =IF(N4="UI",IF(W4>365,"Above 1 Year",IF(AND(W4<=365,W4>180),"Above 6 Months",IF(AND(W4<=180,W4>90),"Above 3 Months",IF(AND(W4<=90,W4>60),"Above 60 Days",IF(AND(W4<=60,W4>45),"45 to 60 Days","Below 45 Days"))))),"") -> Above 1 Year | Y4: =IF(T4<>"",DATEDIF(T4,TODAY(),"D"),"") | Z4: =IF(Y4<>"",IF(Y4>365,"Above 1 Year",IF(AND(Y4<=365,Y4>180),"Above 6 Months",IF(AND(Y4<=180,Y4>90),"Above 3 Months",IF(AND(Y4<=90,Y4>60),"Above 60 Days",IF(AND(Y4<=60,Y4>45),"45 to 60 Days","Below 45 Days"))))),"") | AA4: D-6(Bodily) | AB4: Hiramandalam,'56/2017' | AC4: =IF(S4="SC/PRC/CC No. Awaited","",X4) -> Above 1 Year
A5: 4 | B5: Hiramandalam | C5: '58/2017' | D5: 147, 148, 341, 332, 353, 506, 188 r.w 149 IPC & Sec.7 (1) (a) Of Criminal Law Amendment Act-1932 | E5: 42963 | F5: Aug | G5: 2017 | H5: Rioting (Unlawful Assembly) | I5: Bodily Offiences | J5: IPC | N5: UI | R5: For Arrest of Accused | S5: For Arrest of Accused | U5: Occurred on 16-08-2017 at about 15.10 hrs and reported same day at 18.30 hrs by the Complainant Chamtula Rama Rao S/o.late Tatababu, age 34 yrs, Caste by Kapu, Kintali Village, Madugula Mandal of Visakhapatnam District and worked as Sub-inspector of Police, Laveru Police Station and doing duty at Hiramandalam Police Station limits and Duggupuram to Padali villages beside fields and the Complainant protect the workers of BRR Vamsadhar project mud works in the same time the rehabilitates of Duggpuram and Padali Villagers and came and with stone, deadly weapons and stowed sticks and tried to attacked the Public servants of Police, while they were obstructing the legitimate duties of them and the complainant lodges a report against the accused person of Lothugedda Sundaranarayana and others 46 | V5: Total | W5: =IF(N5="UI",DATEDIF(E5,TODAY(),"D"),"") -> 3348 | X5: =IF(N5="UI",IF(W5>365,"Above 1 Year",IF(AND(W5<=365,W5>180),"Above 6 Months",IF(AND(W5<=180,W5>90),"Above 3 Months",IF(AND(W5<=90,W5>60),"Above 60 Days",IF(AND(W5<=60,W5>45),"45 to 60 Days","Below 45 Days"))))),"") -> Above 1 Year | Y5: =IF(T5<>"",DATEDIF(T5,TODAY(),"D"),"") | Z5: =IF(Y5<>"",IF(Y5>365,"Above 1 Year",IF(AND(Y5<=365,Y5>180),"Above 6 Months",IF(AND(Y5<=180,Y5>90),"Above 3 Months",IF(AND(Y5<=90,Y5>60),"Above 60 Days",IF(AND(Y5<=60,Y5>45),"45 to 60 Days","Below 45 Days"))))),"") | AA5: D-6(Bodily) | AB5: Hiramandalam,'58/2017' | AC5: =IF(S5="SC/PRC/CC No. Awaited","",X5) -> Above 1 Year
A6: 5 | B6: Etcherla | C6: '173/2017' | D6: Man Missing Person | E6: 43000 | F6: Sep | G6: 2017 | H6: Missing Cases | I6: Missing Cases | J6: Missing | N6: UI | R6: Pending records from other depts., | S6: Pending records from other depts., | T6: 46030 | U6: OCCURRED ON 18..09..2017 AT ABOUT 09.00 HOURS AT ALLINAGRAM VILLAGE, ETCHERLA MANDAL, SRIKAKULAM DISTRICT AND REPORTD BY THE COMPLAINANT KILLO CHITTIBABU S/O SHONNU, 25 YEARS, ST GOWDA BY CASTE,MARRIPALEM VILLAGE, PADERU MANDAL, VISAKHAPATNAM DISTRICT IN WHICH IT IS INFORMED THAT ONE KILLO LAKSHMANARAO S/O ADDANNA, 36 YEARS, ST GOWDA BY CASTE, GONDURU VILLAGE, DOKULURU POST, PADEROO MANDAL WHO IS BROTHER OF THE COMPLAINANT AND 4 OTHER ARE CAME TO COOLI WORKS ON 15..08..2017 BHAGIRADHA BORU WELLS WORKS OF DUBBAKULA RAKESH NATIVE OF MURAPAKA VILLAGE, LAVERU MANDAL, SRIKAKULAM DISTRICT.IN THIS REGUARD THEY ARE WORKING BORU WELL WORKS AT ALLINAGARAM VILLAGE FROM 2 DAY WHILE ON 18..09..2017 AT 09.00 HOURS KILLO LAXMANA RAO CON’T DO THIS WORK I AM GOING TO MY HOUSE AND ASKING SOME MONEY FOR C | V6: Total | W6: =IF(N6="UI",DATEDIF(E6,TODAY(),"D"),"") -> 3311 | X6: =IF(N6="UI",IF(W6>365,"Above 1 Year",IF(AND(W6<=365,W6>180),"Above 6 Months",IF(AND(W6<=180,W6>90),"Above 3 Months",IF(AND(W6<=90,W6>60),"Above 60 Days",IF(AND(W6<=60,W6>45),"45 to 60 Days","Below 45 Days"))))),"") -> Above 1 Year | Y6: =IF(T6<>"",DATEDIF(T6,TODAY(),"D"),"") -> 281 | Z6: =IF(Y6<>"",IF(Y6>365,"Above 1 Year",IF(AND(Y6<=365,Y6>180),"Above 6 Months",IF(AND(Y6<=180,Y6>90),"Above 3 Months",IF(AND(Y6<=90,Y6>60),"Above 60 Days",IF(AND(Y6<=60,Y6>45),"45 to 60 Days","Below 45 Days"))))),"") -> Above 6 Months | AA6: D-4(Missing) | AB6: Etcherla,'173/2017' | AC6: =IF(S6="SC/PRC/CC No. Awaited","",X6) -> Above 1 Year
A7: 6 | B7: Srikakulam I Town | C7: '9/2019' | D7: 420 IPC, 66-C,66-D ITA-2000-2008 | E7: 43483 | F7: Jan | G7: 2019 | H7: Cyber Crime offences | I7: Cyber Crime offences | J7: IPC | N7: UI | R7: Want of clues | S7: Want of clues | U7: This is a case of cheating by personation by means of electronic device that occurred on 17.01.2019 at 1230 hours at State Bank of India, Main Branch, Srikakulam town and reported belatedly on 18.01.2019 at 1800 hours by the complainant Dusi Surya Prakash,S/o. Late Sundara Ramarao, age 63 years, Brhmin by caste, Door No. 1-41-26, Bharathi nagar, Hospital Road, Balaga, Srikakulam town is retired SBI Manager, Srikakulam that on 17.01.2019 at 1230 hours, some unknown caller Santhosh Sharma made a call from SIM No. 8789129706 to his SIM No. 9440116227 ATM Verification asking for his Account No.10718089866,OTP and Personal deatils and unfortunately without knowing he provide all the required details un known caller asking me which includes OTP also. on the pretext that his account was in troubl | V7: Total | W7: =IF(N7="UI",DATEDIF(E7,TODAY(),"D"),"") -> 2828 | X7: =IF(N7="UI",IF(W7>365,"Above 1 Year",IF(AND(W7<=365,W7>180),"Above 6 Months",IF(AND(W7<=180,W7>90),"Above 3 Months",IF(AND(W7<=90,W7>60),"Above 60 Days",IF(AND(W7<=60,W7>45),"45 to 60 Days","Below 45 Days"))))),"") -> Above 1 Year | Y7: =IF(T7<>"",DATEDIF(T7,TODAY(),"D"),"") | Z7: =IF(Y7<>"",IF(Y7>365,"Above 1 Year",IF(AND(Y7<=365,Y7>180),"Above 6 Months",IF(AND(Y7<=180,Y7>90),"Above 3 Months",IF(AND(Y7<=90,Y7>60),"Above 60 Days",IF(AND(Y7<=60,Y7>45),"45 to 60 Days","Below 45 Days"))))),"") | AA7: Cyber Cell | AB7: Srikakulam I Town,'9/2019' | AC7: =IF(S7="SC/PRC/CC No. Awaited","",X7) -> Above 1 Year
A8: 7 | B8: Srikakulam Rural | C8: '20/2019' | D8: 380,302 IPC | E8: 43503 | F8: Feb | G8: 2019 | H8: Murder for gain | I8: Property Offences | J8: IPC | N8: UI | R8: For Arrest of Accused | S8: For Arrest of Accused | U8: Occurred on 07.02.19 in between 09.00 Hrs to 17.30 Hrs at Plot No S2/7-28, Viziaynagar Colony, Bondhilipuram, Chapuram Panchayat Srikakulam Rural Mandal and reported on the same day at 22.00 Hrs where in the complaint Abdhul Zilani S/o Abdhul Kuddhus, Age 38 Yrs., Caste by Muslium, Plot No S2/7-28, Viziaynagar Colony, Bondhilipuram, Chapuram Panchayat Srikakulam Rural Mandal reported that he is living by doing “Prince Foot Wear” business at Srikakulam , and he is residing at above said address along with his two sons by names Jafar 16 yrs , Nishan 13 Yrs, his wife by name Abdhul Mehur Nisha-35 Yrs and his mother Jhorona Bhai 67 Yrs. On 07.02.19 at 09.00 Hrs he went to Rajam and Ranasthalam Villages for Weekly collections, and at 17.30 Hrs he received a phone call from his elder son that hi | V8: Total | W8: =IF(N8="UI",DATEDIF(E8,TODAY(),"D"),"") -> 2808 | X8: =IF(N8="UI",IF(W8>365,"Above 1 Year",IF(AND(W8<=365,W8>180),"Above 6 Months",IF(AND(W8<=180,W8>90),"Above 3 Months",IF(AND(W8<=90,W8>60),"Above 60 Days",IF(AND(W8<=60,W8>45),"45 to 60 Days","Below 45 Days"))))),"") -> Above 1 Year | Y8: =IF(T8<>"",DATEDIF(T8,TODAY(),"D"),"") | Z8: =IF(Y8<>"",IF(Y8>365,"Above 1 Year",IF(AND(Y8<=365,Y8>180),"Above 6 Months",IF(AND(Y8<=180,Y8>90),"Above 3 Months",IF(AND(Y8<=90,Y8>60),"Above 60 Days",IF(AND(Y8<=60,Y8>45),"45 to 60 Days","Below 45 Days"))))),"") | AA8: D-3 & D-5 (CAW) | AB8: Srikakulam Rural,'20/2019' | AC8: =IF(S8="SC/PRC/CC No. Awaited","",X8) -> Above 1 Year
A9: 8 | B9: Srikakulam II Town | C9: '13/2019' | D9: 420 IPC, 66-C,66-D ITA-2000-2008 | E9: 43506 | F9: Feb | G9: 2019 | H9: Cyber Crime offences | I9: Cyber Crime offences | J9: IPC | N9: UI | R9: For Suspect Verification | S9: Want of clues | U9: This is a case of cheating coupled with using pass word of another person and also cheating duly using computer resource occurred on 09.02.2019 at 13.45 hrs at Rainbow hospital, Srikakulam town and reported on 10.02.2019 at 11.00 hrs, wherein the complt. Palla Suribabu s/o Yerrayya, 33 yrs, Yadav by caste, Byri vill, Srikakulam rural mandalam reported that some unknown person had cheated him and withdrew the amounts spells-wise to a total of Rs. 1,10,900/- through computer resource by using his ATM card, PIN and OTP number. | V9: Total | W9: =IF(N9="UI",DATEDIF(E9,TODAY(),"D"),"") -> 2805 | X9: =IF(N9="UI",IF(W9>365,"Above 1 Year",IF(AND(W9<=365,W9>180),"Above 6 Months",IF(AND(W9<=180,W9>90),"Above 3 Months",IF(AND(W9<=90,W9>60),"Above 60 Days",IF(AND(W9<=60,W9>45),"45 to 60 Days","Below 45 Days"))))),"") -> Above 1 Year | Y9: =IF(T9<>"",DATEDIF(T9,TODAY(),"D"),"") | Z9: =IF(Y9<>"",IF(Y9>365,"Above 1 Year",IF(AND(Y9<=365,Y9>180),"Above 6 Months",IF(AND(Y9<=180,Y9>90),"Above 3 Months",IF(AND(Y9<=90,Y9>60),"Above 60 Days",IF(AND(Y9<=60,Y9>45),"45 to 60 Days","Below 45 Days"))))),"") | AA9: Cyber Cell | AB9: Srikakulam II Town,'13/2019' | AC9: =IF(S9="SC/PRC/CC No. Awaited","",X9) -> Above 1 Year
A10: 9 | B10: Sompeta | C10: '24/2019' | D10: 174 CrPC | E10: 43549 | F10: Mar | G10: 2019 | H10: 174 CrPC | I10: 174 CrPC | J10: 174 CrPC | N10: UI | R10: Pending records from other depts., | S10: Pending records from other depts., | T10: 45432 | U10: on 25-03-2019 at 10-00 hrs the complainant Palavalasa Kalyani, w/o Sriramurty, age 28yrs, caste by Kalinga, working as process server, VI Additional Dist. Judge, Sompeta, residents of Geetha cable street, Sompeta lodged a written report stating that she is working as process server, VI Additional Dist. Judge, Sompeta since 2015. Every day morning at 08-00 hrs she attending Banglow duty at VI Additional Dist. Judge Madam House. As usually, today, i.e. on 25-3-2019 morning at about 08-00 hours she attending Bunglow duty i.e. the house of Judge Madam situated at BC colony, Kothapeta street belongs to Vysyaraju Gopi Kiran. She along with sweeper Urmila knocked the doors and pressed the calling bell. But no response. Due to suspicion, she informed their court staff Baburao, Sur | V10: Total | W10: =IF(N10="UI",DATEDIF(E10,TODAY(),"D"),"") -> 2762 | X10: =IF(N10="UI",IF(W10>365,"Above 1 Year",IF(AND(W10<=365,W10>180),"Above 6 Months",IF(AND(W10<=180,W10>90),"Above 3 Months",IF(AND(W10<=90,W10>60),"Above 60 Days",IF(AND(W10<=60,W10>45),"45 to 60 Days","Below 45 Days"))))),"") -> Above 1 Year | Y10: =IF(T10<>"",DATEDIF(T10,TODAY(),"D"),"") -> 879 | Z10: =IF(Y10<>"",IF(Y10>365,"Above 1 Year",IF(AND(Y10<=365,Y10>180),"Above 6 Months",IF(AND(Y10<=180,Y10>90),"Above 3 Months",IF(AND(Y10<=90,Y10>60),"Above 60 Days",IF(AND(Y10<=60,Y10>45),"45 to 60 Days","Below 45 Days"))))),"") -> Above 1 Year | AA10: D-4(174 CrPC) | AB10: Sompeta,'24/2019' | AC10: =IF(S10="SC/PRC/CC No. Awaited","",X10) -> Above 1 Year
A11: 10 | B11: Polaki | C11: '88/2019' | D11: Man Missing Person | E11: 43558 | F11: Apr | G11: 2019 | H11: Missing Cases | I11: Missing Cases | J11: Missing | N11: UI | R11: Want of clues | S11: Want of clues | U11: This is a case of Man missing, occurred on 25.03.2019 at 11:00hrs in renku Jaganadhapeta village,Polaki Mandal and reported on 03.04.2019 at 15.00hrs by the complainant Tulugu Saradha W/o Suryanarayana ,Age 30 yrs,runkujaganadhapuram village of Polaki Mandal reported that on 25-03-2019 at about 1100 hrs her father by name Yarabati Appalaramayya S/o lt Chinnavadu, Age 68 yrs, kapu by caste, Runkujaganadhapuram village left from her home for going to Narasannapeta to watch TDP MLA nomination and didn’t return back still now, Complainant, her family members and villagers causes enquiries about missing person in and around the village and surrounding villages, but could not get useful information | V11: Total | W11: =IF(N11="UI",DATEDIF(E11,TODAY(),"D"),"") -> 2753 | X11: =IF(N11="UI",IF(W11>365,"Above 1 Year",IF(AND(W11<=365,W11>180),"Above 6 Months",IF(AND(W11<=180,W11>90),"Above 3 Months",IF(AND(W11<=90,W11>60),"Above 60 Days",IF(AND(W11<=60,W11>45),"45 to 60 Days","Below 45 Days"))))),"") -> Above 1 Year | Y11: =IF(T11<>"",DATEDIF(T11,TODAY(),"D"),"") | Z11: =IF(Y11<>"",IF(Y11>365,"Above 1 Year",IF(AND(Y11<=365,Y11>180),"Above 6 Months",IF(AND(Y11<=180,Y11>90),"Above 3 Months",IF(AND(Y11<=90,Y11>60),"Above 60 Days",IF(AND(Y11<=60,Y11>45),"45 to 60 Days","Below 45 Days"))))),"") | AA11: D-4(Missing) | AB11: Polaki,'88/2019' | AC11: =IF(S11="SC/PRC/CC No. Awaited","",X11) -> Above 1 Year
A12: 11 | B12: Srikakulam II Town | C12: '67/2019' | D12: 420 IPC, 66-C,66-D ITA-2000-2008 | E12: 43575 | F12: Apr | G12: 2019 | H12: Cyber Crime offences | I12: Cyber Crime offences | J12: IPC | N12: UI | R12: For Suspect Verification | S12: Want of clues | U12: This is a case of cheating by personation by using any communication device or computer resource that occurred Prior to 03.11.2018 at Pondara street, Kalinga hights, Balaga, Srikakulam town and reported on 20.04.2019 at 18.30 hours. where the complainant Dupam Kishor, s/o Janakeswara rao, 38 yrs, Vatarnary department, r/o Pondara street, Kalinga hights, Balaga, Srikakulam town reported that on 24.09.2018 at 09.00 hrs the accused Venkatesh informed the complainant over phone No. 8790996638 through his Nos.80175779512, 9674718043 that he has won lottery for Rs. 12,80,000 and asked to pay an amount of Rs. 12,800/- in Bank and issued an account No. 37924172660. Believing the words, he deposited the said amount. On 12.10.2018 he received phone call to Sonia Mehatha asked to pay an amount of Rs | V12: Total | W12: =IF(N12="UI",DATEDIF(E12,TODAY(),"D"),"") -> 2736 | X12: =IF(N12="UI",IF(W12>365,"Above 1 Year",IF(AND(W12<=365,W12>180),"Above 6 Months",IF(AND(W12<=180,W12>90),"Above 3 Months",IF(AND(W12<=90,W12>60),"Above 60 Days",IF(AND(W12<=60,W12>45),"45 to 60 Days","Below 45 Days"))))),"") -> Above 1 Year | Y12: =IF(T12<>"",DATEDIF(T12,TODAY(),"D"),"") | Z12: =IF(Y12<>"",IF(Y12>365,"Above 1 Year",IF(AND(Y12<=365,Y12>180),"Above 6 Months",IF(AND(Y12<=180,Y12>90),"Above 3 Months",IF(AND(Y12<=90,Y12>60),"Above 60 Days",IF(AND(Y12<=60,Y12>45),"45 to 60 Days","Below 45 Days"))))),"") | AA12: Cyber Cell | AB12: Srikakulam II Town,'67/2019' | AC12: =IF(S12="SC/PRC/CC No. Awaited","",X12) -> Above 1 Year
A13: 12 | B13: Srikakulam II Town | C13: '70/2019' | D13: 66-C,66-D ITA-2000-2008 | E13: 43578 | F13: Apr | G13: 2019 | H13: Cyber Crime offences | I13: Cyber Crime offences | J13: IPC | N13: UI | R13: For Suspect Verification | S13: Want of clues | U13: Occurred on prior to 09.04.2019 at Gandi Nagar, Illisipuram junction, Srikakulam town and reported on 23.04.2019 at 10.30 hrs, where in the Complainant Mudu Ramji Naik S/o late Sriramulu, age 35 years, S.T. (Lambadi) by caste, Illisipuram Srikakulam reported that he is working as Asst. Professor at Ambedkar University. He has an Account in Andhra Bank with No.01810100003013 and its credit Card No.4373782067435002. On 04-04-2019 at 05.15 PM, he received a phone call from an unknown person with SIM No.9169764561 and collected his credit card number by deceiving that he would provide SBI Credit card in addition to the Andhra Bank Credit Card. After some time, he asked OTP numbers which are received to his mobile by that time by informing that the OTP numbers are required to make cross check. | V13: Total | W13: =IF(N13="UI",DATEDIF(E13,TODAY(),"D"),"") -> 2733 | X13: =IF(N13="UI",IF(W13>365,"Above 1 Year",IF(AND(W13<=365,W13>180),"Above 6 Months",IF(AND(W13<=180,W13>90),"Above 3 Months",IF(AND(W13<=90,W13>60),"Above 60 Days",IF(AND(W13<=60,W13>45),"45 to 60 Days","Below 45 Days"))))),"") -> Above 1 Year | Y13: =IF(T13<>"",DATEDIF(T13,TODAY(),"D"),"") | Z13: =IF(Y13<>"",IF(Y13>365,"Above 1 Year",IF(AND(Y13<=365,Y13>180),"Above 6 Months",IF(AND(Y13<=180,Y13>90),"Above 3 Months",IF(AND(Y13<=90,Y13>60),"Above 60 Days",IF(AND(Y13<=60,Y13>45),"45 to 60 Days","Below 45 Days"))))),"") | AA13: Cyber Cell | AB13: Srikakulam II Town,'70/2019' | AC13: =IF(S13="SC/PRC/CC No. Awaited","",X13) -> Above 1 Year
